Workbook

Sheet Summary
A1: Lumhe Instagram campaign: blog watercolour images
A2: 200 posts, two per day, from 7 Oct 2026 to 14 Jan 2027. Every Indian and US/UK festival in the window has a post about 10 days before, a reminder 1-2 days before (same images, different copy) and a greeting on the day. All visuals are raw watercolour illustrations with no title text on them. Apart from the intentional festival reminder that reuses its first post's images, no image is used twice.
A4: By format
A5: Single | B5: =COUNTIF(Calendar!$F$2:$F$201,"Single") -> 103
A6: Carousel | B6: =COUNTIF(Calendar!$F$2:$F$201,"Carousel") -> 69
A7: Reel | B7: =COUNTIF(Calendar!$F$2:$F$201,"Reel") -> 28
A8: Total posts | B8: =SUM(B5:B7) -> 200
A10: By market × format | B10: Single | C10: Carousel | D10: Reel | E10: Total
A11: India | B11: =COUNTIFS(Calendar!$G$2:$G$201,"India",Calendar!$F$2:$F$201,"Single") -> 32 | C11: =COUNTIFS(Calendar!$G$2:$G$201,"India",Calendar!$F$2:$F$201,"Carousel") -> 31 | D11: =COUNTIFS(Calendar!$G$2:$G$201,"India",Calendar!$F$2:$F$201,"Reel") -> 13 | E11: =SUM(B11:D11) -> 76
A12: USA | B12: =COUNTIFS(Calendar!$G$2:$G$201,"USA",Calendar!$F$2:$F$201,"Single") -> 32 | C12: =COUNTIFS(Calendar!$G$2:$G$201,"USA",Calendar!$F$2:$F$201,"Carousel") -> 19 | D12: =COUNTIFS(Calendar!$G$2:$G$201,"USA",Calendar!$F$2:$F$201,"Reel") -> 6 | E12: =SUM(B12:D12) -> 57
A13: UK | B13: =COUNTIFS(Calendar!$G$2:$G$201,"UK",Calendar!$F$2:$F$201,"Single") -> 32 | C13: =COUNTIFS(Calendar!$G$2:$G$201,"UK",Calendar!$F$2:$F$201,"Carousel") -> 10 | D13: =COUNTIFS(Calendar!$G$2:$G$201,"UK",Calendar!$F$2:$F$201,"Reel") -> 2 | E13: =SUM(B13:D13) -> 44
A14: Global | B14: =COUNTIFS(Calendar!$G$2:$G$201,"Global",Calendar!$F$2:$F$201,"Single") -> 7 | C14: =COUNTIFS(Calendar!$G$2:$G$201,"Global",Calendar!$F$2:$F$201,"Carousel") -> 9 | D14: =COUNTIFS(Calendar!$G$2:$G$201,"Global",Calendar!$F$2:$F$201,"Reel") -> 7 | E14: =SUM(B14:D14) -> 23
A16: Workflow status
A17: Ready | B17: =COUNTIF(Calendar!$V$2:$V$201,"Ready") -> 200
A18: Scheduled | B18: =COUNTIF(Calendar!$V$2:$V$201,"Scheduled") -> 0
A19: Posted | B19: =COUNTIF(Calendar!$V$2:$V$201,"Posted") -> 0
A20: On hold | B20: =COUNTIF(Calendar!$V$2:$V$201,"On hold") -> 0
A22: Images
A23: Watercolour images logged | B23: =COUNTA('Image usage log'!A2:A264) -> 263
A24: Used in at least one post | B24: =COUNTIF('Image usage log'!D2:D264,"Used") -> 245
A25: Skipped as duplicate artwork | B25: =COUNTIF('Image usage log'!D2:D264,"Skipped (duplicate)") -> 18
A27: How to use
A28: • Calendar tab: one row per post, with the caption, hashtags, first comment, alt text and file names. Change the Status column as you go (Ready, Scheduled, Posted, On hold).
A29: • Asset folder: every post has its own folder under Posts/, and the folders are numbered in posting order. Each folder holds the ready-to-upload JPG or MP4 files plus caption.txt.
A30: • Reels have no audio. Add a trending sound in Instagram using the "Audio suggestion" column. reel_cover.jpg is the suggested cover frame.
A31: • Post times: two slots a day, set by market. India 12:30 and 19:00 IST, US 19:30 and 21:30 IST (9:00 and 11:00 AM ET), UK 16:30 and 23:00 IST, Global 13:00 and 20:30 IST. Times assume one shared Instagram account.
A32: • Festival dates: see the Festival coverage tab. Please check Navratri, Dussehra, Karva Chauth, Dhanteras, Diwali, Chhath, Dev Uthani Ekadashi, Guru Nanak Jayanti, Lohri and Sankranti against your panchang, and Thanksgiving, Hanukkah and Bonfire Night against a calendar, before scheduling.
A33: • Lumhe facts in the copy come from the Lumhe feature pages: per-function RSVP, Moments, Digital Lifafa (India only, by UPI) and Upload Any Invite. No statistics or testimonials were invented.

Sheet Calendar
A1: # | B1: Date | C1: Day | D1: Time (IST) | E1: Target local time | F1: Format | G1: Market | H1: Post ID | I1: Title | J1: On-image hook | K1: Caption | L1: Hashtags | M1: First comment | N1: Alt text | O1: CTA on visual | P1: Slides / length | Q1: Audio suggestion | R1: Images used | S1: Source blog(s) | T1: Asset folder | U1: Files | V1: Status | W1: Posted link / notes | X1: Festival | Y1: Festival date | Z1: Role | AA1: Linked post (same images)
A2: 1 | B2: 46302 | C2: =TEXT(B2,"ddd") -> Wed | D2: 12:30 | E2: IST | F2: Single | G2: India | H2: E03 | I2: Telugu shubhalekha closing line | J2: Sakutumba saparivaara sametamga vichchesi, vadhuvarulanu aashirvadinchandi. | K2: Turmeric on the corners, and one line elders always read twice. A Telugu pelli patrika (శుభలేఖ) usually opens with Sri Ganeshaya Namah, names both families, gives the muhurtham, and closes by asking guests to come with family and bless the couple. That closing line is the heart of it. Sending to cousins abroad too? Keep the Telugu line, then add a simple English one below it so everyone feels invited. 💛 Upload your shubhalekha to Lumhe and share one link for Pellikuthuru, the muhurtham and the reception. Link in bio. | L2: #Lumhe #TeluguWedding #Shubhalekha #PelliPatrika #TeluguPelli #TeluguWeddingCard #Muhurtham #HyderabadWeddings #VizagWeddings #SouthIndianWedding #WeddingCardIdeas #TeluguAmmayi | M2: Does your family still put pasupu and kumkum on the card corners? Tell us below. | N2: Watercolour of a turmeric-dabbed wedding card on a brass plate with yellow talambralu rice, mango leaves and marigolds. Text: the Telugu closing line 'Sakutumba saparivaara sametamga vichchesi, vadhuvarulanu aashirvadinchandi' with its English meaning. | O2: Upload your shubhalekha | P2: 1 image · 4:5 | R2: EV-E03_A | S2: New watercolour, blog topic: telugu | T2: Posts/001_2026-10-07_Single_E03_Telugu-shubhalekha-closing-line | U2: post.jpg | V2: Ready | Z2: Evergreen
A3: 2 | B3: 46302 | C3: =TEXT(B3,"ddd") -> Wed | D3: 19:00 | E3: IST | F3: Carousel | G3: India | H3: F01 | I3: Navratri hosting and invite guide | J3: Nine nights, one invite link | K3: Navratri starts Sunday. Your society Garba planning starts now. 💃 Ten days is enough time to do this without panic: send the invite, lock the dhol, count the dandiya sticks and know how many kanyas are coming for Ashtami. Swipe for: • Garba night invite wording you can copy • A Kanya Pujan message for parents • The host checklist to book this week • A simple way to use the nine colours Hosting more than one night? Create one Lumhe event and add each night as its own function. Guests RSVP only for the nights they can make, you get a live headcount, and the photos stay together in Moments instead of fifty WhatsApp chats. Save this, then create your Navratri invite free. Link in bio. | L3: #Lumhe #Navratri2026 #SharadNavratri #Garba #DandiyaNight #GarbaNight #NavratriVibes #KanyaPujan #ChaniyaCholi #SocietyGarba #NavratriCelebration #FestiveSeason | M3: Team Garba or team Dandiya? Tell us how your society celebrates. | N3: Watercolour carousel: a couple in mirror-work outfits twirling with dandiya sticks beside a lamp-lit garbo pot and marigolds, and a close-up of a puja thali with a diya, coconut and dandiya sticks. Slides share Navratri invite wording and a host checklist. | O3: Create your invite free | P3: 6 slides | R3: PAIR-NAV_A, PAIR-NAV_B | S3: New watercolour, blog topic: festival | New watercolour, blog topic: festival | T3: Posts/002_2026-10-07_Carousel_F01_Navratri-hosting-and-invite-guide | U3: slide_01.jpg, slide_02.jpg, slide_03.jpg, slide_04.jpg, slide_05.jpg, slide_06.jpg | V3: Ready | X3: Sharad Navratri | Y3: 2026-10-11 | Z3: 10 days before | AA3: F02
A4: 3 | B4: 46303 | C4: =TEXT(B4,"ddd") -> Thu | D4: 12:30 | E4: IST | F4: Carousel | G4: India | H4: E01 | I4: Bengali biyer card wording guide | J4: Bengali wording, from Prajapataye to Bou Bhaat | K4: Prajapati on the card, and a guest list longer than the menu. A Bengali biyer card does a lot of work. It comes from the parents, names every ceremony from Ashirbaad to Bou Bhaat, and speaks to elders and friends in slightly different voices. Swipe for: • What to put at the very top • A classic Bengali closing line, with meaning • An English version from the bride's parents • Why Bou Bhaat often needs its own invite Tip: print one bilingual card for the family, then send the same card digitally to everyone who lives far away. Save this for the evening Mama, Mashi and Baba sit down to finalise the card. Then upload it to Lumhe and share one link with a separate RSVP for each function. Link in bio. | L4: #Lumhe #BengaliWedding #BiyerCard #BengaliBride #BongWedding #ShubhoBibaho #BouBhaat #GayeHolud #KolkataWeddings #WeddingCardWording #BengaliCulture #WeddingInvitationIndia #DigitalWeddingCard | M4: Which ceremony is your favourite: Gaye Holud, Shubho Drishti or Bou Bhaat? | N4: Watercolour carousel: a Bengali bride in a red Banarasi and shola crown holding betel leaves before her face, and a red-and-white card with a butterfly motif beside conch-shell bangles and marigolds. Slides share Bengali and English invitation wording. | O4: Share your biyer card | P4: 6 slides | R4: EV-E01_A, EV-E01_B | S4: New watercolour, blog topic: bengali-wedding-invitation | New watercolour, blog topic: bengali-wedding-invitation | T4: Posts/003_2026-10-08_Carousel_E01_Bengali-biyer-card-wording-guide | U4: slide_01.jpg, slide_02.jpg, slide_03.jpg, slide_04.jpg, slide_05.jpg, slide_06.jpg | V4: Ready | Z4: Evergreen
A5: 4 | B5: 46303 | C5: =TEXT(B5,"ddd") -> Thu | D5: 20:30 | E5: IST | F5: Single | G5: Global | H5: S35 | I5: Poll: venue first or guest list | J5: Venue first, or guest list first? | K5: The great planning debate, settled by you. Team Venue says: book the mandap or the arch you love, then build the list around its capacity. Team Guest List says: know your numbers first, or you'll fall for a place that fits half your family. Both work. Whichever you pick, the invitation comes next, and that's where Lumhe helps: one link for your invite, RSVPs and photos. Comment V or G, and share this with whoever you're planning with. | L5: #Lumhe #WeddingPoll #WeddingVenue #GuestList #WeddingDebate #EngagedLife #WeddingPlanningJourney #Mandap #WeddingDecor #BrideAndGroomToBe #CelebrationPlanning | M5: Our vote: guest list first. Fight us gently in the replies. | N5: Watercolour of an empty mandap framed by a floral arch. Text asks 'Venue first, or guest list first?' and invites comments. | O5: Cast your vote | P5: 1 image · 4:5 | R5: US-21 | S5: Wedding Invitation Templates | T5: Posts/004_2026-10-08_Single_S35_Poll-venue-first-or-guest-list | U5: post.jpg | V5: Ready | Z5: Blog image
A6: 5 | B6: 46304 | C6: =TEXT(B6,"ddd") -> Fri | D6: 12:30 | E6: IST | F6: Reel | G6: India | H6: E21 | I6: NRI family plans a Pune wedding | J6: Shaadi in Pune. Family in Toronto. | K6: No hour is a good hour to call home before the shaadi. If you're planning a wedding in Pune, Jaipur or Kochi from Toronto, Dubai or London, you know the drill: late-night calls, 6 a.m. voice notes, and three relatives each holding a different version of the guest list. What actually helps: • One standing family call a week, at an hour both sides can manage • One guest list everyone works from, not five forwarded PDFs • RSVPs collected per function, so you know who's coming to Haldi and who's only coming to the Reception That's the job Lumhe does. Upload your card, add each function, and share one link on WhatsApp. Guests reply without an app or login, and you see live headcounts from wherever you are. Send this to the cousin abroad who's secretly running the wedding. Create your event free, link in bio. | L6: #Lumhe #NRIWedding #NRIWeddingPlanning #DestinationWeddingIndia #IndianWeddingPlanning #DesiDiaspora #WeddingFromAbroad #PuneWedding #ShaadiPlanning #WeddingRSVP #DigitalWeddingInvitation #BrotherKiShaadi | M6: Abroad or at home: which side of the family time zone are you on? | N6: Watercolour reel: a woman with chai by a snowy night window beside a marigold-draped suitcase, and a mother hanging a marigold toran in a sunny Indian courtyard. Text tells how one link coordinates a wedding in India from abroad. | O6: Create your event | P6: 15 s · 9:16 | Q6: Soft lo-fi beat with a gentle flute or sitar line that lifts into an upbeat dhol groove on the CTA. | R6: EV-E21_A, EV-E21_B | S6: New watercolour, blog topic: nri-wedding | New watercolour, blog topic: nri-wedding | T6: Posts/005_2026-10-09_Reel_E21_NRI-family-plans-a-Pune-wedding | U6: reel.mp4, reel_cover.jpg | V6: Ready | Z6: Evergreen
A7: 6 | B7: 46304 | C7: =TEXT(B7,"ddd") -> Fri | D7: 21:30 | E7: 19:30 IST = 9:00 AM ET · 21:30 IST = 11:00 AM ET | F7: Single | G7: USA | H7: E27 | I7: Whose name goes first | J7: Whoever hosts decides whose name goes first | K7: Two names, one order, and somehow a whole family debate. Here's the traditional rule: when the bride's parents host, the bride's name comes first. When the groom's family hosts, his name can lead. When you host together, or as two brides or two grooms, any order works, alphabetical included. The real rule? Consistency. Same order on the invite, the envelope, the wedding website and the RSVP page. On Lumhe, your names, invite and RSVP live on one link, so they always match. Save this for wording day. | L7: #Lumhe #WeddingEtiquette #WeddingInvitationWording #WeddingInvites #EngagedLife #BrideToBe #GroomToBe #WeddingPlanningTips #ModernWedding #WeddingStationery #DigitalInvitations | M7: Whose name went first on yours, and who won that argument? | N7: Watercolor of a calligrapher's desk with a blank ivory invitation, fountain pen, ink pot, eucalyptus and marigold petals. Text reads 'Whoever hosts decides whose name goes first' with a short etiquette rule. | O7: Word your invite | P7: 1 image · 4:5 | R7: EV-E27_A | S7: New watercolour, blog topic: whose-name-first | T7: Posts/006_2026-10-09_Single_E27_Whose-name-goes-first | U7: post.jpg | V7: Ready | Z7: Evergreen
A8: 7 | B8: 46305 | C8: =TEXT(B8,"ddd") -> Sat | D8: 12:30 | E8: IST | F8: Reel | G8: India | H8: F02 | I8: Navratri eve invite reminder reel | J8: Garba starts tomorrow. Invite sent? | K8: Kalash tomorrow, Garba tomorrow night, guest list still a vibe. 😅 If you're hosting a Garba night, a society Dandiya or Kanya Pujan this Navratri, tonight is the night to send the invite. Not a blurry forward that sinks under good-morning messages, but one link with the date, time, venue and the colour of the day. On Lumhe, add each night as a function. Guests tap, RSVP for the nights they're coming, and you see the headcount live, so you know exactly how many dandiya sticks and how much nimbu-paani you need. Afterwards, everyone's videos go into one Moments album, in full quality. Share this with the friend hosting this year. Make your invite free, link in bio. | L8: #Lumhe #NavratriTomorrow #Garba2026 #DandiyaRaas #NavratriReels #GarbaLovers #Navratri #GujaratiGarba #NavratriPreparations #FestiveReels #DigitalInvite | M8: Which colour are you wearing on day one? Drop it below. | N8: Watercolour reel: a couple mid-Garba with dandiya sticks beside a glowing garbo pot, and a puja thali with a diya, chunri-wrapped coconut and dandiya sticks. Text urges hosts to send their Navratri invite tonight. | O8: Make your invite | P8: 15 s · 9:16 | Q8: Upbeat dhol-and-dandiya folk fusion with a fast build, clapping on every scene change. | R8: PAIR-NAV_A, PAIR-NAV_B | S8: New watercolour, blog topic: festival | New watercolour, blog topic: festival | T8: Posts/007_2026-10-10_Reel_F02_Navratri-eve-invite-reminder-reel | U8: reel.mp4, reel_cover.jpg | V8: Ready | X8: Sharad Navratri | Y8: 2026-10-11 | Z8: Reminder (1-2 days) | AA8: F01
A9: 8 | B9: 46305 | C9: =TEXT(B9,"ddd") -> Sat | D9: 19:00 | E9: IST | F9: Carousel | G9: India | H9: F04 | I9: Dussehra get-together planning guide | J9: Ravan Dahan plans, sorted before the arrows fly | K9: The jalebi queue is already forming in our heads. 🏹 Dussehra is the day the whole family wants to be together: lunch at home, an evening at the Ramlila ground, and the cheer when the Ravan effigy goes up in flames. It all goes better when everyone knows the plan. Swipe for: • Invite wording for a family Dussehra lunch • What to tell guests for a colony Ravan Dahan • The shami leaf 'sona' line for Marathi homes • A host checklist to book now Put the whole day in one Lumhe link, with an RSVP for each part, and keep every effigy-burning video in one Moments album instead of ten family chats. Save this for your planning group. Create your invite free, link in bio. | L9: #Lumhe #Dussehra2026 #Vijayadashami #RavanDahan #Ramlila #DussehraCelebration #ShamiPuja #JalebiFafda #FestiveSeasonIndia #GoodOverEvil #DussehraVibes #FamilyGetTogether | M9: Ramlila ground or home lunch: where does your family spend Dussehra? | N9: Watercolour carousel: a family watching a tall Ravan effigy at dusk, and a brass plate of shami leaves with a small bow and arrow and jalebis. Slides share Dussehra invite wording and a host checklist. | O9: Plan your Dussehra | P9: 6 slides | R9: PAIR-DUS_A, PAIR-DUS_B | S9: New watercolour, blog topic: festival | New watercolour, blog topic: festival | T9: Posts/008_2026-10-10_Carousel_F04_Dussehra-get-together-planning-guide | U9: slide_01.jpg, slide_02.jpg, slide_03.jpg, slide_04.jpg, slide_05.jpg, slide_06.jpg | V9: Ready | X9: Dussehra | Y9: 2026-10-20 | Z9: 10 days before | AA9: F05
A10: 9 | B10: 46306 | C10: =TEXT(B10,"ddd") -> Sun | D10: 12:30 | E10: IST | F10: Single | G10: India | H10: F03 | I10: Navratri day one greeting | J10: Nine nights of shakti, devotion and dancing feet | K10: Jai Mata Di! 🌼 Today the kalash is placed, the diya is lit and nine nights of Garba, fasting and family begin. May Maa Durga fill your home with strength, peace and plenty, and may your feet never tire before the last round of Garba. Shubh Navratri from all of us at Lumhe. Hosting Kanya Pujan or a Garba night this week? Your invite is ready in minutes at lumhe.com. | L10: #Lumhe #ShubhNavratri #HappyNavratri #JaiMataDi #NavratriWishes #Ghatasthapana #MaaDurga #NavratriGreetings #NavratriDay1 #Shakti #FestivalsOfIndia | M10: Which day of Navratri do you look forward to most? Tell us why. | N10: Watercolour of a red chunri-draped kalash with mango leaves and a coconut, a pot of sprouting barley, a glowing diya and marigold garlands. Text reads 'Shubh Navratri: Nine nights of shakti, devotion and dancing feet.' | O10: Send the wish | P10: 1 image · 4:5 | R10: DAY-NAV_A | S10: New watercolour, blog topic: festival | T10: Posts/009_2026-10-11_Single_F03_Navratri-day-one-greeting | U10: post.jpg | V10: Ready | X10: Sharad Navratri | Y10: 2026-10-11 | Z10: On the day
A11: 10 | B11: 46306 | C11: =TEXT(B11,"ddd") -> Sun | D11: 21:30 | E11: 19:30 IST = 9:00 AM ET · 21:30 IST = 11:00 AM ET | F11: Carousel | G11: USA | H11: E28 | I11: Destination wedding invite timing and details | J11: Your invite is also a travel brief | K11: Your guests aren't just saving a Saturday. They're booking flights. A destination wedding invitation has two jobs: make people feel wanted, and give them everything they need to plan a trip. Miss the second part and your inbox fills with "Which airport?" and "Is there a room block?" Swipe for: • When to send the save-the-date and invitation • Wording that's warm without sounding like a travel ad • The details guests need before they book • A gentle way to be clear about costs Tip: give travel dates, not just the ceremony date, so guests can plan the whole trip. Save this for your planning folder. Then put the invite, travel details and RSVP on one Lumhe link. Create yours free at lumhe.com. | L11: #Lumhe #DestinationWedding #DestinationWeddingInvitations #BeachWedding #WeddingAbroad #WeddingTimeline #SaveTheDate #WeddingPlanning2027 #TravelWedding #WeddingGuestTips #EngagedAndPlanning #WeddingRSVP | M11: Beach, mountains or a European old town: where would your dream destination wedding be? | N11: Watercolor carousel: a couple walking barefoot toward a flower-draped beach arch at golden hour, and a close-up of a passport, map, straw hat, shells and a wax-sealed envelope. Slides cover destination wedding invitation timing, wording and details. | O11: Send your invite | P11: 6 slides | R11: EV-E28_A, EV-E28_B | S11: New watercolour, blog topic: destination-wedding | New watercolour, blog topic: destination-wedding | T11: Posts/010_2026-10-11_Carousel_E28_Destination-wedding-invite-timing-and-de | U11: slide_01.jpg, slide_02.jpg, slide_03.jpg, slide_04.jpg, slide_05.jpg, slide_06.jpg | V11: Ready | Z11: Evergreen
A12: 11 | B12: 46307 | C12: =TEXT(B12,"ddd") -> Mon | D12: 16:30 | E12: 16:30 IST = 11:00 AM UK · 23:00 IST = 5:30 PM UK | F12: Single | G12: UK | H12: E45 | I12: Gender reveal invite: keep the secret | J12: Only the baker knows. Say so on the invite. | K12: The secret is the whole party, so guard it on the invite. Tell guests who's in on it (usually just the baker or one trusted friend) and roughly when the big moment happens, so nobody nips out to feed the meter and misses it. Then cover the basics: date, time, venue with full address, parking, dress code and an RSVP date. A colour theme is half the fun: ask guests to wear pink or blue to cast their vote. On Lumhe, upload your invite, share one link in the family WhatsApp and watch the headcount build. No app, no login. Save this for your reveal, and make your invite free at lumhe.com. | L12: #Lumhe #GenderReveal #GenderRevealParty #BabyOnTheWay #UKMums #PregnancyUK #BabyShowerUK #PartyInvitations #DigitalInvitations #TeamPinkOrBlue #RevealParty #NewParentsUK | M12: Team pink, team blue or team 'just tell us already'? | N12: Watercolour of an English garden party table with a tall white cake, pink and blue balloons and marigolds. Text reads: Only the baker knows. Say so on the invite. | O12: Create your invite free | P12: 1 image · 4:5 | R12: EV-E45_A | S12: New watercolour, blog topic: gender-reveal | T12: Posts/011_2026-10-12_Single_E45_Gender-reveal-invite-keep-the-secret | U12: post.jpg | V12: Ready | Z12: Evergreen
A13: 12 | B13: 46307 | C13: =TEXT(B13,"ddd") -> Mon | D13: 20:30 | E13: IST | F13: Single | G13: Global | H13: E57 | I13: Moments: the photos on guests' phones | J13: The best photos are on their phones | K13: Your photographer got the portraits. Your guests got everything else. The cousin who caught the cake wobble. The friend who filmed the speeches. The 2 a.m. dance-floor blur that somehow sums up the whole night. Those photos usually stay stuck on a dozen different phones, or get squashed in a chat until nobody can find them. Moments collects them in one shared album: guests open your Lumhe link, tap upload and add their shots, no app and no login. It doesn't vanish after 24 hours and it isn't compressed. Start your album free at lumhe.com (link in bio). | L13: #Lumhe #EventPhotos #PhotoSharing #WeddingPhotos #GuestPhotos #PartyMemories #CelebrationPlatform #SharedAlbum #CandidMoments #WeddingGuests #PhotoAlbum | M13: Whose camera roll has the best photos from your last party? | N13: Watercolor of a reception table after the party, scattered with cameras, loose snapshots and marigolds under fairy lights. Text reads: The best photos are on their phones. | O13: Start your album | P13: 1 image · 4:5 | R13: EV-E57_A | S13: New watercolour, blog topic: share-event-photos | T13: Posts/012_2026-10-12_Single_E57_Moments-the-photos-on-guests-phones | U13: post.jpg | V13: Ready | Z13: Evergreen
A14: 13 | B14: 46308 | C14: =TEXT(B14,"ddd") -> Tue | D14: 12:30 | E14: IST | F14: Single | G14: India | H14: E04 | I14: Kannada lagna patrike structure tip | J14: Four parts every lagna patrike needs | K14: Tambula on the plate, patrike in hand, and Ajji checking the order. A Kannada lagna patrike follows a set sequence: an invocation at the top, both families' names, the muhurta with date and venue, and a closing request. A line many families use: "Taavu sakutumba sametaraagi aagamisi vadhuvararannu aashirvadisabekaagi vinanti." (We request you to come with your family and bless the couple.) Inviting friends who don't read Kannada? Add one English line under each section. Then upload the card to Lumhe and share a single link on WhatsApp. Link in bio. | L14: #Lumhe #KannadaWedding #LagnaPatrike #MaduveInvitation #KannadaMaduve #BengaluruWeddings #MysuruWeddings #KarnatakaWedding #VivahaNimantrana #WeddingCardTips #SouthIndianBride #KannadaCulture | M14: Do you still hand-deliver the patrike with tambula, or is WhatsApp fine now? | N14: Watercolour of a wedding card on a silver plate with betel leaves, areca nuts, a coconut and kumkum, framed by banana stems and a mango-leaf toran with marigolds. Text: 'Four parts every lagna patrike needs'. | O14: Upload your patrike | P14: 1 image · 4:5 | R14: EV-E04_A | S14: New watercolour, blog topic: kannada | T14: Posts/013_2026-10-13_Single_E04_Kannada-lagna-patrike-structure-tip | U14: post.jpg | V14: Ready | Z14: Evergreen
A15: 14 | B15: 46308 | C15: =TEXT(B15,"ddd") -> Tue | D15: 23:00 | E15: 16:30 IST = 11:00 AM UK · 23:00 IST = 5:30 PM UK | F15: Carousel | G15: UK | H15: E44 | I15: Hen party invitations: wording and plan | J15: From Prosecco brunch to a Brighton weekend | K15: Maid of honour duty, day one: the invitation. Get it right and the rest of the hen do plans itself. Get it wrong and you'll spend six weeks answering 'wait, which weekend?' in the group chat. Swipe for two wording styles (classy and cheeky), the four things every hen needs before saying yes, and why a weekend away needs at least two months' notice. Our favourite tip: be upfront about the rough cost per head and the deposit date. Nobody likes a surprise bill, and clear numbers mean faster replies. With Lumhe, upload the invite you designed, share one link with the hens and see exactly who's confirmed. After the weekend, everyone drops their photos into one Moments album instead of forty separate chats. Save this for when you're chief hen, tag your maid of honour, and start free at lumhe.com. | L15: #Lumhe #HenParty #HenDo #HenWeekend #BrideTribe #MaidOfHonour #HenPartyIdeas #UKBride #BrideToBe2027 #HenDoInvites #WeddingPlanningUK #Bridesmaids | M15: Spa day, city weekend or a countryside cottage: what's your dream hen? | N15: Watercolour carousel: friends clinking Prosecco glasses at a brunch table with flower crowns and marigolds, and a packed weekend bag. Cover text reads: From Prosecco brunch to a Brighton weekend. | O15: Send your hen invite | P15: 6 slides | R15: EV-E44_A, EV-E44_B | S15: New watercolour, blog topic: hen-party | New watercolour, blog topic: hen-party | T15: Posts/014_2026-10-13_Carousel_E44_Hen-party-invitations-wording-and-plan | U15: slide_01.jpg, slide_02.jpg, slide_03.jpg, slide_04.jpg, slide_05.jpg, slide_06.jpg | V15: Ready | Z15: Evergreen
A16: 15 | B16: 46309 | C16: =TEXT(B16,"ddd") -> Wed | D16: 13:00 | E16: IST | F16: Carousel | G16: Global | H16: E55 | I16: What is a celebration platform? | J16: What is a celebration platform, exactly? | K16: Invites, RSVPs, photos and gifts usually live in four different places. A celebration platform puts them on one link, so the host isn't stitching together a chat, a spreadsheet, a photo dump and an envelope box. Here's how it works on Lumhe: 1. Upload any invite you've made (Canva, PDF, image or video) or design one. 2. Add your functions, so each guest sees only the ones they're invited to. 3. Guests RSVP without downloading anything, and you see a live headcount per function. 4. After the event, everyone adds photos to Moments, a shared album that doesn't expire. In India, guests can also send shagun through Digital Lifafa, straight to your UPI ID. Swipe through, then try it free at lumhe.com. Link in bio. | L16: #Lumhe #CelebrationPlatform #DigitalInvitations #OnlineRSVP #EventPlanning #PartyPlanning #SharedPhotoAlbum #EventTech #WeddingPlanning #BirthdayPlanning #GuestList #InviteOnline | M16: Which part of hosting do you find hardest: invites, RSVPs, photos or gifts? | N16: Watercolor of a celebration table with a ribbon-tied invitation, a stack of instant photos, a gift envelope and a brass bowl of marigolds around a candle. Cover text reads: What is a celebration platform, exactly? | O16: Start celebrating free | P16: 6 slides | R16: EV-E55_A | S16: New watercolour, blog topic: celebration-platform | T16: Posts/015_2026-10-14_Carousel_E55_What-is-a-celebration-platform | U16: slide_01.jpg, slide_02.jpg, slide_03.jpg, slide_04.jpg, slide_05.jpg, slide_06.jpg | V16: Ready | Z16: Evergreen
A17: 16 | B17: 46309 | C17: =TEXT(B17,"ddd") -> Wed | D17: 21:30 | E17: 19:30 IST = 9:00 AM ET · 21:30 IST = 11:00 AM ET | F17: Single | G17: USA | H17: S32 | I17: Fall wedding invite dress code tip | J17: Let your invite set the dress code | K17: Golden leaves, crisp air and one guest question: what do I wear? Your fall wedding invitation is the first preview of the day, so let it set the formality before anyone goes shopping. Try lines like: "Cocktail attire. The evening gets crisp, so bring a wrap." "Rustic chic: boots welcome, heels may sink in the orchard." Pick colors from the season too: burgundy, burnt orange, sage and gold read "fall" instantly. Building your own invite? Upload it to Lumhe and share one link with RSVP built in. Link in bio. 🍂 | L17: #Lumhe #FallWedding #AutumnWedding #FallWeddingInvitations #WeddingDressCode #OctoberBride #RusticWedding #WeddingInvitationIdeas #BrideToBe #DigitalInvitations #WeddingPlanningTips #BurgundyWedding | M17: Fall couples: cocktail attire, black-tie or boots-and-flannel? Tell us your dress code. | N17: Watercolor illustration of a bride holding a bouquet among autumn trees with golden leaves. Text reads: Fall wedding tip, Let your invite set the dress code. | O17: Create your invite free | P17: 1 image · 4:5 | R17: US-16 | S17: Create Your Own Wedding Invitations: Complete Guide | T17: Posts/016_2026-10-14_Single_S32_Fall-wedding-invite-dress-code-tip | U17: post.jpg | V17: Ready | Z17: Blog image
A18: 17 | B18: 46310 | C18: =TEXT(B18,"ddd") -> Thu | D18: 19:30 | E18: 19:30 IST = 9:00 AM ET · 21:30 IST = 11:00 AM ET | F18: Carousel | G18: USA | H18: C24 | I18: Invite platform comparison checklist | J18: Evite, Paperless Post or Lumhe? Compare this | K18: The prettiest template isn't always the best invite platform. Evite and Paperless Post are both well-known names for digital invitations, and each has its fans. Before you commit, run your shortlist through five quick questions: 1. Can guests RSVP without making an account? 2. Can you upload the design you already have? 3. Does it handle multiple events, like a welcome dinner, ceremony and brunch? 4. Is there somewhere for guests to share photos afterward? 5. What's free, and what costs extra? Whichever platform you pick, these answers decide whether your guests actually reply, and whether you spend RSVP week chasing people by text. Lumhe is our answer: bring any design, share one link, track RSVPs per event and collect every guest's photos in one Moments album. Free to start at the link in bio. Save this before you choose. | L18: #Lumhe #DigitalInvitations #OnlineInvitations #EInvite #WeddingPlanningTips #RSVP #EventPlanningTips #PartyPlanning #WeddingTech #BrideToBe2027 #PaperlessWedding #InvitationIdeas #HostingTips | M18: Which matters most to you: design, RSVP tracking or price? | N18: Watercolour illustration of a hand holding a phone with a gold invitation against navy tones. Text reads: Evite, Paperless Post or Lumhe? Compare this. | O18: Try Lumhe free | P18: 6 slides | R18: US-15, UK-21 | S18: Wedding Invitations Cheap | Personalised Party Invites: Complete Guide | T18: Posts/017_2026-10-15_Carousel_C24_Invite-platform-comparison-checklist | U18: slide_01.jpg, slide_02.jpg, slide_03.jpg, slide_04.jpg, slide_05.jpg, slide_06.jpg | V18: Ready | Z18: Blog image
A19: 18 | B19: 46310 | C19: =TEXT(B19,"ddd") -> Thu | D19: 21:30 | E19: 19:30 IST = 9:00 AM ET · 21:30 IST = 11:00 AM ET | F19: Single | G19: USA | H19: E29 | I19: Rehearsal dinner invite tip | J19: The night before the vows deserves its own invite | K19: Toasts, stories and the first time both families share a table. A rehearsal dinner invite should say three things clearly: who it's for, where to go right after the rehearsal, and whether plus-ones and kids are included. Traditionally the groom's family hosts, but today anyone can. Wording to borrow: "Before we say I do, let's raise a glass. Join us for dinner after the rehearsal, Friday at 7 p.m." Make it on Lumhe, send one link and watch the RSVPs come in. Create yours free, link in bio. | L19: #Lumhe #RehearsalDinner #RehearsalDinnerInvite #WeddingWeekend #WeddingParty #WeddingEve #WeddingInvitationIdeas #BrideAndGroom #WeddingToasts #IntimateDinner #OnlineRSVP | M19: Rehearsal dinner: cozy family meal or the wedding weekend's real party? | N19: Watercolor of a candlelit restaurant table set for a rehearsal dinner with roses, marigolds and string lights. Text reads 'The night before the vows deserves its own invite' with a timing tip. | O19: Create your invite | P19: 1 image · 4:5 | R19: EV-E29_A | S19: New watercolour, blog topic: rehearsal-dinner | T19: Posts/018_2026-10-15_Single_E29_Rehearsal-dinner-invite-tip | U19: post.jpg | V19: Ready | Z19: Evergreen
A20: 19 | B20: 46311 | C20: =TEXT(B20,"ddd") -> Fri | D20: 12:30 | E20: IST | F20: Carousel | G20: India | H20: E02 | I20: Tamil kalyana pathirikai wording and design | J20: Tamil wedding wording, start to finish | K20: Jasmine, temple gold and a card that starts with one small symbol. A Tamil kalyana pathirikai has a rhythm families know by heart. The Pillaiyar Suzhi (உ) sits at the top, both families are named with respect, the muhurtham is stated clearly, and the closing asks guests to come with their kin and bless the couple. Swipe for: • What goes first on the card • A Tamil closing line, with meaning • An English line for friends • Design cues that feel traditional, not dated Tip: put the reception on its own line, since many friends only come for that evening. Save this for your card meeting. Then upload the final pathirikai to Lumhe and share one link with an RSVP for the muhurtham and reception. Link in bio. | L20: #Lumhe #TamilWedding #KalyanaPathirikai #TamilWeddingCard #ChennaiWeddings #Muhurtham #TamilBride #KanjeevaramBride #SouthIndianWeddings #ThirumanaAzhaippithazh #WeddingCardDesign #MaduraiWeddings | M20: Team traditional yellow-and-maroon card or team pastel? Vote below. | N20: Watercolour of a Tamil bride in a Kanjeevaram silk saree with temple jewellery and a jasmine-strand plait, beside banana trees and marigold garlands. Slides give Tamil wedding invitation wording and design tips. | O20: Upload your pathirikai | P20: 6 slides | R20: EV-E02_A | S20: New watercolour, blog topic: tamil-wedding-invitation | T20: Posts/019_2026-10-16_Carousel_E02_Tamil-kalyana-pathirikai-wording-and-des | U20: slide_01.jpg, slide_02.jpg, slide_03.jpg, slide_04.jpg, slide_05.jpg, slide_06.jpg | V20: Ready | Z20: Evergreen
A21: 20 | B21: 46311 | C21: =TEXT(B21,"ddd") -> Fri | D21: 23:00 | E21: 16:30 IST = 11:00 AM UK · 23:00 IST = 5:30 PM UK | F21: Single | G21: UK | H21: E46 | I21: 60th birthday invite wording | J21: Sixty years young and still first on the dance floor. Join us for afternoon tea and bubbles. | K21: Turning sixty deserves better than a 'drinks at ours?' text. Whether it's a garden party with Pimm's and croquet or a proper afternoon tea with scones and fine china, the invite sets the tone. Keep it warm, a little cheeky and crystal clear on the practical bits: date, start and finish time, address, dress code and an RSVP date. Scones before or after the speeches? Add a rough timeline so Grandad knows when to stand up. Copy the wording above, then make your invite on Lumhe and track replies in one place, free. Who's turning sixty in your family? Tag the person organising it. | L21: #Lumhe #60thBirthday #SixtyAndFabulous #60thBirthdayParty #BirthdayInvitations #GardenParty #AfternoonTea #MilestoneBirthday #UKParty #PartyPlanningUK #BirthdayIdeas | M21: Garden party or afternoon tea: how would you celebrate sixty? | N21: Watercolour of an English garden afternoon tea with a tiered stand, fine china and marigolds under string lights. Text reads: Sixty years young and still first on the dance floor. Join us for afternoon tea and bubbles. | O21: Make your invite free | P21: 1 image · 4:5 | R21: EV-E46_A | S21: New watercolour, blog topic: 60th-birthday | T21: Posts/020_2026-10-16_Single_E46_60th-birthday-invite-wording | U21: post.jpg | V21: Ready | Z21: Evergreen
A22: 21 | B22: 46312 | C22: =TEXT(B22,"ddd") -> Sat | D22: 19:30 | E22: 19:30 IST = 9:00 AM ET · 21:30 IST = 11:00 AM ET | F22: Reel | G22: USA | H22: E34 | I22: Themed party invites that set the tone | J22: The theme starts at the invite | K22: Guests decide how excited to be the moment they open the invite. A themed invitation does half your hosting for you. It tells kids what to wear, tells parents what to expect, and gets everyone talking before the party even starts. A few lines to borrow: 🦖 Dinosaurs: "Stomp on over! Max is turning five." ☕ Tea party: "You're invited to a tea-riffic afternoon. Hats encouraged." 🏖️ Beach: "Sunscreen on, flip-flops ready. We're throwing a splash party." Add the essentials too: date, time, address, what to wear and an RSVP date. On Lumhe you can upload your themed design or make one, send a single link, and watch the headcount update live. Create your party invite free at lumhe.com. | L22: #Lumhe #ThemedParty #PartyInvitations #KidsBirthdayParty #DinosaurParty #TeaPartyIdeas #BeachParty #BirthdayPartyIdeas #PartyPlanningMom #KidsPartyIdeas #DigitalInvites #OnlineRSVP #PartyInspo | M22: What's the best party theme you've ever been invited to? | N22: Watercolor reel: children in dinosaur costumes beside a dinosaur cake and balloons in a backyard, and a close-up of a tea-party table with floral cups and macarons. Text shares themed invitation wording ideas. | O22: Make your invite | P22: 15 s · 9:16 | Q22: Bright, bouncy ukulele-pop track with handclaps; quick cuts on each beat. | R22: EV-E34_A, EV-E34_B | S22: New watercolour, blog topic: themed-party | New watercolour, blog topic: themed-party | T22: Posts/021_2026-10-17_Reel_E34_Themed-party-invites-that-set-the-tone | U22: reel.mp4, reel_cover.jpg | V22: Ready | Z22: Evergreen
A23: 22 | B23: 46312 | C23: =TEXT(B23,"ddd") -> Sat | D23: 20:30 | E23: IST | F23: Single | G23: Global | H23: E58 | I23: Free invitation maker: what to check | J23: Free to design isn't always free to send | K23: Before you fall for a template, read what 'free' actually covers. Some tools let you design for free but charge when you send. Others cap the number of guests or keep RSVPs behind an upgrade. And some ask every guest to download an app first, which is where replies go to die. A quick checklist before you commit: • Can you send to your whole list at no cost? • Do RSVPs come back in one place? • Can guests open it without signing up? • Can you bring a design you already made? Lumhe does all four, free. Bring your Canva file, PDF or video, or design one, and share a single link. Try it at lumhe.com. | L23: #Lumhe #FreeInvitations #InvitationMaker #OnlineInvitations #DigitalInvite #FreeTemplates #PartyInvites #EventInvites #DIYInvitations #RSVPOnline #InviteDesign | M23: What's the most annoying 'free' catch you've run into? | N23: Watercolor of a tidy desk with sketched invitation layouts, sample cards, colored pencils, tea and marigolds. Text reads: Free to design isn't always free to send. | O23: Try Lumhe free | P23: 1 image · 4:5 | R23: EV-E58_A | S23: New watercolour, blog topic: free-invitation-maker | T23: Posts/022_2026-10-17_Single_E58_Free-invitation-maker-what-to-check | U23: post.jpg | V23: Ready | Z23: Evergreen
A24: 23 | B24: 46313 | C24: =TEXT(B24,"ddd") -> Sun | D24: 12:30 | E24: IST | F24: Single | G24: India | H24: E07 | I24: Christian wedding invite: church and reception | J24: Church at 11. Reception at 7. Separate RSVPs. | K24: White lilies, a church bell, and a caterer asking for numbers. Many Christian weddings in India have two parts: the Holy Matrimony at church and a reception later. A wording line families use: "Together with their families, Anita and Joel request the honour of your presence at their Holy Matrimony at St. Thomas Church, followed by a reception." Some add a verse at the top, such as 1 Corinthians 13:4, "Love is patient, love is kind." On Lumhe, guests RSVP to each part separately, so the reception count is real. Create your invite at lumhe.com. | L24: #Lumhe #ChristianWedding #ChristianWeddingIndia #HolyMatrimony #ChurchWedding #KeralaChristianWedding #GoanWedding #WeddingReception #WhiteSareeBride #WeddingInvitationIndia #ChristianBride #WeddingRSVP | M24: Which verse would you put on your card? Share it below. | N24: Watercolour of an Indian Christian bride in a white saree and veil with the groom in a suit outside a whitewashed church, with white lilies and marigold garlands. Text reads: church at 11, reception at 7, separate RSVPs. | O24: Create your invite | P24: 1 image · 4:5 | R24: EV-E07_A | S24: New watercolour, blog topic: christian-wedding | T24: Posts/023_2026-10-18_Single_E07_Christian-wedding-invite-church-and-rece | U24: post.jpg | V24: Ready | Z24: Evergreen
A25: 24 | B25: 46313 | C25: =TEXT(B25,"ddd") -> Sun | D25: 21:30 | E25: 19:30 IST = 9:00 AM ET · 21:30 IST = 11:00 AM ET | F25: Carousel | G25: USA | H25: E30 | I25: Christmas-season wedding invitations | J25: Saying I do when it snows | K25: A December wedding competes with every office party in town. Winter weddings are cozy, candlelit and full of twinkle, but your guests' calendars are packed and holiday travel books up early. The invite has to land first and answer more questions than usual. Swipe for: • When to send for a December date • A formal wording sample with a seasonal touch • A playful option for a relaxed celebration • The winter details guests always ask about Tip: name the holiday-week hotel rate on your details page. Guests notice it. Save this if you're saying "I do" in the snow. Then share your invite, details and RSVP on one Lumhe link. Create yours free at lumhe.com. | L25: #Lumhe #ChristmasWedding #WinterWedding #DecemberWedding #HolidayWedding #WinterWeddingInvitations #SnowyWedding #WeddingInvitationWording #FestiveWedding #WeddingSeason #EngagedAF #WeddingDetails | M25: Winter wedding: velvet and candlelight, or would you rather wait for summer? | N25: Watercolor carousel: a couple under an evergreen arch with red berries, pine garlands and candle lanterns in light snow outside a barn. Slides share timing, wording and guest details for Christmas-season wedding invitations. | O25: Create your invite | P25: 6 slides | R25: EV-E30_A | S25: New watercolour, blog topic: christmas-wedding-invitations | T25: Posts/024_2026-10-18_Carousel_E30_Christmas-season-wedding-invitations | U25: slide_01.jpg, slide_02.jpg, slide_03.jpg, slide_04.jpg, slide_05.jpg, slide_06.jpg | V25: Ready | Z25: Evergreen
A26: 25 | B26: 46314 | C26: =TEXT(B26,"ddd") -> Mon | D26: 12:30 | E26: IST | F26: Single | G26: India | H26: F05 | I26: Dussehra eve meet-up reminder | J26: Ravan burns tomorrow. Does everyone know where to meet? | K26: Tomorrow evening, half the colony will be at the Ramlila ground. And nobody will find anybody. Fix that tonight. Send the family one link with lunch timings, the ground's location pin and a clear meet-up spot for after the Ravan Dahan (the jalebi stall counts). Ask for a quick RSVP so you know how many plates to plan. On Lumhe, it takes a few minutes and opens straight from WhatsApp, no app needed. Make yours free, link in bio. | L26: #Lumhe #DussehraTomorrow #Dussehra #RavanDahan2026 #Vijayadashami2026 #RamlilaNights #DussehraPlans #FestivalReminder #IndianFestivals #FamilyPlans #DigitalInvitation | M26: Who in your family always gets lost at the Ravan Dahan? Tag them 😄 | N26: Watercolour of a family seen from behind watching a tall Ravan effigy at dusk, a child on her father's shoulders. Text reads 'Ravan burns tomorrow. Does everyone know where to meet?' | O26: Send one link | P26: 1 image · 4:5 | R26: PAIR-DUS_A, PAIR-DUS_B | S26: New watercolour, blog topic: festival | New watercolour, blog topic: festival | T26: Posts/025_2026-10-19_Single_F05_Dussehra-eve-meet-up-reminder | U26: post.jpg | V26: Ready | X26: Dussehra | Y26: 2026-10-20 | Z26: Reminder (1-2 days) | AA26: F04
A27: 26 | B27: 46314 | C27: =TEXT(B27,"ddd") -> Mon | D27: 19:00 | E27: IST | F27: Carousel | G27: India | H27: F07 | I27: Karva Chauth gathering planning guide | J27: From sargi to moonrise, planned with love | K27: Ten days to the most photographed moon of the year. 🌙 Karva Chauth is about the vrat, but for many of us it's also about the evening together: mehendi the night before, the katha with friends, and that rooftop wait for the moon with a sieve in hand. Swipe for: • Katha invite wording you can copy • How to host a mehendi night without chaos • The puja thali checklist • A moonrise plan, with a backup Hosting? Put both evenings in one Lumhe link, see who's coming to each, and gather every moon photo in one Moments album. Save this and send it to your Karva Chauth group. Link in bio. | L27: #Lumhe #KarvaChauth2026 #KarvaChauth #KarwaChauth #Sargi #MehendiNight #KarvaChauthThali #MoonriseRitual #FestiveFashion #PunjabiTraditions #IndianFestival #KarvaChauthSpecial | M27: Mehendi the night before or the same morning? Tell us your ritual. | N27: Watercolour carousel: a woman in a red saree raising a sieve to the moon on a rooftop beside her husband, and hennaed hands holding a puja thali with a karva, sieve and diya. Slides share Karva Chauth invite wording and a puja checklist. | O27: Plan the gathering | P27: 6 slides | R27: PAIR-KC_A, PAIR-KC_B | S27: New watercolour, blog topic: festival | New watercolour, blog topic: festival | T27: Posts/026_2026-10-19_Carousel_F07_Karva-Chauth-gathering-planning-guide | U27: slide_01.jpg, slide_02.jpg, slide_03.jpg, slide_04.jpg, slide_05.jpg, slide_06.jpg | V27: Ready | X27: Karva Chauth | Y27: 2026-10-29 | Z27: 10 days before | AA27: F08
A28: 27 | B28: 46315 | C28: =TEXT(B28,"ddd") -> Tue | D28: 12:30 | E28: IST | F28: Single | G28: India | H28: F06 | I28: Dussehra day greeting | J28: Goodness wins. Today, and every day after. | K28: Vijayadashami ki hardik shubhkamnayein! 🏹 Today we remember that truth wins, however tall the Ravan. May this Dussehra burn away whatever weighs on you and bring fresh starts, golden shami leaves and a plate of hot jalebis. To every Marathi home: Sona ghya, sonyasarkha raha! 💛 From all of us at Lumhe, Happy Dussehra. Planning the Diwali get-together next? Lumhe is ready when you are. | L28: #Lumhe #HappyDussehra #ShubhVijayadashami #DussehraWishes #VictoryOfGood #Dasara #DussehraGreetings #DasaraWishes #SonaGhya #FestiveIndia #Vijayadashami2026Wishes | M28: Leave a 🏹 if you're watching the Ravan Dahan tonight! | N28: Watercolour of a marigold-wrapped bow and arrow resting against a lit brass diya on a red and yellow rangoli, with shami leaves scattered around. Text reads 'Happy Dussehra: Goodness wins. Today, and every day after.' | O28: Share the wish | P28: 1 image · 4:5 | R28: DAY-DUS_A | S28: New watercolour, blog topic: festival | T28: Posts/027_2026-10-20_Single_F06_Dussehra-day-greeting | U28: post.jpg | V28: Ready | X28: Dussehra | Y28: 2026-10-20 | Z28: On the day
A29: 28 | B29: 46315 | C29: =TEXT(B29,"ddd") -> Tue | D29: 21:30 | E29: 19:30 IST = 9:00 AM ET · 21:30 IST = 11:00 AM ET | F29: Single | G29: USA | H29: E31 | I29: 18th birthday invite tip | J29: Eighteen: officially old enough to write the invite | K29: Eighteen is the first party they'll want to plan themselves. Hand over the theme and the wording, and keep the logistics. A good 18th invite still needs the basics: date, start and end time, address, dress code if there is one, and a clear RSVP date so you can plan food. Wording to borrow: "Eighteen, finally. Come celebrate with cake, music and way too many photos." On Lumhe they design it, you see the headcount, and everyone's photos land in one Moments album. Create it free, link in bio. | L29: #Lumhe #18thBirthday #EighteenthBirthday #18thBirthdayParty #MilestoneBirthday #BirthdayInvitations #BackyardParty #PartyPlanning #SeniorYear #BirthdayPartyIdeas #OnlineInvitations | M29: Parents of 18-year-olds: who wrote the invite in your house? | N29: Watercolor of a backyard party at dusk with a sparkler-lit cake, instant photos on twine and string lights. Text reads 'Eighteen: officially old enough to write the invite' with a tip for parents. | O29: Start the invite | P29: 1 image · 4:5 | R29: EV-E31_A | S29: New watercolour, blog topic: 18th-birthday | T29: Posts/028_2026-10-20_Single_E31_18th-birthday-invite-tip | U29: post.jpg | V29: Ready | Z29: Evergreen
A30: 29 | B30: 46316 | C30: =TEXT(B30,"ddd") -> Wed | D30: 16:30 | E30: 16:30 IST = 11:00 AM UK · 23:00 IST = 5:30 PM UK | F30: Carousel | G30: UK | H30: E48 | I30: Wedding RSVP website guide (UK) | J30: Your RSVP site has one job | K30: Sticky notes, spreadsheets and that RSVP card behind the clock. A wedding RSVP website gathers every answer in one place, but only if you ask the right questions. Swipe for what to put on the form, how to handle day and evening guests, when to set the reply-by date and how to make answering effortless. The big one for UK weddings: day guests and evening guests are really two events. Count them separately and you'll know exactly how many wedding breakfasts to order and how many bacon butties to plan for at 10pm. Lumhe lets you add both as separate functions under one link, so each guest sees only what they're invited to and you get a live headcount for each. Guests don't need an app or a login. Save this for your planning folder, share it with your other half and start free at lumhe.com. | L30: #Lumhe #WeddingRSVP #RSVPWebsite #UKWedding #WeddingPlanningUK #EveningReception #WeddingBreakfast #BrideToBeUK #Engaged2026 #WeddingGuestList #WeddingWebsite #UKBrides | M30: Day guests vs evening guests: how big is your gap? | N30: Watercolour of a cosy kitchen table with an open wedding planner, cream RSVP cards tied with twine, a teapot and marigolds. Cover text reads: Your RSVP site has one job. | O30: Track RSVPs free | P30: 6 slides | R30: EV-E48_A | S30: New watercolour, blog topic: wedding-rsvp-website | T30: Posts/029_2026-10-21_Carousel_E48_Wedding-RSVP-website-guide-UK | U30: slide_01.jpg, slide_02.jpg, slide_03.jpg, slide_04.jpg, slide_05.jpg, slide_06.jpg | V30: Ready | Z30: Evergreen
A31: 30 | B31: 46316 | C31: =TEXT(B31,"ddd") -> Wed | D31: 21:30 | E31: 19:30 IST = 9:00 AM ET · 21:30 IST = 11:00 AM ET | F31: Carousel | G31: USA | H31: F10 | I31: Halloween invite wording and host plan | J31: Costumes? Kids? Answer it on the invite | K31: Two questions will flood your DMs this month. Answer them now. "Do I have to dress up?" and "Can I bring the kids?" If your Halloween invite answers both, you skip most of October's follow-up texts. Halloween falls on a Saturday this year, so party calendars will fill fast. Swipe for: • Wording for an adults-only haunted evening • Wording for a family costume party • The two lines every invite needs • A ten-day host timeline Make the invite on Lumhe or upload the one you designed, text one link, and watch the RSVPs come in. After the party, guests drop their photos into one Moments album. Save this, then send yours this week. Link in bio. 🎃 | L31: #Lumhe #Halloween2026 #HalloweenParty #HalloweenInvitations #HalloweenPartyIdeas #CostumeParty #TrickOrTreat #SpookySeason #HalloweenHost #PartyPlanning #FamilyHalloween #HauntedHouseParty #OctoberVibes | M31: Costume required or optional at your party? Cast your vote below 🎃 | N31: Watercolor carousel: pumpkins and friendly ghosts lining garden stairs, and a mantel styled with a pumpkin, ghosts and a wreath. Slides share Halloween invitation wording and a ten-day host timeline. | O31: Send your invite | P31: 6 slides | R31: US-72, US-50 | S31: Wedding Invitations Cheap: Complete Guide | Evite Invitations: Review, Features & Alternatives | T31: Posts/030_2026-10-21_Carousel_F10_Halloween-invite-wording-and-host-plan | U31: slide_01.jpg, slide_02.jpg, slide_03.jpg, slide_04.jpg, slide_05.jpg, slide_06.jpg | V31: Ready | X31: Halloween | Y31: 2026-10-31 | Z31: 10 days before | AA31: R02
A32: 31 | B32: 46317 | C32: =TEXT(B32,"ddd") -> Thu | D32: 16:30 | E32: 16:30 IST = 11:00 AM UK · 23:00 IST = 5:30 PM UK | F32: Single | G32: UK | H32: E47 | I32: Save the date: only the essentials | J32: Names, date, town. The rest can wait. | K32: The prettiest save the dates say the least. It's tempting to cram in the venue, the dress code and your entire love story. Don't. A save the date has one job: get the date into calendars before guests book their own plans. What it needs: your names, the date, the town or region, and 'Formal invitation to follow'. That's it. Pick a template that matches your season (autumn leaves, winter berries, spring blossom) and keep the wording short enough to read at a glance. Made yours already? Upload it to Lumhe and share it as one link, then send the full invitation from the same place later. Save this, and start at lumhe.com. | L32: #Lumhe #SaveTheDate #SaveTheDateUK #SaveTheDates #WeddingStationery #UKWeddings #EngagedUK #WeddingInspiration #2027Wedding #WeddingTemplates #DigitalSaveTheDate | M32: Did you send save the dates, or skip straight to invitations? | N32: Watercolour of a blank cream card propped against a vase of autumn leaves and marigolds, with a fountain pen and calendar page. Text reads: Names, date, town. The rest can wait. | O32: Send your save-the-date | P32: 1 image · 4:5 | R32: EV-E47_A | S32: New watercolour, blog topic: save-the-date-templates | T32: Posts/031_2026-10-22_Single_E47_Save-the-date-only-the-essentials | U32: post.jpg | V32: Ready | Z32: Evergreen
A33: 32 | B33: 46317 | C33: =TEXT(B33,"ddd") -> Thu | D33: 20:30 | E33: IST | F33: Carousel | G33: Global | H33: E59 | I33: Online wedding RSVP: per-function guide | J33: Five functions. Five different guest lists. | K33: Your caterer wants a number. Your inbox has twelve maybes. Online RSVP fixes that, especially for weddings with more than one function. The trick is per-function invites. Not everyone is invited to every event, and a single 'yes' to 'the wedding' tells you nothing about how many plates the Sangeet needs. Swipe for how it works, how to set up guest groups before you hit send and what to do about the people who never reply. On Lumhe, each guest sees only their functions and taps attending or not for each one. You get a live headcount per function, and guests don't need to download anything or log in. Save this for your wedding planning, share it with whoever is handling the guest list, and try it free at lumhe.com. | L33: #Lumhe #OnlineRSVP #WeddingRSVP #RSVPTracking #IndianWedding #MultiDayWedding #DestinationWedding #WeddingGuestList #WeddingFunctions #WeddingPlanner #SangeetNight #DigitalWedding | M33: How many functions is your wedding: two, five or 'don't ask'? | N33: Watercolour of a mother at a carved wooden table sorting invitation envelopes into neat piles marked with marigolds, roses and jasmine, beside a brass diya and chai. Cover text reads: Five functions. Five different guest lists. | O33: Set up your RSVP | P33: 6 slides | R33: EV-E59_A | S33: New watercolour, blog topic: online-rsvp | T33: Posts/032_2026-10-22_Carousel_E59_Online-wedding-RSVP-per-function-guide | U33: slide_01.jpg, slide_02.jpg, slide_03.jpg, slide_04.jpg, slide_05.jpg, slide_06.jpg | V33: Ready | Z33: Evergreen
A34: 33 | B34: 46318 | C34: =TEXT(B34,"ddd") -> Fri | D34: 12:30 | E34: IST | F34: Single | G34: India | H34: E09 | I34: Sister's wedding WhatsApp invite line | J34: Meri didi ki shaadi hai, aur aap sab ke bina adhoori lagegi. Please zaroor aaiye. | K34: Inviting people to your sister's wedding hits differently. You're not just sending details, you're asking people to show up for someone you love. Copy this for your WhatsApp invite: "मेरी दीदी की शादी है, और आप सब के बिना अधूरी लगेगी। प्लीज़ ज़रूर आइए।" For a younger sister: "Choti ki shaadi hai! Jo bachpan mein meri chocolate chura leti thi, ab dulhan banegi. Aap sab aaiye." Then share one Lumhe link with the card, venue and RSVP for every function. Link in bio. | L34: #Lumhe #SisterKiShaadi #DidiKiShaadi #SisterWedding #WeddingInvitationMessage #ShaadiInvite #WhatsAppInvite #IndianWedding #SiblingLove #BehenKiShaadi #ShaadiSeason2026 #DesiWedding | M34: Tag the sibling who'll cry first at the vidaai. | N34: Watercolour of a laughing bride in a red lehenga with marigold jewellery while her younger sister adjusts her dupatta. Text reads 'Meri didi ki shaadi hai, aur aap sab ke bina adhoori lagegi. Please zaroor aaiye.' with an English translation. | O34: Send the invite | P34: 1 image · 4:5 | R34: EV-E09_A | S34: New watercolour, blog topic: sister-marriage | T34: Posts/033_2026-10-23_Single_E09_Sister-s-wedding-WhatsApp-invite-line | U34: post.jpg | V34: Ready | Z34: Evergreen
A35: 34 | B35: 46318 | C35: =TEXT(B35,"ddd") -> Fri | D35: 23:00 | E35: 16:30 IST = 11:00 AM UK · 23:00 IST = 5:30 PM UK | F35: Reel | G35: UK | H35: E52 | I35: Kids' party invites: themes that work | J35: Dinosaurs, unicorns and twenty-two Year 2s | K35: The invite is where a calm kids' party actually begins. Dinosaurs, princesses, superheroes or unicorns: the theme is the fun part. The wording is what saves your sanity. For toddlers, keep it simple and tell parents to stay. For primary-age children, theme the language, give a clear drop-off and pick-up time, and ask about allergies on the invite itself. Add an RSVP date a few days before the party so you can sort the food, the party bags and the number of chairs without a last-minute scramble. With Lumhe, upload your themed invite, drop one link into the class WhatsApp and see who's coming as parents reply. Nobody needs an app or a login. Save this for the next birthday, and make yours free at lumhe.com. | L35: #Lumhe #KidsParty #KidsBirthdayParty #DinosaurParty #PrincessParty #PartyInvitations #UKMums #UKDads #KidsPartyIdeas #BirthdayInvites #ChildrensParty #PartyPlanningUK | M35: Dinosaur, princess, superhero or unicorn: what's this year's theme? | N35: Watercolour reel of a child's birthday table in a sunny hall with a dinosaur cake, a paper crown, a superhero cape and marigolds. Opening text reads: Dinosaurs, unicorns and twenty-two Year 2s. | O35: Make a party invite | P35: 15 s · 9:16 | Q35: Bouncy, playful ukulele-and-claps kids' party track with a cheeky drum hit on each cut. | R35: EV-E52_A | S35: New watercolour, blog topic: kids-party | T35: Posts/034_2026-10-23_Reel_E52_Kids-party-invites-themes-that-work | U35: reel.mp4, reel_cover.jpg | V35: Ready | Z35: Evergreen
A36: 35 | B36: 46319 | C36: =TEXT(B36,"ddd") -> Sat | D36: 12:30 | E36: IST | F36: Carousel | G36: India | H36: E05 | I36: Gujarati kankotri wording and functions | J36: Gujarati card wording, tahuko and all | K36: First kankotri to Ganpati Bappa. The next 400? WhatsApp. A Gujarati kankotri is warm, detailed and a little poetic. It often opens with a tahuko, lists every function from Mandvo to Hast Melap, and closes with a heartfelt request to come with family. Swipe for: • Why the first card is offered to Ganesh • What a tahuko is and where it goes • A Gujarati closing line, with meaning • The function list most families print Tip: put the raas-garba night on its own line with a dress note. Guests will ask anyway. Save this for your kankotri meeting. Then upload the card to Lumhe and share one link with an RSVP for each function. Link in bio. | L36: #Lumhe #GujaratiWedding #Kankotri #GujaratiLagna #Tahuko #RaasGarba #Panetar #AhmedabadWeddings #SuratWeddings #GujjuWedding #WeddingCardWording #ShubhLagna #DandiyaNight | M36: Raas-garba night or Mandvo: which function does your family go biggest on? | N36: Watercolour carousel: a kankotri on a brass plate with kumkum and marigolds before a small Ganesh idol, and a raas-garba night with dancers holding dandiya sticks under bandhani drapes and fairy lights. Slides share Gujarati kankotri wording. | O36: Share your kankotri | P36: 6 slides | R36: EV-E05_A, EV-E05_B | S36: New watercolour, blog topic: gujarati | New watercolour, blog topic: gujarati | T36: Posts/035_2026-10-24_Carousel_E05_Gujarati-kankotri-wording-and-functions | U36: slide_01.jpg, slide_02.jpg, slide_03.jpg, slide_04.jpg, slide_05.jpg, slide_06.jpg | V36: Ready | Z36: Evergreen
A37: 36 | B37: 46319 | C37: =TEXT(B37,"ddd") -> Sat | D37: 21:30 | E37: 19:30 IST = 9:00 AM ET · 21:30 IST = 11:00 AM ET | F37: Single | G37: USA | H37: E32 | I37: Slumber party pickup time tip | J37: Put pickup time on the invite, not just drop-off | K37: Kids care about popcorn and pillow forts. Parents care about logistics. A slumber party invite gets quick yeses when it answers the parent questions up front: drop-off time, pickup time, what to pack, and who to call about allergies. Wording to borrow: "PJs on, pillows packed! Join us for movies, snacks and giggles. Drop-off 6 p.m., pickup 9 a.m. with pancakes." Send it on Lumhe and parents can RSVP in a tap, no app needed. Make yours free at lumhe.com. | L37: #Lumhe #SlumberParty #SleepoverParty #PajamaParty #KidsSleepover #KidsPartyIdeas #BirthdaySleepover #MomLife #PartyPlanningTips #BlanketFort #KidsBirthdayInvite | M37: Sleepover hosts: what time is a fair pickup, 9 or 10 a.m.? | N37: Watercolor of a fairy-lit blanket fort with sleeping bags, pillows, popcorn and a teddy bear. Text reads 'Put pickup time on the invite, not just drop-off' with a tip for parents. | O37: Make your invite | P37: 1 image · 4:5 | R37: EV-E32_A | S37: New watercolour, blog topic: slumber-party | T37: Posts/036_2026-10-24_Single_E32_Slumber-party-pickup-time-tip | U37: post.jpg | V37: Ready | Z37: Evergreen
A38: 37 | B38: 46320 | C38: =TEXT(B38,"ddd") -> Sun | D38: 19:30 | E38: 19:30 IST = 9:00 AM ET · 21:30 IST = 11:00 AM ET | F38: Carousel | G38: USA | H38: E33 | I38: Dinner party invite wording by vibe | J38: Pick the vibe, then the words | K38: A dinner party starts the moment your guests read the invite. The wording tells them everything before they arrive: how dressed up to get, whether to bring a bottle, and if it's three courses or one big pot of pasta. Swipe for wording you can copy: • Formal, for candles and courses • Casual, for a weeknight pasta night • Themed, for a supper club with a destination • A quick checklist so no detail goes missing Tip: ask about dietary needs in the invite, not the night before. Save this for your next dinner. Then send the invite on Lumhe, see who's coming and gather everyone's photos from the night in one album. Link in bio. | L38: #Lumhe #DinnerParty #DinnerPartyIdeas #HostingAtHome #SupperClub #TableSetting #DinnerPartyInvitation #FriendsDinner #EntertainingAtHome #TablescapeInspo #HomeHosting #PartyInvites | M38: Your dinner party style: formal courses, pasta night or themed supper club? | N38: Watercolor carousel: friends' hands passing bread over a candlelit dinner table, and a close-up of a place setting with a rosemary-tied napkin and a marigold bud vase. Slides share dinner party invitation wording for every vibe. | O38: Host your dinner | P38: 6 slides | R38: EV-E33_A, EV-E33_B | S38: New watercolour, blog topic: dinner-party | New watercolour, blog topic: dinner-party | T38: Posts/037_2026-10-25_Carousel_E33_Dinner-party-invite-wording-by-vibe | U38: slide_01.jpg, slide_02.jpg, slide_03.jpg, slide_04.jpg, slide_05.jpg, slide_06.jpg | V38: Ready | Z38: Evergreen
A39: 38 | B39: 46320 | C39: =TEXT(B39,"ddd") -> Sun | D39: 23:00 | E39: 16:30 IST = 11:00 AM UK · 23:00 IST = 5:30 PM UK | F39: Single | G39: UK | H39: E49 | I39: DIY invite: the thumbnail test | J39: Shrink it to thumbnail size. Still readable? | K39: Lovely on your laptop doesn't always mean lovely in a WhatsApp preview. When you design your own invitation, you see it big and beautiful. Your guests see it as a little thumbnail in a busy chat. Before you send, zoom out until it's postage-stamp sized. Can you still read the names and the date? If not, go bigger on those and lighter on the flourishes. Also: keep strong contrast, and avoid pale lettering on a pale wash. Happy with it? Upload your design (image, PDF or video) to Lumhe and share it as one link, with RSVPs built in. Save this for your next DIY invite and start at lumhe.com. | L39: #Lumhe #DIYInvitations #DesignYourOwn #InvitationDesign #HandmadeInvites #UKWeddings #CanvaDesign #DIYWedding #PartyInvitationsUK #CreativeUK #StationeryLove | M39: What's your go-to tool for designing invites? | N39: Watercolour of a craft table with paints, a half-painted floral invitation card under a magnifying glass, brushes in a jam jar and tea. Text reads: Shrink it to thumbnail size. Still readable? | O39: Upload your design | P39: 1 image · 4:5 | R39: EV-E49_A | S39: New watercolour, blog topic: design-your-own | T39: Posts/038_2026-10-25_Single_E49_DIY-invite-the-thumbnail-test | U39: post.jpg | V39: Ready | Z39: Evergreen
A40: 39 | B40: 46321 | C40: =TEXT(B40,"ddd") -> Mon | D40: 12:30 | E40: IST | F40: Single | G40: India | H40: E10 | I40: Reception-only guest message | J40: Reception-only guests deserve their own message | K40: Not everyone comes for the pheras, and that's completely fine. Office colleagues, neighbours and Papa's business friends usually get a reception-only invite. Give them a message that feels personal, not a forwarded card with five functions they aren't attending. Another line to borrow: "Aap humare reception mein aaiye, khushiyan double ho jayengi." With Lumhe's per-function RSVP, reception guests see only the reception, and you get a separate headcount for the caterer. Create your event free, link in bio. | L40: #Lumhe #WeddingReception #ReceptionInvite #ReceptionNight #IndianWeddingReception #WeddingInvitationMessage #ShaadiReception #WeddingRSVP #IndianWeddings #ShaadiSeason #BigFatIndianWedding | M40: Reception or pheras: which do you actually enjoy more as a guest? | N40: Watercolour of a couple in a sherwani and lehenga on a marigold-framed reception stage with fairy lights. Text reads 'Reception-only guests deserve their own message' with a sample invite line. | O40: Create your event | P40: 1 image · 4:5 | R40: EV-E10_A | S40: New watercolour, blog topic: reception-invitation-messages | T40: Posts/039_2026-10-26_Single_E10_Reception-only-guest-message | U40: post.jpg | V40: Ready | Z40: Evergreen
A41: 40 | B41: 46321 | C41: =TEXT(B41,"ddd") -> Mon | D41: 23:00 | E41: 16:30 IST = 11:00 AM UK · 23:00 IST = 5:30 PM UK | F41: Carousel | G41: UK | H41: F12 | I41: Bonfire Night garden party guide | J41: Fireworks night, planned before the first spark | K41: Sparklers bought? Guest list next. 🎆 Whether you're lighting a small bonfire at home or meeting friends at the local display, a clear invite saves the "what time?" texts and helps you buy the right number of sausages. Swipe for: • Wording for a garden bonfire • Wording for a park display meet-up • A safety-first host checklist (hedgehogs included) • What to serve round the fire Send it all as one Lumhe link. No app, no login; guests just tap and reply. Afterwards, everyone's sparkler shots go into one Moments album. Save this for later and share it with whoever's in charge of the matches. Link in bio. | L41: #Lumhe #BonfireNight #GuyFawkesNight #Bonfire2026 #FireworksNight #RememberRemember #5thNovember #ToffeeApples #Parkin #GardenParty #UKEvents #AutumnEvenings #SparklerSeason | M41: Garden bonfire or the big park display? Which is your 5 November tradition? | N41: Watercolour carousel: friends in coats and scarves around a garden bonfire under soft fireworks, and a garden table with toffee apples, hot chocolate, a tartan blanket and sparklers. Slides share Bonfire Night invite wording and a safety checklist. | O41: Send your invite | P41: 6 slides | R41: PAIR-BON_A, PAIR-BON_B | S41: New watercolour, blog topic: festival | New watercolour, blog topic: festival | T41: Posts/040_2026-10-26_Carousel_F12_Bonfire-Night-garden-party-guide | U41: slide_01.jpg, slide_02.jpg, slide_03.jpg, slide_04.jpg, slide_05.jpg, slide_06.jpg | V41: Ready | X41: Bonfire Night | Y41: 2026-11-05 | Z41: 10 days before | AA41: F13
A42: 41 | B42: 46322 | C42: =TEXT(B42,"ddd") -> Tue | D42: 12:30 | E42: IST | F42: Carousel | G42: India | H42: F15 | I42: Dhanteras puja and gifting guide | J42: Diwali week starts with Dhanteras. Plan it. | K42: Silver coin, new steel kadhai, a row of fresh diyas. ✨ Dhanteras is when the festive shopping lists come out. If you're doing a small puja and dinner for family, it's also the first invite of Diwali week. Swipe for: • The traditional Dhanteras shopping list • Hindi-English invite wording for a puja at home • A doorstep diya and rangoli idea • Gifts that suit the day On Lumhe, put Dhanteras, Diwali and Bhai Dooj under one link, track who's coming each evening, and let family abroad send shagun through Digital Lifafa, straight to your UPI. Save this and share it with whoever handles the family shopping. Link in bio. | L42: #Lumhe #Dhanteras2026 #Dhanteras #DhanterasShopping #DiwaliWeek #DhanterasPuja #LakshmiPuja #SilverCoin #DiwaliPrep #FestiveGifting #DiwaliDecor #IndianFestivals2026 | M42: What does your family always buy on Dhanteras: gold, silver, utensils or a new broom? | N42: Watercolour carousel: a mother and daughter placing lit diyas on a doorstep beside a footprint rangoli and marigold toran, and new brass utensils, a silver coin and a gold bangle on red cloth. Slides share Dhanteras invite wording and gifting ideas. | O42: Plan Diwali week | P42: 6 slides | R42: PAIR-DHA_A, PAIR-DHA_B | S42: New watercolour, blog topic: festival | New watercolour, blog topic: festival | T42: Posts/041_2026-10-27_Carousel_F15_Dhanteras-puja-and-gifting-guide | U42: slide_01.jpg, slide_02.jpg, slide_03.jpg, slide_04.jpg, slide_05.jpg, slide_06.jpg | V42: Ready | X42: Dhanteras | Y42: 2026-11-06 | Z42: 10 days before | AA42: F16
A43: 42 | B43: 46322 | C43: =TEXT(B43,"ddd") -> Tue | D43: 21:30 | E43: 19:30 IST = 9:00 AM ET · 21:30 IST = 11:00 AM ET | F43: Single | G43: USA | H43: E35 | I43: Catholic wedding: Mass or ceremony | J43: Nuptial Mass or ceremony? Say which on the invite. | K43: Guests plan their whole day around how long church takes. A Nuptial Mass includes readings, a homily and the Eucharist, and usually lasts 45 to 60 minutes. A Catholic ceremony without Mass is closer to 20 to 30. Non-Catholic guests especially appreciate knowing which to expect. Wording sample: 'request the honor of your presence at the celebration of their marriage with Nuptial Mass, [Parish Name] Church.' List the church name and full address, the start time, and the reception venue separately if it's somewhere else. Sending digitally too? Upload your invitation to Lumhe and share one link, with ceremony and reception as separate RSVPs. Save this for your wedding binder, and visit lumhe.com. | L43: #Lumhe #CatholicWedding #ChurchWedding #NuptialMass #WeddingInvitations #WeddingWording #FaithAndLove #BrideToBe #WeddingPlanning #InvitationWording #SacramentOfMarriage | M43: Did your wedding include a full Mass or a shorter ceremony? | N43: Watercolor of an arched stone church doorway framed with white flowers and marigold garlands, rose petals on the steps. Text reads: Nuptial Mass or ceremony? Say which on the invite. | O43: Create your invite free | P43: 1 image · 4:5 | R43: EV-E35_A | S43: New watercolour, blog topic: catholic-wedding | T43: Posts/042_2026-10-27_Single_E35_Catholic-wedding-Mass-or-ceremony | U43: post.jpg | V43: Ready | Z43: Evergreen
A44: 43 | B44: 46323 | C44: =TEXT(B44,"ddd") -> Wed | D44: 12:30 | E44: IST | F44: Reel | G44: India | H44: F08 | I44: Karva Chauth eve reminder reel | J44: Moonrise tomorrow. Sieve ready? | K44: Tomorrow, the whole group will be staring at the sky. Make sure they're on the same terrace. 🌙 If you're hosting the Karva Chauth katha or a moonrise get-together, send the invite tonight, while everyone is still at the mehendi stage and has a free hand (well, half of one). Put the address, the katha plan and dinner after moonrise in one Lumhe link. Friends RSVP in a tap, no app needed, and you'll know exactly how many plates to set. Once the moon shows up, everyone's sieve photos land in one Moments album, not scattered across ten chats. Wishing every fasting heart strength tomorrow. Make your invite free, link in bio. | L44: #Lumhe #KarvaChauthTomorrow #KarwaChauth2026 #MoonriseWait #KarvaChauthReels #MehendiLove #VratKatha #FestiveReels #ChaandKaIntezaar #FestiveCouple #SargiThali | M44: Whose moon shows up first in your family group? Let's compare cities 🌙 | N44: Watercolour reel: a woman in a red saree raising a sieve to the moon on a rooftop beside her husband, and hennaed hands holding a puja thali with a karva and diya. Text reminds hosts to send their Karva Chauth invite tonight. | O44: Make your invite | P44: 15 s · 9:16 | Q44: Soft, romantic folk-pop with dholak and a gentle build, warm and devotional rather than clubby. | R44: PAIR-KC_A, PAIR-KC_B | S44: New watercolour, blog topic: festival | New watercolour, blog topic: festival | T44: Posts/043_2026-10-28_Reel_F08_Karva-Chauth-eve-reminder-reel | U44: reel.mp4, reel_cover.jpg | V44: Ready | X44: Karva Chauth | Y44: 2026-10-29 | Z44: Reminder (1-2 days) | AA44: F07
A45: 44 | B45: 46323 | C45: =TEXT(B45,"ddd") -> Wed | D45: 23:00 | E45: 16:30 IST = 11:00 AM UK · 23:00 IST = 5:30 PM UK | F45: Carousel | G45: UK | H45: C04 | I45: RSVP meaning and getting replies | J45: It means reply. Yes or no. | K45: Here's a tiny etiquette secret: "Please RSVP" says please twice. RSVP is short for répondez s'il vous plaît, French for "please reply". It isn't a nice-to-have. A reply, yes or no, is how your caterer, seating plan and evening buffet get planned. Swipe for: • What RSVP actually asks of guests • What "regrets only" means • Wording that gets people to reply • How to chase late replies without making it awkward Save this for your invitation draft, and send it to the friend who still hasn't replied to yours. 👀 Lumhe guests reply from one link, with no app and no login. Link in bio. | L45: #Lumhe #RSVP #RSVPEtiquette #WeddingEtiquette #UKWedding #PartyPlanningUK #InvitationWording #GuestList #WeddingAdviceUK #HostingTips #EtiquetteTips #DigitalRSVP | M45: Honestly: how long did it take you to reply to the last invite you got? | N45: Watercolour carousel: a red tray with a patterned card and fountain pen, and hands holding a tablet with a template grid. Slides explain what RSVP means and how to get guests to reply. | O45: Get replies faster | P45: 6 slides | R45: UK-68, US-38 | S45: What Does RSVP Mean? Complete Guide to RSVP Etiquette | What Does RSVP Mean | T45: Posts/044_2026-10-28_Carousel_C04_RSVP-meaning-and-getting-replies | U45: slide_01.jpg, slide_02.jpg, slide_03.jpg, slide_04.jpg, slide_05.jpg, slide_06.jpg | V45: Ready | Z45: Blog image
A46: 45 | B46: 46324 | C46: =TEXT(B46,"ddd") -> Thu | D46: 12:30 | E46: IST | F46: Single | G46: India | H46: F09 | I46: Karva Chauth day greeting | J46: To every heart waiting on the moon tonight | K46: Happy Karva Chauth to every fasting heart tonight. 🌙 From the sargi before dawn to the first glimpse of the moon through the channi, today is a quiet, beautiful promise. May your vrat be easy, your evening joyful and your togetherness last a lifetime. And to everyone carrying the water up to the terrace: you're part of the story too. With love from team Lumhe. Save tonight's photos in a Moments album, not just the camera roll. | L46: #Lumhe #HappyKarvaChauth #KarvaChauthWishes #KarwaChauthGreetings #KarvaChauthMoon #ForeverTogether #LoveAndFaith #IndianTraditions #FestiveGreetings #MoonlightPromise | M46: Send this to the couple whose terrace selfie you're waiting for tonight 🌙 | N46: Watercolour of hennaed hands holding a decorated sieve that frames a glowing moon, with a clay karva and a diya on a terrace ledge. Text reads 'Happy Karva Chauth: To every heart waiting on the moon tonight.' | O46: Send the wish | P46: 1 image · 4:5 | R46: DAY-KC_A | S46: New watercolour, blog topic: festival | T46: Posts/045_2026-10-29_Single_F09_Karva-Chauth-day-greeting | U46: post.jpg | V46: Ready | X46: Karva Chauth | Y46: 2026-10-29 | Z46: On the day
A47: 46 | B47: 46324 | C47: =TEXT(B47,"ddd") -> Thu | D47: 19:00 | E47: IST | F47: Carousel | G47: India | H47: F18 | I47: Diwali hosting countdown, ten days out | J47: Your Diwali hosting plan, ten days out | K47: The calm Diwali hosts start planning about now. Diwali falls on 8 November this year, and the last week always disappears into cleaning, shopping and mithai runs. Get the big decisions out of the way first. This carousel gives you a simple countdown: • Day 10: pick the format and count your guests • Day 9: send the invite (puja and party wording included) • Day 7: sort gift hampers for family, friends and colleagues • Final 3 days: the checklist that saves the evening Make it one Lumhe link: guests RSVP without an app or login, you see who's coming, and everyone's photos land in a Moments album that never expires. Add Digital Lifafa so relatives who can't make it can still send their gift by UPI, directly to your UPI ID. Save this, and send it to whoever is hosting at your place this year. Link in bio. 🪔 | L47: #Lumhe #Diwali2026 #DiwaliHosting #DiwaliPlanning #DiwaliInvite #LakshmiPujan #DiwaliGiftHampers #DiwaliPartyIdeas #Deepavali2026 #FestiveHosting #DigitalLifafa #DiwaliDecor #IndianFestivals | M47: Puja only, or puja plus a full party? What's the plan at your home this Diwali? | N47: Carousel cover with a watercolour of an elderly couple on a swing with their grandchildren, and the text 'Your Diwali hosting plan, ten days out'. Another slide shows three women in red sarees laughing together. | O47: Plan your Diwali | P47: 6 slides | R47: IN-5, UK-65 | S47: Wedding Anniversary Wishes: Heartfelt Messages | Invitation Template: Complete Guide | T47: Posts/046_2026-10-29_Carousel_F18_Diwali-hosting-countdown-ten-days-out | U47: slide_01.jpg, slide_02.jpg, slide_03.jpg, slide_04.jpg, slide_05.jpg, slide_06.jpg | V47: Ready | X47: Diwali | Y47: 2026-11-08 | Z47: 10 days before | AA47: R03
A48: 47 | B48: 46325 | C48: =TEXT(B48,"ddd") -> Fri | D48: 16:30 | E48: 16:30 IST = 11:00 AM UK · 23:00 IST = 5:30 PM UK | F48: Single | G48: UK | H48: E50 | I48: Myth: hashtags collect wedding photos | J48: Myth: a wedding hashtag will collect every photo | K48: Your nan won't hashtag anything. Neither will plenty of your guests. A wedding hashtag feels like the easy answer, but it only catches photos from guests who post publicly, remember the spelling and have open accounts. Everything else stays on their phones. What most couples actually want: one private place, easy for every guest, that doesn't disappear like a Story and isn't squashed like a WhatsApp forward. That's Moments on Lumhe. Guests open your invite link, tap upload and add their photos in full quality. No app, no login, and the album stays put. Where did your guests' photos end up? Tell us below, then start an album free at lumhe.com. | L48: #Lumhe #WeddingPhotos #WeddingHashtag #UKWedding #GuestPhotos #WeddingPhotoSharing #WeddingMemories #PrivateAlbum #UKBride2027 #MomentsByLumhe #WeddingDayUK | M48: Did you use a wedding hashtag? Did it actually work? | N48: Watercolour of a country-house wedding reception at dusk, guests laughing beside champagne flutes, a vintage camera, white roses and marigolds. Text reads: Myth: a wedding hashtag will collect every photo. | O48: Start your album | P48: 1 image · 4:5 | R48: EV-E50_A | S48: New watercolour, blog topic: photo-sharing-apps-uk | T48: Posts/047_2026-10-30_Single_E50_Myth-hashtags-collect-wedding-photos | U48: post.jpg | V48: Ready | Z48: Evergreen
A49: 48 | B49: 46325 | C49: =TEXT(B49,"ddd") -> Fri | D49: 21:30 | E49: 19:30 IST = 9:00 AM ET · 21:30 IST = 11:00 AM ET | F49: Reel | G49: USA | H49: R02 | I49: Halloween party invite with live headcount | J49: Halloween is Saturday. Invites aren't out. | K49: Two days to Halloween, and still no costume decision? The group chat keeps asking "wait, is it costumes?" Here's a last-minute invite you can steal: "Creeps & Cocktails at the Rivera house. Saturday, October 31, 7 PM. Costumes mandatory, fear optional. Tell us if you're coming before the ghosts do." Three details guests always need: • Is it costume-required or costume-optional? • Is it kid-friendly or after-dark grown-ups only? • Should they bring anything (a dish, a carved pumpkin, a scary playlist)? Upload your design to Lumhe, share one link by text or email, and watch RSVPs roll in on a live headcount. You'll know exactly how much candy and punch to buy. Create your Halloween invite free. Link in bio. 🎃 | L49: #Lumhe #HalloweenParty #HalloweenInvite #Halloween2026 #CostumeParty #SpookySeason #HalloweenDecor #PartyHost #OnlineInvitations #RSVP #LastMinuteParty #HalloweenAtHome | M49: Costume-required or costume-optional? Settle it in the comments. | N49: Reel alternating watercolor scenes of pumpkins and ghosts lining garden stairs and a mantel with a pumpkin, ghosts and a wreath, with text about sending a Halloween invite and tracking RSVPs live. | O49: Make my Halloween invite | P49: 15 s · 9:16 | Q49: Playful spooky synth or theremin-style trending audio with a bouncy beat; campy, not horror. | R49: US-72, US-50 | S49: Wedding Invitations Cheap: Complete Guide | Evite Invitations: Review, Features & Alternatives | T49: Posts/048_2026-10-30_Reel_R02_Halloween-party-invite-with-live-headcou | U49: reel.mp4, reel_cover.jpg | V49: Ready | X49: Halloween | Y49: 2026-10-31 | Z49: Reminder (1-2 days) | AA49: F10
A50: 49 | B50: 46326 | C50: =TEXT(B50,"ddd") -> Sat | D50: 12:30 | E50: IST | F50: Carousel | G50: India | H50: C35 | I50: Bhai Dooj rituals wishes and lifafa | J50: Tilak, mithai and shagun across the miles | K50: Bhai Dooj hits differently when your sibling is in another city. The tilak, the aarti, the mithai, the playful bargaining over gifts: some of it travels well over a video call, and some of it needs a little planning. This carousel covers: • What the ritual involves, and its names across India • Wishes in Hindi, Marathi and English • Gift ideas that don't need a courier • How to do a video-call Bhai Dooj without chaos If you're hosting the family lunch, make it one Lumhe link: invite, RSVP and a Moments album for the tilak photos. Turn on Digital Lifafa and siblings who couldn't come can send shagun by UPI, straight to your UPI ID. Tag your bhai or behen, and save this for next year too. 🪔 | L50: #Lumhe #BhaiDooj #BhaiDooj2026 #BhauBeej #BhaiPhonta #SiblingLove #BhaiBehen #Tilak #DigitalLifafa #Shagun #UPI #IndianFestivals #DiwaliWeek | M50: Bhai Dooj, Bhau Beej or Bhai Phonta: what do you call it at home? | N50: Carousel cover showing a watercolour of a sister applying tilak to her brother on a rangoli, with the text 'Tilak, mithai and shagun across the miles'. | O50: Add Digital Lifafa | P50: 6 slides | R50: UK-64 | S50: Meaning Of Rsvp In Invitation: Complete Guide | T50: Posts/049_2026-10-31_Carousel_C35_Bhai-Dooj-rituals-wishes-and-lifafa | U50: slide_01.jpg, slide_02.jpg, slide_03.jpg, slide_04.jpg, slide_05.jpg, slide_06.jpg | V50: Ready | X50: Bhai Dooj | Y50: 2026-11-10 | Z50: 10 days before | AA50: F19
A51: 50 | B51: 46326 | C51: =TEXT(B51,"ddd") -> Sat | D51: 21:30 | E51: 19:30 IST = 9:00 AM ET · 21:30 IST = 11:00 AM ET | F51: Single | G51: USA | H51: F11 | I51: Halloween night greeting | J51: May your candy bowl never run empty tonight | K51: Porch light on, candy bowl full, costume (mostly) finished. 🎃 Happy Halloween from all of us at Lumhe! To the parents walking the block, the hosts stringing up cobwebs and the neighbor handing out full-size bars: you're the real heroes of tonight. Stay safe, stay sticky and snap plenty of photos. Hosting tonight? A Lumhe Moments album keeps every guest's photos in one place. | L51: #Lumhe #HappyHalloween #Halloween #TrickOrTreating #HalloweenNight #JackOLantern #SpookyFun #HalloweenCostumes #CandyBowl #FamilyFun #October31 | M51: What's the best costume that knocked on your door tonight? 👻 | N51: Watercolor of a twilight front porch with jack-o'-lanterns, a candy bowl, a witch hat on the door and a child in a bedsheet ghost costume reaching for a treat. Text reads 'Happy Halloween: May your candy bowl never run empty tonight.' | O51: Share the fun | P51: 1 image · 4:5 | R51: DAY-HAL_A | S51: New watercolour, blog topic: festival | T51: Posts/050_2026-10-31_Single_F11_Halloween-night-greeting | U51: post.jpg | V51: Ready | X51: Halloween | Y51: 2026-10-31 | Z51: On the day
A52: 51 | B52: 46327 | C52: =TEXT(B52,"ddd") -> Sun | D52: 13:00 | E52: IST | F52: Carousel | G52: Global | H52: C12 | I52: Engagement captions and hashtags | J52: Captions for the ring reveal | K52: The ring is on. Now the caption needs to land too. You've got one shot at the ring post, and "Engaged!!!" with twelve exclamation marks is a valid choice. If you want options, we've written some: short ones, funny ones and proposal-story ones, plus how to make a couple hashtag that's actually yours. One tip before you post: tell your parents and grandparents first. Nobody wants to find out from Instagram. 😉 Save this for the big moment, or send it to the friend who's about to pop the question. Once the congratulations calm down, the save the date comes next, and Lumhe can help with that. Link in bio. | L52: #Lumhe #EngagementCaptions #SheSaidYes #Engaged #EngagementRing #RingSelfie #JustEngaged #PutARingOnIt #EngagementAnnouncement #CoupleHashtag #FutureMrsAndMr #InstagramCaptions #ProposalStory | M52: Drop your couple hashtag idea below and we'll rate the pun. | N52: Watercolour carousel of a couple holding hands to show an engagement ring. Slides offer engagement caption ideas and tips for creating a couple hashtag. | O52: Plan what's next | P52: 6 slides | R52: US-35 | S52: Party Invitations - Complete Guide | T52: Posts/051_2026-11-01_Carousel_C12_Engagement-captions-and-hashtags | U52: slide_01.jpg, slide_02.jpg, slide_03.jpg, slide_04.jpg, slide_05.jpg, slide_06.jpg | V52: Ready | Z52: Blog image
A53: 52 | B53: 46327 | C53: =TEXT(B53,"ddd") -> Sun | D53: 20:30 | E53: IST | F53: Reel | G53: Global | H53: E56 | I53: Send digital invites with RSVP tracking | J53: Sent 80 invites. Got 6 replies. | K53: Digital invites are easy. Knowing who's actually coming is the hard part. Emailing a PDF gets the invite out, but then replies trickle in through texts, emails and 'oh, I meant to tell you' in the hallway at work. The fix is an invite with RSVP built in: 1. Upload the design you already made, or design one. 2. Add each event if there's more than one. 3. Share one link on WhatsApp, text or email. 4. Watch replies land in one live headcount. Guests don't download anything or create an account, which is exactly why they reply. That's how Lumhe works, and it's free. Save this reel and send your next invite from lumhe.com. | L53: #Lumhe #DigitalInvitations #RSVPTracking #OnlineInvites #EventPlanningTips #PartyPlanning #SendInvites #EventHost #RSVP #PlanningHacks #EInvite | M53: What's the longest you've waited for an RSVP? | N53: Watercolor reel of a host at a kitchen counter with a laptop, envelopes pushed aside and marigolds, then a close-up of a ribbon-tied invitation and a softly glowing phone. Opening text reads: Sent 80 invites. Got 6 replies. | O53: Send your invite free | P53: 15 s · 9:16 | Q53: Upbeat lo-fi pop beat with a satisfying click or pop sound on each step reveal. | R53: EV-E56_A, EV-E56_B | S53: New watercolour, blog topic: send-digital-invitations | New watercolour, blog topic: send-digital-invitations | T53: Posts/052_2026-11-01_Reel_E56_Send-digital-invites-with-RSVP-tracking | U53: reel.mp4, reel_cover.jpg | V53: Ready | Z53: Evergreen
A54: 53 | B54: 46328 | C54: =TEXT(B54,"ddd") -> Mon | D54: 12:30 | E54: IST | F54: Single | G54: India | H54: E11 | I54: One-line wedding invitation message | J54: Two families, one mandap, and a seat saved just for you. | K54: Sometimes the shortest invite says the most. Not every guest needs a paragraph. For the WhatsApp message that goes with your card, try one of these: • "Hum shaadi kar rahe hain! Aapke bina kaise?" • "Save the date, bring the dancing shoes." • "Mandap ready, mithai ready. Bas aapka intezaar hai." Pair your one-liner with one Lumhe link that holds the card, venue map and RSVP for every function. Create yours free, link in bio. | L54: #Lumhe #WeddingInvitationMessage #ShortWeddingWishes #WeddingOneLiners #ShaadiCard #IndianWeddingInvite #WhatsAppWeddingInvite #MandapDecor #ShaadiVibes #DigitalShaadiCard #WeddingSeasonIndia | M54: Write your shaadi invite in one line. Best one gets pinned. | N54: Watercolour of a mandap corner with hanging marigolds, a brass kalash with mango leaves and two empty ornate chairs. Text reads 'Two families, one mandap, and a seat saved just for you.' | O54: Send your invite | P54: 1 image · 4:5 | R54: EV-E11_A | S54: New watercolour, blog topic: short-wedding-invitation | T54: Posts/053_2026-11-02_Single_E11_One-line-wedding-invitation-message | U54: post.jpg | V54: Ready | Z54: Evergreen
A55: 54 | B55: 46328 | C55: =TEXT(B55,"ddd") -> Mon | D55: 23:00 | E55: 16:30 IST = 11:00 AM UK · 23:00 IST = 5:30 PM UK | F55: Single | G55: UK | H55: S12 | I55: Check addresses before Christmas cards | J55: Check addresses before you write a single card | K55: Card season creeps up fast; start the list now. A little November admin saves a lot of December stress: • Pull last year's list and check who's moved • Write cards in batches of ten, with a cuppa • Post overseas cards first; they take longest For friends abroad or anyone whose address you can't confirm, a digital greeting arrives the same day and can't get lost in the post. Hosting a festive get-together too? Send the invite as one Lumhe link with RSVP. Save this for your December to-do list. | L55: #Lumhe #ChristmasCards #HolidayCards #ChristmasPrep #FestiveSeason #CardWriting #ChristmasPlanning #Stationery #SnailMail #UKChristmas #OrganisedChristmas | M55: How many cards do you send each year: a handful, or the whole street? | N55: Watercolour fan of green and pink holiday cards. Text reads: Card season tip, Check addresses before you write a single card. | O55: Send a digital greeting | P55: 1 image · 4:5 | R55: UK-19 | S55: Christmas & Holiday Party Invitations: Wording & Ideas | T55: Posts/054_2026-11-02_Single_S12_Check-addresses-before-Christmas-cards | U55: post.jpg | V55: Ready | Z55: Blog image
A56: 55 | B56: 46329 | C56: =TEXT(B56,"ddd") -> Tue | D56: 12:30 | E56: IST | F56: Carousel | G56: India | H56: E06 | I56: Nikah invitation wording and order | J56: Nikah invitation wording, in order | K56: Bismillah at the top, Walima at the end, family in between. A Nikah invitation in India blends Islamic tradition with family warmth. It opens with Bismillah, names the families with respect, and gives clear details for each function, from Manjha and Mehndi to the Nikah and Walima. Swipe for: • What goes at the top • An English line from the bride's parents • An Urdu-style closing line, with meaning • Why the Walima often gets its own invite Tip: write the Nikah time and the Walima date in the same format, so no one mixes them up. Save this for your card draft. Then upload the invitation to Lumhe and share one link with a separate RSVP for the Nikah and Walima. Link in bio. | L56: #Lumhe #NikahInvitation #MuslimWedding #NikahCard #Walima #IndianMuslimWedding #Mehndi #HyderabadiWedding #LucknowWedding #WeddingCardWording #Nikah #ShaadiCard #WeddingInvitationIndia | M56: Do you send one card for all functions, or a separate Walima card? | N56: Watercolour carousel: a courtyard with arches strung with marigold and jasmine, lanterns and a couple seated on a low stage, and an ornate card with an arch motif on a tray with dates, an attar bottle and rose petals. Slides share Nikah invitation wording. | O56: Upload your Nikah card | P56: 6 slides | R56: EV-E06_A, EV-E06_B | S56: New watercolour, blog topic: Muslim_Wedding | New watercolour, blog topic: Muslim_Wedding | T56: Posts/055_2026-11-03_Carousel_E06_Nikah-invitation-wording-and-order | U56: slide_01.jpg, slide_02.jpg, slide_03.jpg, slide_04.jpg, slide_05.jpg, slide_06.jpg | V56: Ready | Z56: Evergreen
A57: 56 | B57: 46329 | C57: =TEXT(B57,"ddd") -> Tue | D57: 21:30 | E57: 19:30 IST = 9:00 AM ET · 21:30 IST = 11:00 AM ET | F57: Single | G57: USA | H57: E36 | I57: Diaper party: ask for sizes | J57: Ask for size 1 and up, not just newborn | K57: Dad's turn to throw the baby party, and he wants a grill. A diaper party is the laid-back cousin of the baby shower: backyard, burgers, maybe the game on, and every guest brings a pack of diapers or wipes. The one detail that makes it useful: list sizes on the invite. Newborn diapers get outgrown in a blink, so ask for a mix of sizes 1 to 3. Wording to steal: 'Beer, burgers and a baby on the way. Bring a pack of diapers (size 1 or up) and your appetite.' Make the invite on Lumhe, share one link and see who's coming without chasing the group text. Tag the dad-to-be, and start free at lumhe.com. | L57: #Lumhe #DiaperParty #DadToBe #BabyShowerForDad #CoedBabyShower #BabyOnTheWay #BackyardParty #NewDad #BabyShowerIdeas #PartyInvitationsUSA #DiaperShower | M57: Dads: shower, diaper party or no party at all? | N57: Watercolor of a backyard grill party with burgers, a diaper-pack cake tied with ribbon, a cooler and marigolds under string lights. Text reads: Ask for size 1 and up, not just newborn. | O57: Plan the diaper party | P57: 1 image · 4:5 | R57: EV-E36_A | S57: New watercolour, blog topic: diaper-party | T57: Posts/056_2026-11-03_Single_E36_Diaper-party-ask-for-sizes | U57: post.jpg | V57: Ready | Z57: Evergreen
A58: 57 | B58: 46330 | C58: =TEXT(B58,"ddd") -> Wed | D58: 12:30 | E58: IST | F58: Carousel | G58: India | H58: F21 | I58: Chhath Puja family plan, ten days out | J58: Four days, one ghat, the whole family | K58: Chhath brings everyone home. A little planning keeps it peaceful. For many families, Chhath is the one time of year the whole khandaan is back under one roof. That means train tickets, beds, ghat logistics and a lot of thekua. Swipe for: • The four days of Chhath, in order • A travel checklist for everyone coming home • Invite wording for the family WhatsApp group • What to carry to the ghat Then put it all on one Lumhe link. Relatives reply without downloading anything, you know who's arriving, and after the sunrise arghya everyone's photos go into a shared Moments album that doesn't expire like Stories. Save this, and share it with the person in your family who always handles the ghat plan. Link in bio. 🌅 | L58: #Lumhe #ChhathPuja #ChhathPuja2026 #Chhath #ChhathiMaiya #ChhathParv #BiharFestival #Thekua #SandhyaArghya #UshaArghya #PurvanchalTraditions #FamilyFestival #IndianFestivals | M58: Thekua in your home: crunchy or soft? Settle it below. | N58: Carousel cover with a watercolour of two women in yellow and orange sarees standing in a river at sunset holding bamboo baskets of fruit and diyas, with the text 'Four days, one ghat, the whole family'. | O58: Share the ghat plan | P58: 6 slides | R58: PAIR-CHH_A, PAIR-CHH_B | S58: New watercolour, blog topic: festival | New watercolour, blog topic: festival | T58: Posts/057_2026-11-04_Carousel_F21_Chhath-Puja-family-plan-ten-days-out | U58: slide_01.jpg, slide_02.jpg, slide_03.jpg, slide_04.jpg, slide_05.jpg, slide_06.jpg | V58: Ready | X58: Chhath Puja | Y58: 2026-11-15 | Z58: 10 days before | AA58: F22
A59: 58 | B59: 46330 | C59: =TEXT(B59,"ddd") -> Wed | D59: 23:00 | E59: 16:30 IST = 11:00 AM UK · 23:00 IST = 5:30 PM UK | F59: Single | G59: UK | H59: F13 | I59: Bonfire Night eve invite reminder | J59: Bonfire's tomorrow. Send the link tonight. | K59: Wellies by the door. Guest list still in your head? Bonfire Night is tomorrow. If you're hosting, tonight's the night to send the details: start time, address, what to wear and whether children are coming, so you've got enough gloves and sparklers to go round. Make it on Lumhe in a few minutes, or upload the invite you've already designed, then share one link on WhatsApp. Guests reply in a tap, no app needed. Link in bio. Stay warm out there. 🎆 | L59: #Lumhe #BonfireNightTomorrow #GuyFawkes #FireworkNight #November5th #BonfireParty #UKFamilyFun #SparklerNight #AutumnHosting #LastMinutePlans #DigitalInvites | M59: What's your non-negotiable Bonfire Night snack? Parkin, toffee apples or a hot dog? | N59: Watercolour of friends in coats and scarves around a garden bonfire at dusk, one holding a sparkler, with soft fireworks above. Text reads 'Bonfire's tomorrow. Send the link tonight.' | O59: Send it tonight | P59: 1 image · 4:5 | R59: PAIR-BON_A, PAIR-BON_B | S59: New watercolour, blog topic: festival | New watercolour, blog topic: festival | T59: Posts/058_2026-11-04_Single_F13_Bonfire-Night-eve-invite-reminder | U59: post.jpg | V59: Ready | X59: Bonfire Night | Y59: 2026-11-05 | Z59: Reminder (1-2 days) | AA59: F12
A60: 59 | B60: 46331 | C60: =TEXT(B60,"ddd") -> Thu | D60: 12:30 | E60: IST | F60: Single | G60: India | H60: F16 | I60: Dhanteras eve puja invite reminder | J60: Puja tomorrow? Send the invite before you shop. | K60: The jewellers will be packed tomorrow. Your phone shouldn't be. If you're hosting family for Dhanteras puja and dinner, send the invite tonight. Add the puja time, the address and whether dinner is on, and ask for a quick RSVP so you know how many plates and diyas you need. On Lumhe, that's one link on the family WhatsApp group. No app, no login. Relatives who can't make it can still send their blessings and shagun via Digital Lifafa. Shubh Dhanteras in advance! Link in bio. | L60: #Lumhe #DhanterasTomorrow #ShubhDhanteras #DiwaliCountdown #FamilyPuja #DiwaliInvite #FestiveReminder #DigitalLifafa #ShagunOnline #IndianHomes #DhanterasEve | M60: Who in your family starts the Dhanteras shopping list first? Tag them! | N60: Watercolour of a mother and daughter placing lit diyas on a doorstep beside a footprint rangoli under a marigold toran. Text reads 'Puja tomorrow? Send the invite before you shop.' | O60: Send the invite | P60: 1 image · 4:5 | R60: PAIR-DHA_A, PAIR-DHA_B | S60: New watercolour, blog topic: festival | New watercolour, blog topic: festival | T60: Posts/059_2026-11-05_Single_F16_Dhanteras-eve-puja-invite-reminder | U60: post.jpg | V60: Ready | X60: Dhanteras | Y60: 2026-11-06 | Z60: Reminder (1-2 days) | AA60: F15
A61: 60 | B61: 46331 | C61: =TEXT(B61,"ddd") -> Thu | D61: 23:00 | E61: 16:30 IST = 11:00 AM UK · 23:00 IST = 5:30 PM UK | F61: Single | G61: UK | H61: F14 | I61: Bonfire Night greeting | J61: Wrap up warm and write your name in sparks | K61: Remember, remember the fifth of November... and the gloves. 🧤 Whether you're round a garden fire or squeezed in at the park display, we hope tonight brings big bangs, warm hands and someone sharing their parkin. A little reminder: keep a bucket of water close and sparklers well away from small faces. Happy Bonfire Night from all of us at Lumhe. If you're hosting, pop your guests' photos into one Moments album tomorrow. | L61: #Lumhe #HappyBonfireNight #BonfireNight2026 #RememberRememberThe5thOfNovember #Fireworks #Sparklers #GuyFawkesNight2026 #BritishTraditions #CosyEvenings #NightSky #FamilyTime | M61: Sparkler artists, what are you writing tonight? Your name or someone else's? ✨ | N61: Watercolour of gloved hands drawing loops with sparklers against a night sky, fireworks above and bonfire embers behind a garden wall. Text reads 'Happy Bonfire Night: Wrap up warm and write your name in sparks.' | O61: Share the warmth | P61: 1 image · 4:5 | R61: DAY-BON_A | S61: New watercolour, blog topic: festival | T61: Posts/060_2026-11-05_Single_F14_Bonfire-Night-greeting | U61: post.jpg | V61: Ready | X61: Bonfire Night | Y61: 2026-11-05 | Z61: On the day
A62: 61 | B62: 46332 | C62: =TEXT(B62,"ddd") -> Fri | D62: 12:30 | E62: IST | F62: Single | G62: India | H62: F17 | I62: Dhanteras day greeting | J62: May your home shine brighter than new silver | K62: Shubh Dhanteras! ✨ Today the first diyas glow at the door, the new utensils come home and Diwali week officially begins. May Maa Lakshmi bless your home with prosperity and Dhanvantari bless your family with good health. From all of us at Lumhe, a very happy Dhanteras. Inviting family over this Diwali? Your invite is a link away at lumhe.com. | L62: #Lumhe #ShubhDhanteras2026 #HappyDhanteras #DhanterasWishes #Dhanvantari #MaaLakshmi #DiwaliBegins #DiyaLights #FestivalOfLights #DhanterasGreetings #ProsperityAndHealth | M62: Gold, silver or steel: what came home with you today? 🪔 | N62: Watercolour of a red-draped wooden chowki holding a brass lamp, silver coins and a copper kalash, framed by marigold garlands and glowing diyas. Text reads 'Shubh Dhanteras: May your home shine brighter than new silver.' | O62: Share the wish | P62: 1 image · 4:5 | R62: DAY-DHA_A | S62: New watercolour, blog topic: festival | T62: Posts/061_2026-11-06_Single_F17_Dhanteras-day-greeting | U62: post.jpg | V62: Ready | X62: Dhanteras | Y62: 2026-11-06 | Z62: On the day
A63: 62 | B63: 46332 | C63: =TEXT(B63,"ddd") -> Fri | D63: 23:00 | E63: 16:30 IST = 11:00 AM UK · 23:00 IST = 5:30 PM UK | F63: Single | G63: UK | H63: E51 | I63: What's in a wedding stationery set | J63: What's actually in a wedding stationery set? | K63: Stationers talk in 'suites'. Here's what that actually means. Before the wedding: a save the date, the invitation itself, an RSVP card and a details card for the practical bits (accommodation, parking, dress code, timings). On the day: order of service, menus, place cards and a table plan. You don't need every piece in paper. Plenty of couples keep the invitation printed as the keepsake and move RSVPs and details online, where they're easier to update and impossible to lose in a kitchen drawer. With Lumhe, upload your printed design and share it as a link with RSVPs built in, ceremony and evening reception tracked separately. Save this checklist and visit lumhe.com. | L63: #Lumhe #WeddingStationery #StationerySuite #UKWeddingStationery #OrderOfService #PlaceCards #WeddingInvites #UKWeddingPlanning #WeddingDetails #PaperLove #TablePlan | M63: Which piece of wedding stationery would you skip? | N63: Watercolour of blank cream wedding stationery pieces with a wax seal, silk ribbon, pressed flowers and marigolds on linen. Text reads: What's actually in a wedding stationery set? | O63: Add RSVPs online | P63: 1 image · 4:5 | R63: EV-E51_A | S63: New watercolour, blog topic: stationery-wedding | T63: Posts/062_2026-11-06_Single_E51_What-s-in-a-wedding-stationery-set | U63: post.jpg | V63: Ready | Z63: Evergreen
A64: 63 | B64: 46333 | C64: =TEXT(B64,"ddd") -> Sat | D64: 12:30 | E64: IST | F64: Reel | G64: India | H64: R03 | I64: Diwali family get-together invite reel | J64: 'Sab aa rahe hain na?' asks Dadi | K64: Hosting Diwali milan this year? Stop guessing the numbers. Family get-togethers go wrong in two places: someone gets left out of the invite, and the food is either too little or enough for a baraat. Fix both: • Send one invite to the whole family group 5 to 7 days before • Mention date, time, address and whether it's lunch, dinner or just mithai and patakhe • Ask each family to RSVP with how many are coming • Remind everyone the day before With Lumhe, one link carries your invite and RSVP. You see a live headcount, and on the night every cousin's photos land in one Moments album that doesn't expire. Share this with whoever is hosting Diwali this year. Create your invite free, link in bio. 🪔 | L64: #Lumhe #Diwali2026 #DiwaliMilan #DiwaliParty #HappyDiwali #FestivalOfLights #IndianFamily #DiwaliCelebrations #FamilyGetTogether #DesiFamily #Deepavali #DiwaliVibes | M64: Who hosts Diwali in your family? Tag them so they see this. | N64: Reel alternating watercolour scenes of an elderly couple on a swing with their grandchildren and three women in red sarees laughing together, with text about inviting the whole family to a Diwali get-together through one link. | O64: Create your invite free | P64: 15 s · 9:16 | Q64: Warm festive Indian instrumental with light dhol and shehnai, building to a joyful beat drop. | R64: IN-5, UK-65 | S64: Wedding Anniversary Wishes: Heartfelt Messages | Invitation Template: Complete Guide | T64: Posts/063_2026-11-07_Reel_R03_Diwali-family-get-together-invite-reel | U64: reel.mp4, reel_cover.jpg | V64: Ready | X64: Diwali | Y64: 2026-11-08 | Z64: Reminder (1-2 days) | AA64: F18
A65: 64 | B65: 46333 | C65: =TEXT(B65,"ddd") -> Sat | D65: 21:30 | E65: 19:30 IST = 9:00 AM ET · 21:30 IST = 11:00 AM ET | F65: Carousel | G65: USA | H65: E37 | I65: How to track RSVPs for free | J65: Track every RSVP without spending a dime | K65: That color-coded spreadsheet was cute. Until reply number forty. RSVP tracking is the wedding chore nobody budgets time for, and the one your caterer cares about most. Most want a final count two to three weeks before the day. Swipe for three free ways to do it: the spreadsheet (great for small guest lists), the online form (neat, but separate from your invite) and an invitation with RSVP built in. Whichever you choose, set a reply-by date a week before your caterer's deadline so you have time to follow up. Lumhe is the third option, and it's free: guests open your invite, tap yes or no for each event, and you see a live headcount. They don't need an app or a login. Save this before your invites go out, and start at lumhe.com. | L65: #Lumhe #RSVPTracking #WeddingRSVP #FreeWeddingTools #WeddingBudget #WeddingPlanningTips #GuestListManagement #BrideToBe2027 #WeddingOrganization #EventPlanningUSA #RSVPDeadline #WeddingChecklist | M65: Spreadsheet, form or built-in RSVP: how are you tracking yours? | N65: Watercolor of a bright home office table with a highlighted guest list, returned reply cards, a calculator, coffee and marigolds. Cover text reads: Track every RSVP without spending a dime. | O65: Track RSVPs free | P65: 6 slides | R65: EV-E37_A | S65: New watercolour, blog topic: track-rsvps | T65: Posts/064_2026-11-07_Carousel_E37_How-to-track-RSVPs-for-free | U65: slide_01.jpg, slide_02.jpg, slide_03.jpg, slide_04.jpg, slide_05.jpg, slide_06.jpg | V65: Ready | Z65: Evergreen
A66: 65 | B66: 46334 | C66: =TEXT(B66,"ddd") -> Sun | D66: 12:30 | E66: IST | F66: Single | G66: India | H66: E14 | I66: Return gifts guests keep | J66: Give something they'll use, not just unwrap | K66: Be honest: how many return-gift photo frames are in your cupboard? From Diwali get-togethers to wedding functions, the return gifts people remember are the ones they actually use. A small brass diya gets lit again next year. A tulsi sapling grows on the balcony. A good dry-fruit tin gets refilled for months. And the gift everyone secretly wants? The photos from the day. Share a Lumhe Moments album and every guest can download their favourites, full quality. Save this for your next return-gift run. Link in bio. | L66: #Lumhe #ReturnGifts #ReturnGiftIdeas #WeddingFavours #DiwaliGifts #EcoFriendlyGifts #BrassDiya #TulsiPlant #IndianWeddingFavours #GiftIdeasIndia #FestiveHosting #ShaadiReturnGifts | M66: Best return gift you've ever received? Worst one too, we won't tell. | N66: Watercolour of return gifts on a jute runner: brass diyas, tulsi saplings in terracotta, dry-fruit tins and cloth potlis among marigolds. Text reads 'Give something they'll use, not just unwrap' with gift ideas. | O66: Start an album | P66: 1 image · 4:5 | R66: EV-E14_A | S66: New watercolour, blog topic: return-gift | T66: Posts/065_2026-11-08_Single_E14_Return-gifts-guests-keep | U66: post.jpg | V66: Ready | Z66: Evergreen
A67: 66 | B67: 46334 | C67: =TEXT(B67,"ddd") -> Sun | D67: 19:00 | E67: IST | F67: Single | G67: India | H67: S24 | I67: Diwali greeting with diya | J67: May your home glow as bright as this diya | K67: Diwali ki hardik shubhkamnayein! Diwalichya hardik shubhechha! 🪔 Today is for diyas on every ledge, marigold torans at the door and that one plate of chakli nobody can stop eating. Sending wishes today? Try this one: "May Maa Lakshmi fill your home with roshni, your kitchen with mithai and your heart with peace. Happy Diwali to you and your family." And if the celebrations continue this week, send your get-together invite as one Lumhe link with RSVP. Share this with someone you're wishing today. ✨ | L67: #Lumhe #HappyDiwali #ShubhDeepavali #Diwali2026 #DiwaliWishes #Deepavali #FestivalOfLights #DiwaliGreetings #Marigold #DiyaLights #ShubhDiwali #IndianFestivals | M67: Which Diwali sweet disappears first at your home? | N67: Watercolour illustration of a gold-framed blank card with marigolds and a lit diya. Text reads: Shubh Deepavali, May your home glow as bright as this diya. | O67: Send your invite | P67: 1 image · 4:5 | R67: UK-55 | S67: Templates For Party Invites: Complete Guide | T67: Posts/066_2026-11-08_Single_S24_Diwali-greeting-with-diya | U67: post.jpg | V67: Ready | X67: Diwali | Y67: 2026-11-08 | Z67: On the day
A68: 67 | B68: 46335 | C68: =TEXT(B68,"ddd") -> Mon | D68: 12:30 | E68: IST | F68: Reel | G68: India | H68: E22 | I68: Groom manages a 400-guest list | J68: Your side of the list: 400 | K68: Your side of the guest list just crossed 400. Now what? Big Indian families are a blessing, right up until you have to track who's coming to which function. Chachas, mama-mamis, more cousins than you can count, and Papa's business friends who have attended every family function for decades. The spreadsheet works for about two weeks. Then Papa makes his own version, and nobody knows which list is real. What works better: • One list, owned by one person • Guests invited function by function • RSVPs that update without a single follow-up call That's Lumhe. Each guest sees only the functions they're invited to, and you see live headcounts for Haldi, Mehendi, Sangeet, the pheras and the Reception. Send this to the groom who's quietly drowning in rows. Plan your guest list free, link in bio. | L68: #Lumhe #GroomLife #DulhaDiaries #BigFatIndianWedding #WeddingGuestList #GuestListManagement #IndianGroom #ShaadiPlanning #WeddingRSVPTracking #SangeetNight #GroomToBe #FamilyWedding | M68: How many guests are on your side of the list? Be brave. | N68: Watercolour reel: a groom on a floor cushion surrounded by papers, chai and a marigold garland, and the groom laughing and dancing with cousins at a marigold-lit sangeet. Text shows how per-function RSVP tames a 400-guest list. | O68: Plan your guest list | P68: 15 s · 9:16 | Q68: Wry, plucky comedic beat that switches to a high-energy Punjabi dhol track at scene 4. | R68: EV-E22_A, EV-E22_B | S68: New watercolour, blog topic: 400-wedding-guests | New watercolour, blog topic: 400-wedding-guests | T68: Posts/067_2026-11-09_Reel_E22_Groom-manages-a-400-guest-list | U68: reel.mp4, reel_cover.jpg | V68: Ready | Z68: Evergreen
A69: 68 | B69: 46335 | C69: =TEXT(B69,"ddd") -> Mon | D69: 19:00 | E69: IST | F69: Reel | G69: India | H69: F19 | I69: Bhai Dooj tomorrow reminder reel | J69: Bhai Dooj is tomorrow. Thali ready? | K69: Tomorrow is for tilak, teasing and too many laddoos. Bhai Dooj comes right after the Diwali rush, so it's easy to wake up without a thali ready. Tonight's quick check: • Roli, rice, a diya and the mithai he actually likes • Lunch plan: who's cooking, who's coming • Sibling far away? Fix the call time now, across time zones Hosting the Bhai Dooj lunch? Send it as one Lumhe link so cousins can RSVP in seconds. Switch on Digital Lifafa and a brother who can't travel can still send shagun by UPI, straight to his sister's UPI ID. Afterwards, every tilak photo goes into one Moments album. Tag the sibling who will definitely forget, and send your invite tonight. Link in bio. 🪔 | L69: #Lumhe #BhaiDooj #HappyBhaiDooj #BhaiDoojTomorrow #BhauBeej #BhaiPhonta #BhaiTika #SiblingsDay #BrotherSisterLove #ShagunOnline #DiwaliWeek2026 #DesiSiblings | M69: Brothers, be honest: what's the best Bhai Dooj gift you've ever given? | N69: Reel with a watercolour of a sister applying tilak to her brother over a rangoli, alternating with clean text cards reminding viewers that Bhai Dooj is tomorrow and showing how to send shagun and share photos. | O69: Send your invite | P69: 15 s · 9:16 | Q69: Soft, nostalgic Indian acoustic track with flute and light tabla that lifts into a warm, playful beat for the closing scenes. | R69: UK-64 | S69: Meaning Of Rsvp In Invitation: Complete Guide | T69: Posts/068_2026-11-09_Reel_F19_Bhai-Dooj-tomorrow-reminder-reel | U69: reel.mp4, reel_cover.jpg | V69: Ready | X69: Bhai Dooj | Y69: 2026-11-10 | Z69: Reminder (1-2 days) | AA69: C35
A70: 69 | B70: 46336 | C70: =TEXT(B70,"ddd") -> Tue | D70: 12:30 | E70: IST | F70: Single | G70: India | H70: F20 | I70: Bhai Dooj day greeting | J70: One tilak, a lifetime of 'main mummy ko bataungi' | K70: Roli on the forehead, laddoo in hand, complaints saved for later. Happy Bhai Dooj to the siblings who share secrets, steal each other's chargers and still show up every single year, in person or on a video call. Bhau Beej, Bhai Phonta, Bhai Tika: whatever you call it, today is theirs. Send your bhai or didi this one: "Thank you for being my first friend and my favourite rival." Siblings far away today? Shagun can still reach by Digital Lifafa on Lumhe. 💛 | L70: #Lumhe #BhaiDooj2026 #HappyBhaiDooj #BhaiBehenKaPyaar #SiblingGoals #BhauBeej2026 #BhaiPhonta2026 #BhaiyaDidi #SiblingBond #FestivalWishes #IndianSiblings | M70: Tag the sibling who still owes you a Bhai Dooj gift from last year. | N70: Watercolour of a brass aarti thali on a rangoli with roli, rice, a lit diya, a coconut and mithai, held by a sister's hennaed hand. Text reads: Happy Bhai Dooj. One tilak, a lifetime of 'main mummy ko bataungi'. | O70: Send shagun | P70: 1 image · 4:5 | R70: DAY-BHA_A | S70: New watercolour, blog topic: festival | T70: Posts/069_2026-11-10_Single_F20_Bhai-Dooj-day-greeting | U70: post.jpg | V70: Ready | X70: Bhai Dooj | Y70: 2026-11-10 | Z70: On the day
A71: 70 | B71: 46336 | C71: =TEXT(B71,"ddd") -> Tue | D71: 19:00 | E71: IST | F71: Carousel | G71: India | H71: F24 | I71: Dev Uthani Ekadashi and Tulsi Vivah plan | J71: Tulsi Vivah first, then the shehnai season | K71: The ekadashi that sets the whole shaadi calendar moving. Dev Uthani Ekadashi, also known as Prabodhini Ekadashi, falls on 20 November. Many homes mark it with Tulsi Vivah in the aangan, and for lots of families it's the signal that wedding dates can finally be fixed. Swipe for: • What the day means • A Tulsi Vivah puja checklist • Invite wording for neighbours and family • Four things to finish now if there's a shaadi in your family Whether it's an evening aarti for 15 or a five-function wedding for 500, Lumhe gives you one link. Each guest sees only their functions, you get a live headcount for each, and Digital Lifafa sends shagun by UPI directly to you. Save this, and share it with the family member who keeps the panchang. Link in bio. 🌼 | L71: #Lumhe #DevUthaniEkadashi #TulsiVivah #PrabodhiniEkadashi #DevUthani2026 #WeddingSeasonIndia #ShaadiSeason2026 #TulsiPuja #HinduFestivals #ShubhVivah #WeddingPlanningIndia #DigitalLifafa | M71: Does your family hold Tulsi Vivah at home? Tell us how you decorate the mandap. | N71: Carousel cover with a watercolour of a tulsi plant dressed as a bride in a red chunri under a sugarcane mandap with marigolds and diyas, and the text 'Tulsi Vivah first, then the shehnai season'. | O71: Create your invite free | P71: 6 slides | R71: PAIR-DEV_A, PAIR-DEV_B | S71: New watercolour, blog topic: festival | New watercolour, blog topic: festival | T71: Posts/070_2026-11-10_Carousel_F24_Dev-Uthani-Ekadashi-and-Tulsi-Vivah-plan | U71: slide_01.jpg, slide_02.jpg, slide_03.jpg, slide_04.jpg, slide_05.jpg, slide_06.jpg | V71: Ready | X71: Dev Uthani Ekadashi / wedding season opens | Y71: 2026-11-20 | Z71: 10 days before | AA71: F25
A72: 71 | B72: 46337 | C72: =TEXT(B72,"ddd") -> Wed | D72: 16:30 | E72: 16:30 IST = 11:00 AM UK · 23:00 IST = 5:30 PM UK | F72: Carousel | G72: UK | H72: C06 | I72: UK save the date guide | J72: When to send it, what to say | K72: A save the date is a heads-up, not a full invitation. Its only job is to get your date into diaries before summer holidays, stag and hen weekends, and everyone else's weddings fill them. So keep it short: names, date, town and a promise that the proper invitation will follow. Swipe for when to send it, what to include, three wordings you can borrow, and the one etiquette rule that catches couples out. Save this for your planning folder and share it with your other half. With Lumhe you can share your save the date as one link on WhatsApp or email, then follow up with the full invitation and RSVP. Link in bio. | L72: #Lumhe #SaveTheDate #SaveTheDateUK #UKWeddingPlanning #WeddingStationeryUK #EngagedUK #2027Wedding #DigitalSaveTheDate #BrideToBeUK #WeddingInspoUK #CotswoldsWedding #WeddingTipsUK | M72: Digital or printed save the dates: which are you sending? Tell us why. | N72: Watercolour carousel: a hand pulling a card from a stationery drawer, and a desktop monitor showing a card design beside a marigold vase. Slides explain when to send save the dates and what to write. | O72: Share your date | P72: 6 slides | R72: UK-36, UK-53 | S72: Save the Date Cards: When to Send, Wording & Ideas | Save the Date Cards: When to Send, Wording & Ideas | T72: Posts/071_2026-11-11_Carousel_C06_UK-save-the-date-guide | U72: slide_01.jpg, slide_02.jpg, slide_03.jpg, slide_04.jpg, slide_05.jpg, slide_06.jpg | V72: Ready | Z72: Blog image
A73: 72 | B73: 46337 | C73: =TEXT(B73,"ddd") -> Wed | D73: 21:30 | E73: 19:30 IST = 9:00 AM ET · 21:30 IST = 11:00 AM ET | F73: Single | G73: USA | H73: E38 | I73: Reception-only wedding invitations | J73: Private vows? Invite everyone to the party. | K73: Eloped, married at city hall or kept the ceremony family-only? You still get the party. A reception-only invitation lets your wider circle celebrate with you, without anyone wondering whether they missed the ceremony. Be clear and warm: 'Sarah and Michael were married in a private ceremony and invite you to celebrate with them' tells guests exactly what's happening. Then the essentials: date, time, venue, what to expect (cocktails, dinner, dancing) and an RSVP date. Send it digitally with Lumhe: upload your design, share one link and see a live headcount for the reception. Would you do a private ceremony and a big party? Tell us, then start yours at lumhe.com. | L73: #Lumhe #ReceptionOnly #WeddingReception #Elopement #CourthouseWedding #MicroWedding #JustMarried #WeddingParty #ReceptionInvitation #NewlywedsUSA #WeddingCelebration | M73: Private ceremony plus big party: yes or no? | N73: Watercolor of a candlelit reception tent with long tables, a two-tier cake and marigold garlands around a glowing dance floor. Text reads: Private vows? Invite everyone to the party. | O73: Invite them to party | P73: 1 image · 4:5 | R73: EV-E38_A | S73: New watercolour, blog topic: wedding-reception-invitation | T73: Posts/072_2026-11-11_Single_E38_Reception-only-wedding-invitations | U73: post.jpg | V73: Ready | Z73: Evergreen
A74: 73 | B74: 46338 | C74: =TEXT(B74,"ddd") -> Thu | D74: 12:30 | E74: IST | F74: Carousel | G74: India | H74: C13 | I74: Mehendi invitation designs and wording | J74: Invites as pretty as the henna | K74: Your Mehendi invite should feel colourful, musical and a little filmy. It's the most relaxed event of the wedding week, so the invite can play more than the main wedding card does. Think henna-hand illustrations, paisley in emerald and gold, a marigold jhoola, or clean line art on cream. Inside: • Four design directions to brief your designer (or pick in Canva) • A Hinglish line and an English line you can copy • The practical details guests always ask about Tip from many shaadis: mention when guests can get their mehendi done. Otherwise everyone queues for the artist at the same time. 💚 Save this, send it to your sister who's handling the Mehendi, and create your function-wise invite free at lumhe.com. | L74: #Lumhe #MehendiInvitation #MehndiCeremony #MehendiNight #MehendiDecor #IndianWeddingInvite #HennaArt #BrideToBeIndia #ShaadiFunctions #WeddingCardIndia #MehendiVibes #DesiBride | M74: Green, yellow or full rainbow: what's your Mehendi dress code? | N74: Watercolour illustration of mehendi cones beside a fan of invitation cards with henna patterns. On-image text reads: Mehendi invites as pretty as the henna. | O74: Create Mehendi invite | P74: 6 slides | R74: RU-3 | S74: 10 Beautiful Mehendi Invitation Designs — Free Templates to Download & Share | T74: Posts/073_2026-11-12_Carousel_C13_Mehendi-invitation-designs-and-wording | U74: slide_01.jpg, slide_02.jpg, slide_03.jpg, slide_04.jpg, slide_05.jpg, slide_06.jpg | V74: Ready | Z74: Blog image
A75: 74 | B75: 46338 | C75: =TEXT(B75,"ddd") -> Thu | D75: 21:30 | E75: 19:30 IST = 9:00 AM ET · 21:30 IST = 11:00 AM ET | F75: Single | G75: USA | H75: S41 | I75: Home printing invitations test tip | J75: Printing at home? Test on plain paper first. | K75: Holiday party invites coming off your own printer this year? Before you load the good card stock, print one copy on plain paper. Check spelling, margins and whether that soft blush color turned out peach. Then switch the printer setting to heavy card stock, feed one sheet at a time, and trim with a paper cutter rather than scissors for clean edges. Printing a few for close family and sending the rest as a link? Lumhe hosts the same design online with RSVP built in. Save this, and find us via the link in bio. | L75: #Lumhe #PrintAtHome #DIYInvitations #HolidayPartyInvites #PrintableInvitations #CardStock #CraftTips #InvitationPrinting #HolidayHosting #DIYTips #StationeryLove | M75: What's your worst home-printing fail? We won't judge. | N75: Watercolour illustration of a home printer printing an invitation card beside a vase of flowers. On-image text reads: Printing at home? Test on plain paper first. | O75: Share it online | P75: 1 image · 4:5 | R75: US-61 | S75: Halloween Party Invitations: Spooky Wording & Ideas | T75: Posts/074_2026-11-12_Single_S41_Home-printing-invitations-test-tip | U75: post.jpg | V75: Ready | Z75: Blog image
A76: 75 | B76: 46339 | C76: =TEXT(B76,"ddd") -> Fri | D76: 13:00 | E76: IST | F76: Carousel | G76: Global | H76: C18 | I76: First birthday invitation themes and wording | J76: One candle, a lot of guests | K76: One candle and a lot of excited grandparents. A first birthday is really a party for the grown-ups who made it through year one, and the invitation sets the mood. Swipe for themes that suit a one-year-old, ready wording (royal, sweet and wild), and the practical details parents of little guests will thank you for. A tip from the trenches: plan the party around nap time, not the other way round. A rested birthday baby is a smiling one in photos. 🎈 Save this for your planning, and share it with a parent whose little one is turning one soon. On Lumhe one link holds the invite and RSVPs, plus an album for every guest's photos. Link in bio. | L76: #Lumhe #FirstBirthday #FirstBirthdayParty #TurningOne #OneYearOld #WildOne #ONEderland #FirstBirthdayIdeas #SmashCake #BirthdayInvitation #BabyFirstBirthday #PartyThemes #MomLife | M76: Which theme are you choosing: Wild One, ONEderland or Little Royal? Tell us below. | N76: Watercolour carousel: a baby at a first-birthday cake table with balloons, and a pink first-birthday cake topped with a crown and balloons. Slides give first birthday themes and invitation wording. | O76: Create the invite | P76: 6 slides | R76: IN-43, US-80 | S76: Happy Wedding Anniversary To Both Of You: Complete Guide | Electronic Wedding Invitations: Complete Guide | T76: Posts/075_2026-11-13_Carousel_C18_First-birthday-invitation-themes-and-wor | U76: slide_01.jpg, slide_02.jpg, slide_03.jpg, slide_04.jpg, slide_05.jpg, slide_06.jpg | V76: Ready | Z76: Blog image
A77: 76 | B77: 46339 | C77: =TEXT(B77,"ddd") -> Fri | D77: 23:00 | E77: 16:30 IST = 11:00 AM UK · 23:00 IST = 5:30 PM UK | F77: Single | G77: UK | H77: E53 | I77: RSVP card: the seat-count line | J77: 'We have reserved two seats in your honour.' | K77: The most useful line on an RSVP card isn't 'accepts' or 'declines'. It's the seat count. 'We have reserved two seats in your honour' quietly answers the plus-one question before anyone asks it. What else to print: a reply-by date (usually six to eight weeks before the wedding), a space for names, accepts or declines, dietary requirements, and a separate line for evening reception guests if you have them. Printed cards are lovely, but they do get lost in handbags and drawers. Many couples add a link so guests can reply in seconds; with Lumhe, every answer lands in one live headcount. Save this for when you order your stationery, and visit lumhe.com. | L77: #Lumhe #RSVPCards #WeddingRSVPUK #UKWeddingStationeryIdeas #WeddingInvitationsUK #PlusOne #WeddingEtiquette #RSVPWording #UKBride #WeddingPlanning2027 #WeddingStationeryUK | M77: Plus-ones: named, unnamed or not at all? | N77: Watercolour close-up of blank cream RSVP cards on linen beside a fountain pen, a wax-sealed envelope and marigold petals. Text reads: We have reserved two seats in your honour. | O77: Collect RSVPs free | P77: 1 image · 4:5 | R77: EV-E53_A | S77: New watercolour, blog topic: rsvp-cards | T77: Posts/076_2026-11-13_Single_E53_RSVP-card-the-seat-count-line | U77: post.jpg | V77: Ready | Z77: Evergreen
A78: 77 | B78: 46340 | C78: =TEXT(B78,"ddd") -> Sat | D78: 12:30 | E78: IST | F78: Single | G78: India | H78: F22 | I78: Chhath tomorrow ghat plan reminder | J78: Ghat location, family plan, timings: sent yet? | K78: The soop is packed. Is the family actually on the same page? Chhath's ghat days start early and run on teamwork: who carries the daura, where everyone meets, which ghat the family is using this year. Put it in one message tonight and save yourself the calls tomorrow. Share it as a Lumhe link, and relatives can open it without an app, see the plan and RSVP. After the arghya, everyone's photos go into one Moments album. Send the plan tonight. Link in bio. 🌅 | L78: #Lumhe #ChhathPuja2026 #ChhathTomorrow #ChhathMahaparv #JaiChhathiMaiya #ChhathGhat #BiharDiaries #PatnaDiaries #ChhathVibes #FamilyPlans #FestivalReminder | M78: Which ghat does your family go to every year? | N78: Watercolour of two women in bright sarees standing in a river at sunset holding bamboo baskets of fruit and diyas. Text reads: Chhath is tomorrow. Ghat location, family plan, timings: sent yet? | O78: Send the plan | P78: 1 image · 4:5 | R78: PAIR-CHH_A, PAIR-CHH_B | S78: New watercolour, blog topic: festival | New watercolour, blog topic: festival | T78: Posts/077_2026-11-14_Single_F22_Chhath-tomorrow-ghat-plan-reminder | U78: post.jpg | V78: Ready | X78: Chhath Puja | Y78: 2026-11-15 | Z78: Reminder (1-2 days) | AA78: F21
A79: 78 | B79: 46340 | C79: =TEXT(B79,"ddd") -> Sat | D79: 19:00 | E79: IST | F79: Carousel | G79: India | H79: F26 | I79: Gurpurab path and langar hosting guide | J79: Path, kirtan and langar: invite the sangat | K79: Opening your home for Gurpurab? Here's the plan, ten days ahead. Guru Nanak Jayanti falls on 24 November. In the days before, the mornings fill with Prabhat Pheri, and many families hold a Sukhmani Sahib path or kirtan at home followed by langar. Swipe for: • What the Gurpurab week usually looks like • A home path checklist • Invite wording you can copy • How to share the langar seva without last-minute panic Send the invite as a single Lumhe link on WhatsApp. Elders can open it without an app or login, you get RSVPs for a real langar headcount, and every diya-lit photo from the evening lands in one Moments album. Save this, and share it with the family hosting the path this year. Link in bio. 🙏 | L79: #Lumhe #Gurpurab #GuruNanakJayanti #Gurpurab2026 #PrakashPurab #Langar #SewaSimran #SukhmaniSahib #PrabhatPheri #Waheguru #PunjabiFamily #SikhCommunity #Kirtan | M79: Which langar dish do you look forward to most: kaali dal, kheer or karah prasad? | N79: Carousel cover with a watercolour of a white gurdwara courtyard glowing with diyas and marigold garlands as a family walks in with heads covered, and the text 'Path, kirtan and langar: invite the sangat'. | O79: Invite the sangat | P79: 6 slides | R79: PAIR-GNJ_A, PAIR-GNJ_B | S79: New watercolour, blog topic: festival | New watercolour, blog topic: festival | T79: Posts/078_2026-11-14_Carousel_F26_Gurpurab-path-and-langar-hosting-guide | U79: slide_01.jpg, slide_02.jpg, slide_03.jpg, slide_04.jpg, slide_05.jpg, slide_06.jpg | V79: Ready | X79: Guru Nanak Jayanti (Gurpurab) | Y79: 2026-11-24 | Z79: 10 days before | AA79: F27
A80: 79 | B80: 46341 | C80: =TEXT(B80,"ddd") -> Sun | D80: 12:30 | E80: IST | F80: Single | G80: India | H80: E15 | I80: Gift box hero item tip | J80: Build the box around one hero item | K80: A gift box feels thoughtful when one thing clearly leads. Start with the hero: a scented candle for a new home, an engraved frame for newlyweds, a brass diya for the festive season. Then build around it with smaller things that match: a jar of dry fruits, artisan chocolates, a sachet of kesar. Finish with a handwritten note. That's the part people keep. Tip: line the box with tissue and pack the heaviest item at the bottom. Sending the invite for the event too? Make it on Lumhe, free, link in bio. | L80: #Lumhe #GiftBox #GiftHamper #GiftBoxIdeas #WeddingGiftBox #FestiveHamper #GiftPacking #CuratedGifts #DryFruitHamper #GiftingIdeasIndia #HandwrittenNote | M80: What's always in your gift box: dry fruits, chocolates or something homemade? | N80: Watercolour of an open kraft hamper with dry fruits, a candle, chocolates and a brass diya, tied with ribbon and marigolds. Text reads 'Build the box around one hero item' with a packing tip. | O80: Create your invite | P80: 1 image · 4:5 | R80: EV-E15_A | S80: New watercolour, blog topic: Gift_Box | T80: Posts/079_2026-11-15_Single_E15_Gift-box-hero-item-tip | U80: post.jpg | V80: Ready | Z80: Evergreen
A81: 80 | B81: 46341 | C81: =TEXT(B81,"ddd") -> Sun | D81: 19:00 | E81: IST | F81: Single | G81: India | H81: F23 | I81: Chhath Puja day greeting | J81: Chhath Puja ki hardik shubhkamnayein | K81: To every vrati standing in the water with folded hands today. Chhath is devotion at its most patient: days of fasting, the walk to the ghat with the daura on someone's head, the hush before the sun appears, and the thekua shared afterwards with everyone around. Wishing you and your family the blessings of Chhathi Maiya and Surya Dev. And when you're back home, collect the ghat photos from everyone in one Moments album on Lumhe. 🌅 | L81: #Lumhe #HappyChhathPuja #ChhathPujaWishes #ChhathiMaiya #SuryaDev #ChhathPuja2026 #Arghya #ChhathParv2026 #Bihar #Purvanchal #IndianTraditions | M81: Send your Chhath wishes to your family here, in your own words. | N81: Watercolour of a woman in a yellow saree standing in a river at sunrise, pouring water from a brass lota towards the sun, with a basket of fruit and a floating diya beside her. Text reads: Chhath Puja ki hardik shubhkamnayein. | O81: Share the photos | P81: 1 image · 4:5 | R81: DAY-CHH_A | S81: New watercolour, blog topic: festival | T81: Posts/080_2026-11-15_Single_F23_Chhath-Puja-day-greeting | U81: post.jpg | V81: Ready | X81: Chhath Puja | Y81: 2026-11-15 | Z81: On the day
A82: 81 | B82: 46342 | C82: =TEXT(B82,"ddd") -> Mon | D82: 19:30 | E82: 19:30 IST = 9:00 AM ET · 21:30 IST = 11:00 AM ET | F82: Single | G82: USA | H82: E39 | I82: Vintage or western invitation poll | J82: Lace and letterpress, or boots and barn doors? | K82: Some invitations feel like they came out of a cedar chest. Vintage invitations lean on texture: deckled edges, letterpress, lace wraps, sepia tones and classic serif type. Western ones swap the lace for kraft paper, twine, horseshoes and a hand-lettered ranch name. Both work for a barn, a vineyard or a backyard, and both photograph beautifully. Whichever way you lean, you can upload the finished design to Lumhe and share it as one link, with RSVPs built in and no app for guests. Comment LACE or BOOTS and show us your style. Then start your invite at lumhe.com. | L82: #Lumhe #VintageWedding #WesternWedding #RusticWedding #BarnWedding #LetterpressInvitations #CountryWedding #WeddingStyle #WeddingInspo #RanchWedding #WeddingInvitationIdeas | M82: LACE or BOOTS? Drop your answer below. | N82: Watercolor of two blank invitations on a weathered barn plank, one wrapped in lace with a pressed rose, one tied with twine and a horseshoe, with cowboy boots and marigolds. Text reads: Lace and letterpress, or boots and barn doors? | O82: Upload your design | P82: 1 image · 4:5 | R82: EV-E39_A | S82: New watercolour, blog topic: vintage | T82: Posts/081_2026-11-16_Single_E39_Vintage-or-western-invitation-poll | U82: post.jpg | V82: Ready | Z82: Evergreen
A83: 82 | B83: 46342 | C83: =TEXT(B83,"ddd") -> Mon | D83: 21:30 | E83: 19:30 IST = 9:00 AM ET · 21:30 IST = 11:00 AM ET | F83: Carousel | G83: USA | H83: F29 | I83: Thanksgiving hosting plan, ten days out | J83: The long table needs a guest list first | K83: Ten days is plenty of time if you start tonight. Thanksgiving is Thursday, November 26, and the hosts who stay relaxed are the ones who settle the guest count early. Everything else depends on it: the size of the bird, the number of chairs, how many pies to bake. Swipe for: • Invite wording you can send today • Turkey math and fridge-thawing timing • A three-days-out setup list • Little table rituals people actually remember Send it all as one Lumhe link. Guests RSVP in a tap with no app or login, you watch the headcount update, and after dinner everyone adds their photos to a shared Moments album instead of scattering them across group chats. Save this and share it with your co-host. Your free invite is at lumhe.com. 🦃 | L83: #Lumhe #Thanksgiving2026 #ThanksgivingHosting #ThanksgivingPrep #ThanksgivingInvite #HostingThanksgiving #TurkeyDay #HolidayHosting #FallEntertaining #ThanksgivingTable #GatherTogether #HolidayPlanning | M83: Turkey, ham or a vegetarian main: what's the centerpiece at your table this year? | N83: Carousel cover with a watercolour of an autumn barn with picnic tables and string lights, and the text 'The long table needs a guest list first'. Another slide shows a garden dinner party under string lights. | O83: Send your invite | P83: 6 slides | R83: US-6, US-39 | S83: Gender Reveal Party Invitations: Wording, Ideas & Free Templates | Personalized Party Invites Guide | T83: Posts/082_2026-11-16_Carousel_F29_Thanksgiving-hosting-plan-ten-days-out | U83: slide_01.jpg, slide_02.jpg, slide_03.jpg, slide_04.jpg, slide_05.jpg, slide_06.jpg | V83: Ready | X83: Thanksgiving | Y83: 2026-11-26 | Z83: 10 days before | AA83: R09
A84: 83 | B84: 46343 | C84: =TEXT(B84,"ddd") -> Tue | D84: 12:30 | E84: IST | F84: Carousel | G84: India | H84: E08 | I84: Original Hindi shayari for wedding cards | J84: Two lines your shaadi card deserves | K84: Two lines of shayari can do what a whole paragraph can't. A shaadi card with a sher on top feels instantly personal. The trick is choosing a tone that matches your family: devotional for the elders' card, warm for relatives, a little filmy for friends. Swipe for four original couplets you can copy: • A traditional one about two families • A heartfelt invite • A blessing line for elders • A playful one for the friends' group Tip: keep shayari to two lines, and place it between the invocation and the names. More than that, and guests skip it. Save this and send it to the cousin who's "good with words". Then upload your card to Lumhe and share one link. Link in bio. | L84: #Lumhe #WeddingShayari #HindiShayari #ShaadiCard #ShayariForWeddingCard #ShaadiKaCard #HindiWedding #WeddingCardIdeas #ShaadiSeason #DulhanDiaries #IndianWeddingInvite #Shayari | M84: Write your own two-line shaadi shayari in the comments. Best one gets a reshare. | N84: Watercolour of a blank ornate card on a low wooden desk with a brass inkpot, a calligraphy pen, a diya and marigolds. Slides share original Hindi shayari for wedding invitation cards. | O84: Upload your shaadi card | P84: 6 slides | R84: EV-E08_A | S84: New watercolour, blog topic: shayari | T84: Posts/083_2026-11-17_Carousel_E08_Original-Hindi-shayari-for-wedding-cards | U84: slide_01.jpg, slide_02.jpg, slide_03.jpg, slide_04.jpg, slide_05.jpg, slide_06.jpg | V84: Ready | Z84: Evergreen
A85: 84 | B85: 46343 | C85: =TEXT(B85,"ddd") -> Tue | D85: 23:00 | E85: 16:30 IST = 11:00 AM UK · 23:00 IST = 5:30 PM UK | F85: Single | G85: UK | H85: E54 | I85: Card or online invites poll (UK) | J85: Card on the mantelpiece, or a link in the chat? | K85: There's no wrong answer, just the one that suits your guests. Printed cards still have real pull in the UK: something to hold, something for the fridge door, something to tuck into a scrapbook. Online invitations win on speed, easy updates and replies that actually come back. Many couples now do both: a printed card for the keepsake and a link for RSVPs, with day and evening guests tracked separately. Whichever you pick, Lumhe takes any design you've made, a scanned card or a Canva file, and turns it into one shareable link with RSVPs built in. So which is it for you: card, online or both? Tell us in the comments. | L85: #Lumhe #WeddingInvitations #UKWedding #PrintedInvitations #OnlineInvitations #WeddingPoll #WeddingStationeryLove #DigitalWedding #UKWeddingIdeas #EngagedLife #WeddingDecisions | M85: Card, online or both? One word in the comments. | N85: Watercolour of a cosy living-room mantelpiece with a blank cream invitation card between a carriage clock and a vase of marigolds and roses. Text reads: Card on the mantelpiece, or a link in the chat? | O85: Vote in comments | P85: 1 image · 4:5 | R85: EV-E54_A | S85: New watercolour, blog topic: card-wedding-invites | T85: Posts/084_2026-11-17_Single_E54_Card-or-online-invites-poll-UK | U85: post.jpg | V85: Ready | Z85: Evergreen
A86: 85 | B86: 46344 | C86: =TEXT(B86,"ddd") -> Wed | D86: 12:30 | E86: IST | F86: Single | G86: India | H86: E17 | I86: Satyanarayan Katha aarti timing tip | J86: Say when the aarti is, not just when katha starts | K86: Some guests arrive just in time for prasad. Help them. A Satyanarayan Katha invitation needs the occasion (new home, anniversary, or an annual puja), the date, the katha start time, the aarti time and the address. Wording to borrow: "श्री सत्यनारायण कथा के पावन अवसर पर आप सपरिवार सादर आमंत्रित हैं। कथा के पश्चात आरती एवं प्रसाद।" Share it as one Lumhe link with the timings and a map, and see who's coming before you order the prasad. Link in bio. | L86: #Lumhe #SatyanarayanKatha #SatyanarayanPuja #PujaInvitation #KathaInvitation #HomePuja #PoojaAtHome #HinduRituals #AartiTime #PrasadTime #IndianTraditions | M86: Sheera or panchamrit: which prasad do you look forward to most? | N86: Watercolour of a home puja set-up with a chowki framed by banana stems, a brass kalash, prasad, marigold garlands and a diya. Text reads 'Say when the aarti is, not just when katha starts' with a timing tip. | O86: Create your invite | P86: 1 image · 4:5 | R86: EV-E17_A | S86: New watercolour, blog topic: satyanarayan | T86: Posts/085_2026-11-18_Single_E17_Satyanarayan-Katha-aarti-timing-tip | U86: post.jpg | V86: Ready | Z86: Evergreen
A87: 86 | B87: 46344 | C87: =TEXT(B87,"ddd") -> Wed | D87: 21:30 | E87: 19:30 IST = 9:00 AM ET · 21:30 IST = 11:00 AM ET | F87: Carousel | G87: USA | H87: E40 | I87: Anniversary party invitations: 25th and 50th | J87: Twenty-five years? Fifty? Throw them a party. | K87: Fifty years deserves more than a card on the kitchen table. Whether it's a silver 25th or a golden 50th, an anniversary party is often planned by the kids, the grandkids or a best friend who's been there since the wedding day. Swipe for formal and warm wording for both milestones, how to word it when the children are hosting and a short checklist for the party itself. Our favorite touch: ask every guest to bring one old photo of the couple. It turns the evening into a walk through the decades. With Lumhe, you can upload the invite, share one link with family across the country, track RSVPs live and gather everyone's photos into a Moments album the couple keeps. Save this for the next big anniversary in your family, and start free at lumhe.com. | L87: #Lumhe #AnniversaryParty #50thAnniversary #25thAnniversary #GoldenAnniversary #SilverAnniversary #AnniversaryInvitations #FamilyCelebration #MarriageMilestone #LoveStory #PartyPlanningUSA #CelebrateLove | M87: Which couple in your family is next to hit a big milestone? | N87: Watercolor carousel: an older couple slow-dancing under warm lights among marigold centerpieces, and hands holding a vintage framed wedding photo. Cover text reads: Twenty-five years? Fifty? Throw them a party. | O87: Plan their party | P87: 6 slides | R87: EV-E40_A, EV-E40_B | S87: New watercolour, blog topic: anniversary-invitations | New watercolour, blog topic: anniversary-invitations | T87: Posts/086_2026-11-18_Carousel_E40_Anniversary-party-invitations-25th-and-5 | U87: slide_01.jpg, slide_02.jpg, slide_03.jpg, slide_04.jpg, slide_05.jpg, slide_06.jpg | V87: Ready | Z87: Evergreen
A88: 87 | B88: 46345 | C88: =TEXT(B88,"ddd") -> Thu | D88: 12:30 | E88: IST | F88: Reel | G88: India | H88: F25 | I88: Dev Uthani tomorrow reminder reel | J88: Ekadashi tomorrow. Shaadi season next. | K88: Tomorrow, the tulsi gets married and the shaadi calendar opens. Dev Uthani Ekadashi is tomorrow. If you're holding Tulsi Vivah in the aangan, there's still time to send the neighbours a quick invite for the evening aarti and prasad. And if there's a wedding in your family this season, this is the week to get organised. On Lumhe, one event holds every function. Each guest sees only the ones they're invited to, you get a live headcount per function, and Digital Lifafa lets relatives send shagun by UPI straight to your UPI ID. After the pheras, guests drop their photos into one Moments album. Forward this to the family member who's already asking about dates. Create your invite free, link in bio. 🌼 | L88: #Lumhe #TulsiVivah2026 #DevUthaniEkadashi2026 #ShaadiSeason #WeddingSeasonIsHere #IndianWeddingInvite #EInviteIndia #FunctionWiseRSVP #ShagunOnline #DesiShaadi #Ekadashi #WeddingReelsIndia | M88: How many weddings are on your calendar this season? Count them below. | N88: Reel alternating a watercolour of a tulsi plant dressed as a bride under a sugarcane mandap with a close-up of a brass thali holding wedding envelopes, haldi and marigolds, with text reminders that Dev Uthani Ekadashi is tomorrow. | O88: Create your invite | P88: 15 s · 9:16 | Q88: Gentle shehnai and soft temple-bell intro that rolls into an upbeat, festive wedding dhol groove. | R88: PAIR-DEV_A, PAIR-DEV_B | S88: New watercolour, blog topic: festival | New watercolour, blog topic: festival | T88: Posts/087_2026-11-19_Reel_F25_Dev-Uthani-tomorrow-reminder-reel | U88: reel.mp4, reel_cover.jpg | V88: Ready | X88: Dev Uthani Ekadashi / wedding season opens | Y88: 2026-11-20 | Z88: Reminder (1-2 days) | AA88: F24
A89: 88 | B89: 46345 | C89: =TEXT(B89,"ddd") -> Thu | D89: 21:30 | E89: 19:30 IST = 9:00 AM ET · 21:30 IST = 11:00 AM ET | F89: Reel | G89: USA | H89: E41 | I89: Wedding photo sharing: every guest photo | J89: First dance. Filmed from twelve angles. | K89: Your wedding was photographed by everyone you love. Your photographer covers the big moments. Your guests catch the rest: the flower girl asleep under a table, your dad's dance moves, the sparkler exit from three different spots. The problem is getting those photos back. They sit in camera rolls, get posted to Stories that disappear, or arrive months later in a compressed text thread. Moments on Lumhe is a shared album that lives on the same link as your invitation. Guests tap upload and add photos in full quality, with no app or login needed, and the album doesn't expire. Save this for your wedding to-do list, send it to your partner, and start your album free at lumhe.com. | L89: #Lumhe #WeddingPhotoSharing #WeddingPhotos #GuestPhotos #WeddingApp #FirstDance #WeddingMemoriesUSA #SharedAlbum #CandidWeddingPhotos #WeddingReel #Bride2027 #WeddingDayUSA | M89: Who at your wedding took the best candid photos? | N89: Watercolor reel of a couple's first dance in a lantern-lit barn, then an aunt wiping a happy tear holding a camera beside wedding cake and marigolds. Opening text reads: First dance. Filmed from twelve angles. | O89: Start your album | P89: 15 s · 9:16 | Q89: Warm, nostalgic acoustic pop with soft strings that swells into a joyful chorus on the reveal. | R89: EV-E41_A, EV-E41_B | S89: New watercolour, blog topic: photo-sharing | New watercolour, blog topic: photo-sharing | T89: Posts/088_2026-11-19_Reel_E41_Wedding-photo-sharing-every-guest-photo | U89: reel.mp4, reel_cover.jpg | V89: Ready | Z89: Evergreen
A90: 89 | B90: 46346 | C90: =TEXT(B90,"ddd") -> Fri | D90: 12:30 | E90: IST | F90: Single | G90: India | H90: S06 | I90: Wedding season: invites after venue | J90: Venue booked? Your invites are next. | K90: Mandap booked, caterer confirmed, halwai finalised. Now the invites. Shaadi season is in full swing, and the families who send invites early are the ones whose outstation relatives actually turn up for the Haldi. Tell faraway family the dates two to three months ahead so they can book trains and flights before fares jump. Send the full e-invite four to six weeks out, with every function listed. On Lumhe each guest sees only the functions they're invited to, and you get a live headcount for each one. Create yours free, link in bio. 🌼 | L90: #Lumhe #ShaadiSeason #IndianWedding #WeddingEInvite #WeddingInvitationIndia #BigFatIndianWedding #ShaadiPlanning #DulhanDiaries #WeddingSeason2026 #DigitalInvite #DesiWedding #WeddingPlannerIndia | M90: How many functions are on your family's wedding list this season? | N90: Watercolour illustration of a grand marigold arch at a wedding venue entrance with a petal-strewn aisle. On-image text reads: Venue booked? Your invites are next. | O90: Create your e-invite | P90: 1 image · 4:5 | R90: IN-52 | S90: Happy Wedding Anniversary PNG | T90: Posts/089_2026-11-20_Single_S06_Wedding-season-invites-after-venue | U90: post.jpg | V90: Ready | X90: Dev Uthani Ekadashi / wedding season opens | Y90: 2026-11-20 | Z90: On the day
A91: 90 | B91: 46346 | C91: =TEXT(B91,"ddd") -> Fri | D91: 21:30 | E91: 19:30 IST = 9:00 AM ET · 21:30 IST = 11:00 AM ET | F91: Single | G91: USA | H91: E42 | I91: Vinyl record wedding invitation idea | J91: Put your wedding on a track list | K91: Some couples write vows. Others write a track list. A vinyl-record invitation turns your wedding details into songs that guests actually read: 'Track 1: Save the Date', 'Track 2: The Ceremony (4 PM)', 'Track 3: Dinner & Dancing'. Side B can cover the after-party. More unique ideas worth stealing: boarding-pass invites for destination weddings, puzzle invites guests piece together, and pressed-flower cards. Going digital? Design the record sleeve in Canva, upload it to Lumhe as an image or video, and share one link with RSVP built in. Which would you choose? Tell us below, and start yours at lumhe.com. | L91: #Lumhe #UniqueWeddingInvitations #VinylWedding #MusicLovers #CreativeInvites #WeddingIdeas2027 #QuirkyWedding #WeddingInvitationIdeasUSA #RecordLovers #CustomInvitations #WeddingDIY | M91: What song would be Track 1 on your wedding invite? | N91: Watercolor of a record player on a wooden sideboard with a vinyl half out of its sleeve, marigolds, ranunculus and two champagne glasses. Text reads: Put your wedding on a track list. | O91: Upload your design | P91: 1 image · 4:5 | R91: EV-E42_A | S91: New watercolour, blog topic: unique-wedding | T91: Posts/090_2026-11-20_Single_E42_Vinyl-record-wedding-invitation-idea | U91: post.jpg | V91: Ready | Z91: Evergreen
A92: 91 | B92: 46347 | C92: =TEXT(B92,"ddd") -> Sat | D92: 16:30 | E92: 16:30 IST = 11:00 AM UK · 23:00 IST = 5:30 PM UK | F92: Carousel | G92: UK | H92: C07 | I92: Day vs evening wedding guest etiquette | J92: Day guest or evening guest? | K92: The evening invitation is where UK wedding etiquette gets wobbly. Evening guests aren't a B-list. They're often colleagues, wider family and friends you'd love to have all day if the venue allowed. The trick is clear wording and arrival times so nobody walks in mid-speech. Swipe for: • Who gets which invitation • Evening reception wording you can borrow • How to make evening guests feel wanted • Keeping two sets of numbers straight for the caterer With Lumhe, your wedding has separate functions. Each guest only sees the parts they're invited to, RSVPs are counted per function, and everyone (day and evening) adds photos to one Moments album. Save this for when you're writing your guest list, and share it with your other half. | L92: #Lumhe #UKWedding #EveningWeddingGuests #EveningReception #WeddingEtiquette #WeddingInvitationsUK #BrideToBeUK #WeddingBreakfast #UKBride #Engaged2026 #WeddingPlanningUK #BarnWedding | M92: Did you have evening guests at your wedding? How did you word it? | N92: Carousel cover showing a watercolour shop window full of invitation cards, with the text 'Day guest or evening guest?'. Following slides cover UK etiquette and wording for evening wedding invitations. | O92: Set up your functions | P92: 6 slides | R92: UK-32 | S92: Wedding Invitation Wedding Invitation: Complete Guide | T92: Posts/091_2026-11-21_Carousel_C07_Day-vs-evening-wedding-guest-etiquette | U92: slide_01.jpg, slide_02.jpg, slide_03.jpg, slide_04.jpg, slide_05.jpg, slide_06.jpg | V92: Ready | Z92: Blog image
A93: 92 | B93: 46347 | C93: =TEXT(B93,"ddd") -> Sat | D93: 23:00 | E93: 16:30 IST = 11:00 AM UK · 23:00 IST = 5:30 PM UK | F93: Single | G93: UK | H93: S01 | I93: UK day and evening guests, one link | J93: Day guests see the ceremony. Evening guests see the party. | K93: The British two-tier guest list, minus the awkward. Your day guests need ceremony times, the wedding breakfast and the dietary question. Your evening guests need 7.30pm, the venue and the dress code for the do. On Lumhe you add the ceremony and the evening reception as separate functions on one event. Each guest only sees what they're invited to, and you get a separate headcount for each. No one spots a ceremony they weren't asked to. Set yours up free. Link in bio. | L93: #Lumhe #UKWedding #EveningWeddingInvitations #DayGuests #WeddingBreakfast #BridesOfTheUK #UKBride #WeddingGuestList #DigitalWeddingInvites #EngagedUK #WeddingPlanningUK | M93: Day guest or evening guest: which do you secretly prefer being? | N93: Watercolour of a cork pinboard covered with photos, cards, a graduation cap and marigolds. Text reads 'Day guests see the ceremony. Evening guests see the party.' | O93: Split your guest list | P93: 1 image · 4:5 | R93: AB-7 | S93: How to Send Digital Wedding Invitations in the UK — Day & Evening Guest Guide | T93: Posts/092_2026-11-21_Single_S01_UK-day-and-evening-guests-one-link | U93: post.jpg | V93: Ready | Z93: Blog image
A94: 93 | B94: 46348 | C94: =TEXT(B94,"ddd") -> Sun | D94: 12:30 | E94: IST | F94: Single | G94: India | H94: E18 | I94: Griha pravesh Hindi invite line | J94: Naye ghar ki dehleez par aapke aashirwad ka intezaar hai. | K94: A house becomes a home when the right people step in first. For your griha pravesh card or WhatsApp message, copy this: "नए घर की दहलीज़ पर आपके आशीर्वाद का इंतज़ार है। गृह प्रवेश पूजा में सपरिवार पधारें।" It works on a printed card for the elders and as a message for everyone else. Add the puja time and the new address below it, because nobody knows the way yet. Upload your card to Lumhe and share one link with the map and RSVP. Link in bio. | L94: #Lumhe #GrihaPravesh #GrihaPraveshInvitation #Housewarming #NewHomeIndia #GrihaPraveshPuja #HindiInvitation #NayaGhar #HousewarmingInvite #RangoliDesign #ToranDecor | M94: Who's the first person you'd invite into your new home? | N94: Watercolour of a new home's doorway with a marigold toran, rangoli at the threshold, a copper kalash and hands holding an aarti plate. Text reads 'Naye ghar ki dehleez par aapke aashirwad ka intezaar hai.' with an English translation. | O94: Upload your card | P94: 1 image · 4:5 | R94: EV-E18_A | S94: New watercolour, blog topic: griha-pravesh | T94: Posts/093_2026-11-22_Single_E18_Griha-pravesh-Hindi-invite-line | U94: post.jpg | V94: Ready | Z94: Evergreen
A95: 94 | B95: 46348 | C95: =TEXT(B95,"ddd") -> Sun | D95: 20:30 | E95: IST | F95: Carousel | G95: Global | H95: C23 | I95: Wedding website include and skip list | J95: What to include, what to skip | K95: Guests open your wedding site with one question: where, and when? A wedding website is meant to answer questions before they reach your phone. The best ones are short, clear and guest-first, and they leave out anything that causes awkward conversations. Swipe for: • The four must-haves • Nice-to-haves that add personality • What to skip (especially events not everyone is invited to) • Simple privacy rules If you're juggling several functions, Lumhe makes the tricky part easy. One link carries the invite and RSVP for every event, and each guest sees only the functions they're invited to. Afterwards, everyone's photos collect in one Moments album. Save this for website-building day, and share it with your partner so you can split the work. 💌 | L95: #Lumhe #WeddingWebsite #WeddingPlanning #WeddingChecklist #BrideToBe #GroomToBe #WeddingGuests #DestinationWedding #WeddingTips #EngagedLife #WeddingOrganization #ModernWedding | M95: Building a wedding website? What's the one question guests keep asking you? | N95: Carousel cover showing a watercolour Indian wedding welcome under a floral door arch with the text 'What to include, what to skip'; another slide shows a photographer capturing a bride's hennaed feet. | O95: Create your link free | P95: 6 slides | R95: US-10, UK-72 | S95: Best Wedding Websites: Complete Guide | Create A Wedding Website: Complete Guide | T95: Posts/094_2026-11-22_Carousel_C23_Wedding-website-include-and-skip-list | U95: slide_01.jpg, slide_02.jpg, slide_03.jpg, slide_04.jpg, slide_05.jpg, slide_06.jpg | V95: Ready | Z95: Blog image
A96: 95 | B96: 46349 | C96: =TEXT(B96,"ddd") -> Mon | D96: 12:30 | E96: IST | F96: Carousel | G96: India | H96: E12 | I96: Invite messages for friends and colleagues | J96: Invite the work gang without the awkward email | K96: Inviting your best friends is easy. Inviting your manager? Less so. Your wedding guest list has layers: the friends who knew about him before your parents did, the team you see every day, and the boss who has to approve your leave. Each one needs a slightly different message. Swipe for: • A message for your closest friends • A team invite that doesn't trigger reply-all chaos • A warm, formal note for your manager • Who gets invited to which function Tip: never invite half a team. Either the whole team or just your close friends from it. Save this before the guest list meeting. Then send one Lumhe link where each guest sees only their functions. Link in bio. | L96: #Lumhe #WeddingInvitationMessage #OfficeColleagues #WeddingInviteForFriends #FriendsWedding #ShaadiInvite #IndianWeddingEtiquette #WorkFriends #WeddingGuestList #BrideTribe #ShaadiSeason2026 #DesiBride | M96: Did you invite your whole team to your wedding, or just your work besties? | N96: Watercolour carousel: three colleagues laughing over chai in an office pantry with a marigold-trimmed sweets box, and hands passing mithai and an envelope across a desk. Slides share wedding invitation messages for friends and colleagues. | O96: Create your event | P96: 6 slides | R96: EV-E12_A, EV-E12_B | S96: New watercolour, blog topic: messages-for-friends | New watercolour, blog topic: messages-for-friends | T96: Posts/095_2026-11-23_Carousel_E12_Invite-messages-for-friends-and-colleagu | U96: slide_01.jpg, slide_02.jpg, slide_03.jpg, slide_04.jpg, slide_05.jpg, slide_06.jpg | V96: Ready | Z96: Evergreen
A97: 96 | B97: 46349 | C97: =TEXT(B97,"ddd") -> Mon | D97: 19:00 | E97: IST | F97: Single | G97: India | H97: F27 | I97: Gurpurab tomorrow langar reminder | J97: Langar for how many? Let the RSVPs decide | K97: Atta kneaded, dal soaked, sheets washed. Is the invite out? Gurpurab is tomorrow. If you're hosting a path or kirtan at home, a quick final message tonight helps everyone: the start time, the address, and a gentle reminder to bring something to cover the head. Share it as a Lumhe link. Relatives open it without an app, RSVP in a tap, and you see how many are coming before the langar prep starts. Send it tonight. Link in bio. 🙏 | L97: #Lumhe #GurpurabTomorrow #GuruNanakDevJi #GuruNanakJayanti2026 #LangarSeva #PathAtHome #Gurbani #SikhFestival #PunjabiFestivals #KartikPurnima #Sangat | M97: Hosting a path at home tomorrow? Tell us which city you're in. | N97: Watercolour of a white gurdwara courtyard at dusk lit with diyas and marigold garlands, with a family walking in, heads covered. Text reads: Gurpurab tomorrow. Langar for how many? Let the RSVPs decide. | O97: Send the invite | P97: 1 image · 4:5 | R97: PAIR-GNJ_A, PAIR-GNJ_B | S97: New watercolour, blog topic: festival | New watercolour, blog topic: festival | T97: Posts/096_2026-11-23_Single_F27_Gurpurab-tomorrow-langar-reminder | U97: post.jpg | V97: Ready | X97: Guru Nanak Jayanti (Gurpurab) | Y97: 2026-11-24 | Z97: Reminder (1-2 days) | AA97: F26
A98: 97 | B98: 46350 | C98: =TEXT(B98,"ddd") -> Tue | D98: 12:30 | E98: IST | F98: Single | G98: India | H98: F28 | I98: Gurpurab day greeting | J98: Gurpurab diyan lakh lakh vadhaiyan | K98: Diyas on the balcony, kirtan in the air, prasad in cupped hands. On Guru Nanak Dev Ji's Prakash Purab, we wish you and your family peace, chardi kala and a table where everyone is welcome, just as at the langar. Wishing someone today? Try: "May Waheguru bless your home with naam, seva and endless happiness. Gurpurab diyan lakh lakh vadhaiyan!" Sharing today's photos with family? One Moments album on Lumhe keeps them all. 🪔 | L98: #Lumhe #HappyGurpurab #GuruNanakJayantiWishes #PrakashPurab2026 #GurpurabWishes #WaheguruJi #ChardiKala #IkOnkar #SikhHeritage #FestivalOfLight #PunjabDiaries | M98: Share a line of Gurbani or a Gurpurab memory that stays with you. | N98: Watercolour of a home balcony at night lined with glowing diyas and marigold garlands, with a bowl of karah prasad on a white cloth under a full moon. Text reads: Guru Nanak Jayanti. Gurpurab diyan lakh lakh vadhaiyan. | O98: Share the moments | P98: 1 image · 4:5 | R98: DAY-GNJ_A | S98: New watercolour, blog topic: festival | T98: Posts/097_2026-11-24_Single_F28_Gurpurab-day-greeting | U98: post.jpg | V98: Ready | X98: Guru Nanak Jayanti (Gurpurab) | Y98: 2026-11-24 | Z98: On the day
A99: 98 | B99: 46350 | C99: =TEXT(B99,"ddd") -> Tue | D99: 20:30 | E99: IST | F99: Carousel | G99: Global | H99: F31 | I99: Hanukkah party planning and invite guide | J99: Eight nights. Pick yours to host. | K99: Forty-four candles, eight nights and one very busy frying pan. Hanukkah begins at sundown on Friday, 4 December. If you're hosting a candle-lighting night, now is the moment to pick your night and send the invite. Swipe for: • Invite wording you can copy • Which night to host • A host checklist from candles to gelt • How to get every guest's candle-lighting photo in one place Tip: ask guests to RSVP with numbers, so you can do the latke math before you start grating potatoes. 🥔 Save this, then create your Hanukkah invite on Lumhe and share one link with family and friends. Link in bio. | L99: #Lumhe #Hanukkah #Hanukkah2026 #ChagSameach #Menorah #Latkes #Sufganiyot #Dreidel #FestivalOfLights #HanukkahParty #HolidayHosting #JewishHolidays | M99: Latkes: applesauce or sour cream? Pick a side. | N99: Watercolour carousel: a grandmother guiding a child's hand to light a menorah at a family table at dusk, and a close-up of latkes, sufganiyot, dreidels and gold coins. Slides share Hanukkah invite wording and a host checklist. | O99: Create your invite | P99: 6 slides | R99: PAIR-HAN_A, PAIR-HAN_B | S99: New watercolour, blog topic: festival | New watercolour, blog topic: festival | T99: Posts/098_2026-11-24_Carousel_F31_Hanukkah-party-planning-and-invite-guide | U99: slide_01.jpg, slide_02.jpg, slide_03.jpg, slide_04.jpg, slide_05.jpg, slide_06.jpg | V99: Ready | X99: Hanukkah (begins at sundown) | Y99: 2026-12-04 | Z99: 10 days before | AA99: F32
A100: 99 | B100: 46351 | C100: =TEXT(B100,"ddd") -> Wed | D100: 19:30 | E100: 19:30 IST = 9:00 AM ET · 21:30 IST = 11:00 AM ET | F100: Single | G100: USA | H100: E43 | I100: Pocket invitation suites explained | J100: Stack inserts largest at the back, smallest in front | K100: A pocket invitation is a tiny filing system that looks gorgeous. Pocket-fold suites hold everything guests need in one piece: the main invitation on one panel, and a pocket for the extras, usually a reception card, a details card with directions or hotels, and a reply card. The assembly rule: inserts go in largest to smallest, back to front, all facing the same way, so every card peeks out in a neat staircase. The one thing they can't do is count replies. Mailing a pocket suite? Upload the same design to Lumhe and share a link for RSVPs, so responses land in one live headcount. Save this for assembly night and visit lumhe.com. | L100: #Lumhe #PocketInvitations #PocketFold #WeddingInvitationSuite #WeddingStationeryUSA #FormalWedding #InvitationAssembly #WeddingPaper #LuxuryWedding #WeddingDetailsMatter #StationeryDesign | M100: Pocket fold, flat card or fully digital: what's your pick? | N100: Watercolor of an open sage pocket-fold invitation with blank insert cards stepped in a staircase, a silk ribbon, wax seal and marigolds on marble. Text reads: Stack inserts largest at the back, smallest in front. | O100: Add RSVP online | P100: 1 image · 4:5 | R100: EV-E43_A | S100: New watercolour, blog topic: pocket-wedding | T100: Posts/099_2026-11-25_Single_E43_Pocket-invitation-suites-explained | U100: post.jpg | V100: Ready | Z100: Evergreen
...

Sheet Carousel slides
A1: # | B1: Date | C1: Post ID | D1: Slide | E1: Kicker | F1: Headline | G1: Body | H1: Image | I1: File
A2: 2 | B2: 46302 | C2: F01 | D2: 1 | E2: Navratri 2026 | F2: Nine nights, one invite link | G2: Garba nights, Kanya Pujan and invite wording, sorted early. | H2: PAIR-NAV_A | I2: Posts/002_2026-10-07_Carousel_F01_Navratri-hosting-and-invite-guide/slide_01.jpg
A3: 2 | B3: 46302 | C3: F01 | D3: 2 | E3: Invite wording | F3: Copy-paste lines for your Garba night | G3: "Chaniya choli ready? Join us for Garba under the lights on [Date], [Time] at [Venue]. Dandiya sticks provided, energy compulsory!" | H3: — (text card) | I3: Posts/002_2026-10-07_Carousel_F01_Navratri-hosting-and-invite-guide/slide_02.jpg
A4: 2 | B4: 46302 | C4: F01 | D4: 3 | E4: Kanya Pujan | F4: Inviting little goddesses for Ashtami | G4: "Please send [Name] for Kanya Pujan on Ashtami, [Date], at ours. Puri, chana and halwa await!" Ask parents early so you cook the right amount. | H4: PAIR-NAV_B | I4: Posts/002_2026-10-07_Carousel_F01_Navratri-hosting-and-invite-guide/slide_03.jpg
A5: 2 | B5: 46302 | C5: F01 | D5: 4 | E5: Host checklist | F5: Book these this week | G5: • Dhol or DJ, plus sound permission • Dandiya sticks and a few spares • A flat, non-slip floor • Water, nimbu-paani and a snack counter | H5: — (text card) | I5: Posts/002_2026-10-07_Carousel_F01_Navratri-hosting-and-invite-guide/slide_04.jpg
A6: 2 | B6: 46302 | C6: F01 | D6: 5 | E6: Nine colours | F6: Put the colours in the invite | G6: Share the day-wise colour list so guests plan outfits early. Add a small prize for the best-dressed kid in each night's colour. | H6: — (text card) | I6: Posts/002_2026-10-07_Carousel_F01_Navratri-hosting-and-invite-guide/slide_05.jpg
A7: 2 | B7: 46302 | C7: F01 | D7: 6 | E7: With Lumhe | F7: One link for all nine nights | G7: Add each Garba night and Kanya Pujan as functions. Guests RSVP per night, you see a live headcount, and every twirl lands in one Moments album. | H7: — (text card) | I7: Posts/002_2026-10-07_Carousel_F01_Navratri-hosting-and-invite-guide/slide_06.jpg
A8: 3 | B8: 46303 | C8: E01 | D8: 1 | E8: Biyer card | F8: Bengali wording, from Prajapataye to Bou Bhaat | G8: Bengali and English lines your family will approve. | H8: EV-E01_A | I8: Posts/003_2026-10-08_Carousel_E01_Bengali-biyer-card-wording-guide/slide_01.jpg
A9: 3 | B9: 46303 | C9: E01 | D9: 2 | E9: At the top | F9: Start with Prajapati | G9: • Prajapataye Namah heads most cards • A butterfly (prajapati) motif is the classic touch • Parents' names come next, then the couple | H9: — (text card) | I9: Posts/003_2026-10-08_Carousel_E01_Bengali-biyer-card-wording-guide/slide_02.jpg
A10: 3 | B10: 46303 | C10: E01 | D10: 3 | E10: Bengali closing | F10: The line elders look for | G10: "Sabandhabe upasthit theke nabadampatike ashirbad kore badhito korben." Please come with your loved ones and bless the newlyweds. | H10: EV-E01_B | I10: Posts/003_2026-10-08_Carousel_E01_Bengali-biyer-card-wording-guide/slide_03.jpg
A11: 3 | B11: 46303 | C11: E01 | D11: 4 | E11: In English | F11: From the bride's parents | G11: "Mr and Mrs Subhash Ghosh request the pleasure of your company at the wedding of their daughter Rimi with Arnab, son of Mr and Mrs Partha Sen." | H11: — (text card) | I11: Posts/003_2026-10-08_Carousel_E01_Bengali-biyer-card-wording-guide/slide_04.jpg
A12: 3 | B12: 46303 | C12: E01 | D12: 5 | E12: Function list | F12: Give each ceremony a line | G12: • Ashirbaad: date, time, venue • Gaye Holud: close family • Biye: the main evening • Bou Bhaat: hosted by the groom's family, often its own invite | H12: — (text card) | I12: Posts/003_2026-10-08_Carousel_E01_Bengali-biyer-card-wording-guide/slide_05.jpg
A13: 3 | B13: 46303 | C13: E01 | D13: 6 | E13: With Lumhe | F13: Every ceremony, its own RSVP | G13: Upload your card, share one link and see live headcounts for Biye and Bou Bhaat separately. | H13: EV-E01_B | I13: Posts/003_2026-10-08_Carousel_E01_Bengali-biyer-card-wording-guide/slide_06.jpg
... A415: 195 | B415: 46399 | C415: C30 | D415: 6 | E415: Can't attend? | F415: Send shagun along with your wishes | G415: If the couple's Lumhe invite has Digital Lifafa, send shagun by UPI straight to them, and add photos to their Moments album. | H415: — (text card) | I415: Posts/195_2027-01-12_Carousel_C30_Wedding-day-wishes-for-everyone/slide_06.jpg

Sheet Reel scenes
A1: # | B1: Date | C1: Post ID | D1: Scene | E1: On-screen text | F1: Sub text | G1: Image | H1: Audio suggestion
A2: 5 | B2: 46304 | C2: E21 | D2: 1 | E2: Shaadi in Pune. Family in Toronto. | F2: And no good hour for a single phone call. | G2: EV-E21_A | H2: Soft lo-fi beat with a gentle flute or sitar line that lifts into an upbeat dhol groove on the CTA.
A3: 5 | B3: 46304 | C3: E21 | D3: 2 | E3: Three aunts. Three different guest lists. | F3: Each one sure she's the main coordinator. | G3: EV-E21_B
A4: 5 | B4: 46304 | C4: E21 | D4: 3 | E4: The spreadsheet hadn't moved in months | F4: Updated whenever someone remembered. So, never. | G4: EV-E21_A
A5: 5 | B5: 46304 | C5: E21 | D5: 4 | E5: One link, shared from any time zone | F5: Card, functions and venue details, sent once on WhatsApp. | G5: EV-E21_B
A6: 5 | B6: 46304 | C6: E21 | D6: 5 | E6: RSVPs land while you sleep | F6: Wake up to live headcounts for Haldi, Sangeet and Reception. | G6: EV-E21_A
A7: 5 | B7: 46304 | C7: E21 | D7: 6 | E7: Plan from anywhere. Celebrate together. | F7: Create your event free at lumhe.com | G7: — (end card)
A8: 7 | B8: 46305 | C8: F02 | D8: 1 | E8: Garba starts tomorrow. Invite sent? | F8: Not the forward. The actual invite. | G8: PAIR-NAV_A | H8: Upbeat dhol-and-dandiya folk fusion with a fast build, clapping on every scene change.
A9: 7 | B9: 46305 | C9: F02 | D9: 2 | E9: Thali ready. Diya ready. | F9: Guest list? Still split across three chats. | G9: PAIR-NAV_B
A10: 7 | B10: 46305 | C10: F02 | D10: 3 | E10: Send one link tonight | F10: Every Garba night gets its own RSVP. | G10: PAIR-NAV_A
A11: 7 | B11: 46305 | C11: F02 | D11: 4 | E11: Know who's coming each night | F11: Live headcount, so snacks last past 9. | G11: PAIR-NAV_B
A12: 7 | B12: 46305 | C12: F02 | D12: 5 | E12: Every twirl in one album | F12: Guests upload to Moments in full quality. | G12: PAIR-NAV_A
A13: 7 | B13: 46305 | C13: F02 | D13: 6 | E13: Nine nights. One link. | F13: Create your Navratri invite free at lumhe.com | G13: — (end card)
A14: 21 | B14: 46312 | C14: E34 | D14: 1 | E14: The theme starts at the invite | F14: Not at the front door. | G14: EV-E34_A | H14: Bright, bouncy ukulele-pop track with handclaps; quick cuts on each beat.
A15: 21 | B15: 46312 | C15: E34 | D15: 2 | E15: Tea party? Pinkies up. | F15: "A tea-riffic afternoon awaits. Hats encouraged." | G15: EV-E34_B
A16: 21 | B16: 46312 | C16: E34 | D16: 3 | E16: Dinosaur bash? Let it roar. | F16: "Stomp on over! Max is turning five." | G16: EV-E34_A
A17: 21 | B17: 46312 | C17: E34 | D17: 4 | E17: Tell guests what to wear | F17: Costumes, sun hats or swimsuits: one line ends the guessing. | G17: EV-E34_B
A18: 21 | B18: 46312 | C18: E34 | D18: 5 | E18: Count cupcakes before Saturday | F18: Live RSVPs show who's coming, kids and adults. | G18: EV-E34_A
A19: 21 | B19: 46312 | C19: E34 | D19: 6 | E19: Theme it. Link it. Send it. | F19: Create your party invite free at lumhe.com | G19: — (end card)
A20: 34 | B20: 46318 | C20: E52 | D20: 1 | E20: Dinosaurs, unicorns and twenty-two Year 2s | F20: The invite decides how smoothly Saturday goes. | G20: EV-E52_A | H20: Bouncy, playful ukulele-and-claps kids' party track with a cheeky drum hit on each cut.
A21: 34 | B21: 46318 | C21: E52 | D21: 2 | E21: Theme the wording, too | F21: Roar-some for dinos, sparkly for princesses, capes for superheroes. | G21: — (end card)
A22: 34 | B22: 46318 | C22: E52 | D22: 3 | E22: Say: stay or drop-off? | F22: Under-fives: parents stay. Older kids: give a pick-up time. | G22: EV-E52_A
A23: 34 | B23: 46318 | C23: E52 | D23: 4 | E23: Ask about allergies | F23: One line on the invite saves a panic at cake time. | G23: — (end card)
A24: 34 | B24: 46318 | C24: E52 | D24: 5 | E24: Know who's coming by Wednesday | F24: Set an RSVP date a few days before the party. | G24: EV-E52_A
A25: 34 | B25: 46318 | C25: E52 | D25: 6 | E25: One link for the class chat | F25: Free on Lumhe. Parents reply without an app. | G25: — (end card)
A26: 43 | B26: 46323 | C26: F08 | D26: 1 | E26: Moonrise tomorrow. Sieve ready? | F26: Sargi sorted. Thali sorted. Guests? | G26: PAIR-KC_A | H26: Soft, romantic folk-pop with dholak and a gentle build, warm and devotional rather than clubby.
A27: 43 | B27: 46323 | C27: F08 | D27: 2 | E27: Karva, diya, channi: checked | F27: One thing is still missing. | G27: PAIR-KC_B
A28: 43 | B28: 46323 | C28: F08 | D28: 3 | E28: Your friends still need the plan | F28: Katha where? Whose terrace? Dinner after? | G28: PAIR-KC_A
A29: 43 | B29: 46323 | C29: F08 | D29: 4 | E29: Send one link tonight | F29: Mehendi, katha and moonrise, each with RSVP. | G29: PAIR-KC_B
A30: 43 | B30: 46323 | C30: F08 | D30: 5 | E30: Every moon photo, one album | F30: Guests upload to Moments. Full quality, no expiry. | G30: PAIR-KC_A
A31: 43 | B31: 46323 | C31: F08 | D31: 6 | E31: One link till the moon | F31: Make your invite free at lumhe.com | G31: — (end card)
A32: 48 | B32: 46325 | C32: R02 | D32: 1 | E32: Halloween is Saturday. Invites aren't out. | F32: Don't panic. Ghosts work fast. | G32: US-72 | H32: Playful spooky synth or theremin-style trending audio with a bouncy beat; campy, not horror.
A33: 48 | B33: 46325 | C33: R02 | D33: 2 | E33: Drop in your spooky design | F33: Canva, PDF, image or video, any invite works | G33: US-50
A34: 48 | B34: 46325 | C34: R02 | D34: 3 | E34: Add the scary-important details | F34: Costume rules, 7 PM start, candy-bucket policy | G34: US-72
A35: 48 | B35: 46325 | C35: R02 | D35: 4 | E35: Text one link to everyone | F35: Guests RSVP in a tap. No app, no login. | G35: US-50
A36: 48 | B36: 46325 | C36: R02 | D36: 5 | E36: Watch the headcount climb live | F36: Buy candy for 23, not 'a lot' | G36: US-72
A37: 48 | B37: 46325 | C37: R02 | D37: 6 | E37: Create your invite free | F37: lumhe.com, link in bio | G37: — (end card)
A38: 52 | B38: 46327 | C38: E56 | D38: 1 | E38: Sent 80 invites. Got 6 replies. | F38: Sound familiar? Here's the fix. | G38: EV-E56_A | H38: Upbeat lo-fi pop beat with a satisfying click or pop sound on each step reveal.
A39: 52 | B39: 46327 | C39: E56 | D39: 2 | E39: Step 1: upload your design | F39: Canva, PDF, photo or video. Or design one. | G39: EV-E56_B
A40: 52 | B40: 46327 | C40: E56 | D40: 3 | E40: Step 2: add your events | F40: Ceremony, dinner, after-party. Guests see only theirs. | G40: EV-E56_A
A41: 52 | B41: 46327 | C41: E56 | D41: 4 | E41: Step 3: share one link | F41: WhatsApp, text or email. No app to download. | G41: EV-E56_B
A42: 52 | B42: 46327 | C42: E56 | D42: 5 | E42: Step 4: watch the headcount | F42: Live RSVPs for every event, in one place. | G42: EV-E56_A
A43: 52 | B43: 46327 | C43: E56 | D43: 6 | E43: Free on Lumhe | F43: Send your first invite at lumhe.com | G43: — (end card)
A44: 63 | B44: 46333 | C44: R03 | D44: 1 | E44: 'Sab aa rahe hain na?' asks Dadi | F44: The only Diwali question that matters | G44: IN-5 | H44: Warm festive Indian instrumental with light dhol and shehnai, building to a joyful beat drop.
A45: 63 | B45: 46333 | C45: R03 | D45: 2 | E45: Mausi, bua, cousins: everyone's invited | F45: One invite link in the family WhatsApp group | G45: UK-65
A46: 63 | B46: 46333 | C46: R03 | D46: 3 | E46: Each family taps yes | F46: No app, no login. Even Nanaji manages. | G46: IN-5
A47: 63 | B47: 46333 | C47: R03 | D47: 4 | E47: Live headcount for the mithai order | F47: Kaju katli for 34, not 'andaaz se' | G47: UK-65
A48: 63 | B48: 46333 | C48: R03 | D48: 5 | E48: Every phone's photos, one album | F48: Moments keeps the rangoli and diya pics forever | G48: IN-5
A49: 63 | B49: 46333 | C49: R03 | D49: 6 | E49: Is baar Diwali, ek link | F49: Create your invite free on lumhe.com | G49: — (end card)
A50: 67 | B50: 46335 | C50: E22 | D50: 1 | E50: Your side of the list: 400 | F50: Papa's business friends included. Obviously. | G50: EV-E22_A | H50: Wry, plucky comedic beat that switches to a high-energy Punjabi dhol track at scene 4.
A51: 67 | B51: 46335 | C51: E22 | D51: 2 | E51: Five functions. Five different lists. | F51: Haldi, Mehendi, Sangeet, pheras, Reception. | G51: EV-E22_B
A52: 67 | B52: 46335 | C52: E22 | D52: 3 | E52: The spreadsheet survives two weeks | F52: Then Papa starts his own version. | G52: EV-E22_A
A53: 67 | B53: 46335 | C53: E22 | D53: 4 | E53: So switch to one link | F53: Each guest sees only the functions they're invited to. | G53: EV-E22_B
A54: 67 | B54: 46335 | C54: E22 | D54: 5 | E54: Headcounts update themselves | F54: Confirmed, pending, declined: per function, in real time. | G54: EV-E22_A
A55: 67 | B55: 46335 | C55: E22 | D55: 6 | E55: Less chasing. More baraat. | F55: Plan your guest list free at lumhe.com | G55: — (end card)
A56: 68 | B56: 46335 | C56: F19 | D56: 1 | E56: Bhai Dooj is tomorrow. Thali ready? | F56: Check it tonight, not during the morning rush | G56: UK-64 | H56: Soft, nostalgic Indian acoustic track with flute and light tabla that lifts into a warm, playful beat for the closing scenes.
A57: 68 | B57: 46335 | C57: F19 | D57: 2 | E57: Roli, chawal, diya, mithai | F57: And his favourite sweet, not just the box one | G57: — (end card)
A58: 68 | B58: 46335 | C58: F19 | D58: 3 | E58: Bhai in another city? | F58: Agree on the video-call time tonight | G58: UK-64
A59: 68 | B59: 46335 | C59: F19 | D59: 4 | E59: Shagun still arrives on time | F59: Digital Lifafa: UPI straight to her, Lumhe never touches it | G59: — (end card)
A60: 68 | B60: 46335 | C60: F19 | D60: 5 | E60: Every tilak photo, one album | F60: Moments keeps them in full quality | G60: UK-64
A61: 68 | B61: 46335 | C61: F19 | D61: 6 | E61: Tilak tomorrow. Invite tonight. | F61: Create yours free on lumhe.com | G61: — (end card)
A62: 87 | B62: 46345 | C62: F25 | D62: 1 | E62: Ekadashi tomorrow. Shaadi season next. | F62: Tulsi Vivah first, then the wedding calendar fills up | G62: PAIR-DEV_A | H62: Gentle shehnai and soft temple-bell intro that rolls into an upbeat, festive wedding dhol groove.
A63: 87 | B63: 46345 | C63: F25 | D63: 2 | E63: Shaadi dates finally fixed? | F63: Every function, Haldi to Reception, on one link | G63: PAIR-DEV_B
A64: 87 | B64: 46345 | C64: F25 | D64: 3 | E64: Neighbours invited for the aarti? | F64: One link beats knocking on every door | G64: PAIR-DEV_A
A65: 87 | B65: 46345 | C65: F25 | D65: 4 | E65: Guests see only their functions | F65: Live headcount for each one | G65: PAIR-DEV_B
A66: 87 | B66: 46345 | C66: F25 | D66: 5 | E66: Shagun by Digital Lifafa | F66: UPI to your account. Lumhe never touches it. | G66: PAIR-DEV_A
A67: 87 | B67: 46345 | C67: F25 | D67: 6 | E67: Shubh vivah season begins | F67: Create your invite free on lumhe.com | G67: — (end card)
A68: 88 | B68: 46345 | C68: E41 | D68: 1 | E68: First dance. Filmed from twelve angles. | F68: And you've seen exactly one of them. | G68: EV-E41_A | H68: Warm, nostalgic acoustic pop with soft strings that swells into a joyful chorus on the reveal.
A69: 88 | B69: 46345 | C69: E41 | D69: 2 | E69: Your aunt has the tearful toast | F69: Still on her phone. Three months later. | G69: EV-E41_B
A70: 88 | B70: 46345 | C70: E41 | D70: 3 | E70: Your roommate caught the sparkler exit | F70: Posted to Stories. Gone in 24 hours. | G70: EV-E41_A
A71: 88 | B71: 46345 | C71: E41 | D71: 4 | E71: One link. One shared album. | F71: Guests upload full-quality photos from your invite link. | G71: EV-E41_B
A72: 88 | B72: 46345 | C72: E41 | D72: 5 | E72: Nothing expires. Nothing gets squashed. | F72: No app, no login. Just tap and upload. | G72: EV-E41_A
A73: 88 | B73: 46345 | C73: E41 | D73: 6 | E73: Moments, free on Lumhe | F73: Start your album at lumhe.com | G73: — (end card)
A74: 100 | B74: 46351 | C74: R09 | D74: 1 | E74: Four pies. Zero stuffing. | F74: Every potluck without a plan | G74: US-6 | H74: Cozy upbeat indie-folk with acoustic guitar and hand claps, warm autumn energy, light enough to let the text land.
A75: 100 | B75: 46351 | C75: R09 | D75: 2 | E75: Put dish categories on the invite | F75: Mains, sides, desserts, drinks | G75: US-39
A76: 100 | B76: 46351 | C76: R09 | D76: 3 | E76: Split by last name | F76: A to M bring sides, N to Z bring dessert | G76: US-6
A77: 100 | B77: 46351 | C77: R09 | D77: 4 | E77: RSVPs tell you the headcount | F77: Enough chairs, right-sized turkey | G77: US-39
A78: 100 | B78: 46351 | C78: R09 | D78: 5 | E78: Photos land in one album | F78: Not buried in the group chat | G78: US-6
A79: 100 | B79: 46351 | C79: R09 | D79: 6 | E79: Host Friendsgiving the easy way | F79: Free invite and RSVP on Lumhe | G79: — (end card)
A80: 102 | B80: 46352 | C80: R05 | D80: 1 | E80: How many goody bags, exactly? | F80: Every party parent, the night before | G80: UK-13 | H80: Bouncy, playful kids-party pop with a clap beat; light and cheerful, cuts on each scene change.
A81: 102 | B81: 46352 | C81: R05 | D81: 2 | E81: One link in the class WhatsApp | F81: Dinosaur theme, date, drop-off and pick-up times | G81: UK-4
A82: 102 | B82: 46352 | C82: R05 | D82: 3 | E82: Parents tap yes, no or maybe | F82: No app, no login, no lost paper slips | G82: UK-13
A83: 102 | B83: 46352 | C83: R05 | D83: 4 | E83: Live headcount, updated as replies land | F83: Order cake for fourteen, not 'about twenty' | G83: UK-4
A84: 102 | B84: 46352 | C84: R05 | D84: 5 | E84: Every parent's photos, one album | F84: Moments keeps the candle-blowing shots forever | G84: UK-13
A85: 102 | B85: 46352 | C85: R05 | D85: 6 | E85: Party sorted. One link. | F85: Create your invite free at lumhe.com | G85: — (end card)
A86: 111 | B86: 46357 | C86: R06 | D86: 1 | E86: Envelopes. Stamps. Lost RSVP cards. | F86: The old way had a lot of steps | G86: US-4 | H86: Upbeat transformation-style trending audio with a satisfying beat drop at the switch from envelopes to screens.
A87: 111 | B87: 46357 | C87: R06 | D87: 2 | E87: Or upload the design you love | F87: Canva, PDF, image or video invite | G87: UK-11
A88: 111 | B88: 46357 | C88: R06 | D88: 3 | E88: Add every function, once | F88: Guests see only the events they're invited to | G88: US-4
A89: 111 | B89: 46357 | C89: R06 | D89: 4 | E89: Share one link anywhere | F89: WhatsApp, SMS or email. No app, no login. | G89: UK-11
A90: 111 | B90: 46357 | C90: R06 | D90: 5 | E90: RSVPs counted live, per event | F90: No spreadsheet, no chasing replies | G90: US-4
A91: 111 | B91: 46357 | C91: R06 | D91: 6 | E91: Make the Lumhe switch | F91: Create your invite free at lumhe.com | G91: — (end card)
A92: 115 | B92: 46359 | C92: F32 | D92: 1 | E92: Candle one. Tomorrow. Sundown. | F92: Hanukkah starts Friday evening. | G92: PAIR-HAN_A | H92: Warm, upbeat acoustic folk track with handclaps and a gentle build, cosy rather than loud.
A93: 115 | B93: 46359 | C93: F32 | D93: 2 | E93: Latkes for how many? | F93: Ask for headcounts, not maybes. | G93: PAIR-HAN_B
A94: 115 | B94: 46359 | C94: F32 | D94: 3 | E94: One link to the family chat | F94: No app, no login for guests. | G94: PAIR-HAN_A
A95: 115 | B95: 46359 | C95: F32 | D95: 4 | E95: Fry ahead, crisp later | F95: Dreidels and gelt on the table. | G95: PAIR-HAN_B
A96: 115 | B96: 46359 | C96: F32 | D96: 5 | E96: Eight nights of glow, saved | F96: Everyone adds photos to one Moments album. | G96: PAIR-HAN_A
A97: 115 | B97: 46359 | C97: F32 | D97: 6 | E97: Light it up together | F97: Create your invite free at lumhe.com | G97: — (end card)
A98: 116 | B98: 46359 | C98: R10 | D98: 1 | E98: December grads deserve a party too | F98: Semester done. Cap thrown. Cake pending. | G98: RU-8 | H98: Bright, upbeat feel-good pop with a hand-clap beat and a big lift at the photo-album reveal.
A99: 116 | B99: 46359 | C99: R10 | D99: 2 | E99: One link, sent by text | F99: Guests open it. No app, no login. | G99: US-66
A100: 116 | B100: 46359 | C100: R10 | D100: 3 | E100: RSVPs roll in live | F100: Now you know how many cupcakes to order. | G100: RU-8
...

Sheet Image usage log
A1: Image code | B1: Blog title | C1: Market | D1: Status | E1: Used in post | F1: Post date | G1: Format | H1: Note
A2: AB-7 | B2: How to Send Digital Wedding Invitations in the UK — Day & Evening Guest Guide | C2: UK | D2: Used | E2: S01 | F2: 46347 | G2: Single
A3: BR-15 | B3: How to Design Your Wedding Invitations on Canva — A UK Guide to Going Digital | C3: UK | D3: Used | E3: S02 | F3: 46353 | G3: Single
A4: IN-2 | B4: Happy 30Th Wedding Anniversary: Complete Guide | C4: India | D4: Used | E4: C09 | F4: 46379 | G4: Carousel
A5: IN-3 | B5: Happy Wedding Anniversary To Us: Complete Guide | C5: India | D5: Used | E5: C10 | F5: 46384 | G5: Carousel
A6: IN-4 | B6: Hindu Wedding Card Matter In English For Daughter: Complete Guide | C6: India | D6: Used | E6: C08 | F6: 46376 | G6: Carousel
A7: IN-5 | B7: Wedding Anniversary Wishes: Heartfelt Messages | C7: India | D7: Used | E7: F18 | F7: 46324 | G7: Carousel
A8: IN-6 | B8: Wedding Invitation In Whatsapp Style: Complete Guide | C8: India | D8: Used | E8: C28 | F8: 46396 | G8: Carousel
A9: IN-7 | B9: How To Create A Wedding Invitation Video: Complete Guide | C9: India | D9: Used | E9: C29 | F9: 46398 | G9: Carousel
A10: IN-8 | B10: Hashtag For Pre Wedding: Best Ideas for Social Media | C10: India | D10: Used | E10: R07 | F10: 46374 | G10: Reel
A11: IN-15 | B11: Happy Wedding Anniversary In Marathi: Complete Guide | C11: India | D11: Used | E11: S03 | F11: 46367 | G11: Single
A12: IN-16 | B12: Wedding Anniversary Quotes: Beautiful Messages for Every Year | C12: India | D12: Used | E12: S04 | F12: 46370 | G12: Single
A13: IN-17 | B13: Wedding Instagram Captions: Best Ideas for Social Media | C13: India | D13: Used | E13: C11 | F13: 46388 | G13: Carousel
... A18: IN-25 | B18: Caption For New Wedding Couple: Best Ideas for Social Media | C18: India | D18: Used | E18: R12 | F18: 46397 | G18: Reel
A19: IN-28 | B19: Wedding Cards Near Me: Complete Guide | C19: India | D19: Skipped (duplicate) | H19: Identical artwork to IN-17, which is used in C11
A20: IN-32 | B20: Happy Wedding Anniversary Both Of You: Complete Guide | C20: India | D20: Used | E20: R01 | F20: 46364 | G20: Reel
A21: IN-33 | B21: Happy Wedding Anniversary Png: Complete Guide | C21: India | D21: Used | E21: C29 | F21: 46398 | G21: Carousel
A22: IN-34 | B22: Wish You Happy Wedding Anniversary: Complete Guide | C22: India | D22: Used | E22: C10 | F22: 46384 | G22: Carousel
A23: IN-36 | B23: Happy Wedding Anniversary Background: Complete Guide | C23: India | D23: Skipped (duplicate) | H23: Identical artwork to IN-24, which is used in C08
A24: IN-37 | B24: Create Indian Wedding Invitation Card Online Free For Whatsapp: Complete Guide | C24: India | D24: Used | E24: C28 | F24: 46396 | G24: Carousel
A25: IN-38 | B25: Wedding Anniversary Images Download: Complete Guide | C25: India | D25: Used | E25: C09 | F25: 46379 | G25: Carousel
A26: IN-42 | B26: Happy Wedding Day Wishes: Heartfelt Messages & Quotes | C26: India | D26: Used | E26: C30 | F26: 46399 | G26: Carousel
A27: IN-43 | B27: Happy Wedding Anniversary To Both Of You: Complete Guide | C27: India | D27: Used | E27: C18 | F27: 46339 | G27: Carousel
A28: IN-45 | B28: Wishes For Newly Wed Couple: Heartfelt Messages & Quotes | C28: India | D28: Used | E28: F37 | F28: 46390 | G28: Carousel
A29: IN-46 | B29: Friends Wedding Quotes: Complete Guide | C29: India | D29: Used | E29: C30 | F29: 46399 | G29: Carousel
A30: IN-52 | B30: Happy Wedding Anniversary PNG | C30: India | D30: Used | E30: S06 | F30: 46346 | G30: Single
A31: RU-3 | B31: 10 Beautiful Mehendi Invitation Designs — Free Templates to Download & Share | C31: India | D31: Used | E31: C13 | F31: 46338 | G31: Carousel
A32: RU-5 | B32: 8 Elegant Engagement Invitation Templates — Free Downloads for Indian Ceremonies | C32: India | D32: Used | E32: C15 | F32: 46395 | G32: Carousel
A33: RU-6 | B33: 10 Best Sangeet Night Invitation Templates — Download Free & Send Digitally | C33: India | D33: Used | E33: C14 | F33: 46392 | G33: Carousel
A34: RU-8 | B34: 8 Kitty Party Invitation Templates That Will Impress Your Group — Free & Ready | C34: India | D34: Used | E34: R10 | F34: 46359 | G34: Reel
A35: RU-9 | B35: 15 Best Free Wedding Invitation Templates in 2026 — Download & Customize | C35: USA | D35: Skipped (duplicate) | H35: Identical artwork to BR-15, which is used in S02
A36: RU-10 | B36: 10 Adorable Baby Shower Invitation Templates — Free Downloads + Digital Sending | C36: USA | D36: Used | E36: S07 | F36: 46354 | G36: Single
A37: RU-11 | B37: 10 Best Graduation Party Invitation Templates — Free, Customizable & Ready | C37: USA | D37: Used | E37: S08 | F37: 46373 | G37: Single
A38: RU-12 | B38: 8 Elegant Bridal Shower Invitation Templates — Free Downloads + Digital Sending | C38: USA | D38: Used | E38: C27 | F38: 46385 | G38: Carousel
A39: RU-13 | B39: 10 Beautiful Wedding Invitation Templates for UK Couples — Free Downloads | C39: UK | D39: Used | E39: S09 | F39: 46355 | G39: Single
A40: RU-14 | B40: 8 Gorgeous Christening Invitation Templates — Free to Download & Customise | C40: UK | D40: Used | E40: C17 | F40: 46355 | G40: Carousel
A41: UK-2 | B41: Evening Wedding Invitations: Wording & Etiquette (UK) | C41: UK | D41: Used | E41: R13 | F41: 46381 | G41: Reel
A42: UK-3 | B42: Evening Wedding Invitations: Wording & Etiquette (UK) | C42: UK | D42: Used | E42: C19 | F42: 46361 | G42: Carousel
A43: UK-4 | B43: Evening Wedding Invitations: Wording & Etiquette (UK) | C43: UK | D43: Used | E43: R05 | F43: 46352 | G43: Reel
A44: UK-5 | B44: Sixty Birthday Party: Complete Guide | C44: UK | D44: Used | E44: S22 | F44: 46374 | G44: Single
A45: UK-9 | B45: Engagement Party Invitations: Wording & Design Ideas | C45: UK | D45: Used | E45: C33 | F45: 46368 | G45: Carousel
A46: UK-11 | B46: Halloween Party Invitations: Spooky Wording & Ideas | C46: UK | D46: Used | E46: R06 | F46: 46357 | G46: Reel
A47: UK-12 | B47: 40Th Birthday Invitations: Wording & Creative Ideas | C47: UK | D47: Used | E47: S10 | F47: 46358 | G47: Single
... A65: UK-38 | B65: Invitation Print: Complete Guide | C65: UK | D65: Used | E65: S18 | F65: 46382 | G65: Single
A66: UK-39 | B66: Printed Wedding Invitations: Complete Guide | C66: UK | D66: Skipped (duplicate) | H66: Identical artwork to UK-29, which is used in C26
A67: UK-41 | B67: Baby Shower Invitations: Wording, Ideas & Etiquette | C67: UK | D67: Skipped (duplicate) | H67: Identical artwork to UK-11, which is used in R06
A68: UK-42 | B68: Birthday Online Invite: Complete Guide | C68: UK | D68: Used | E68: S19 | F68: 46383 | G68: Single
A69: UK-43 | B69: Einvite: Complete Guide | C69: UK | D69: Used | E69: S20 | F69: 46385 | G69: Single
A70: UK-44 | B70: Party Invitations: Complete Guide | C70: UK | D70: Used | E70: C25 | F70: 46367 | G70: Carousel
A71: UK-46 | B71: Personalised Wedding Invitations: Complete Guide | C71: UK | D71: Skipped (duplicate) | H71: Identical artwork to IN-15, which is used in S03
A72: UK-47 | B72: Party Template Invite: Complete Guide | C72: UK | D72: Skipped (duplicate) | H72: Identical artwork to IN-6, which is used in C28
A73: UK-48 | B73: Free Bridal Websites: Complete Guide | C73: UK | D73: Used | E73: S21 | F73: 46389 | G73: Single
A74: UK-49 | B74: Cards And Invitations: Complete Guide | C74: UK | D74: Used | E74: R07 | F74: 46374 | G74: Reel
A75: UK-51 | B75: Party Invite Template: Complete Guide | C75: UK | D75: Skipped (duplicate) | H75: Identical artwork to UK-21, which is used in C24
A76: UK-52 | B76: Wedding Invitations UK: Best Options & Ideas | C76: UK | D76: Used | E76: R08 | F76: 46386 | G76: Reel
A77: UK-53 | B77: Save the Date Cards: When to Send, Wording & Ideas | C77: UK | D77: Used | E77: C06 | F77: 46337 | G77: Carousel
A78: UK-54 | B78: Wedding Card Printing: Complete Guide | C78: UK | D78: Used | E78: S23 | F78: 46391 | G78: Single
A79: UK-55 | B79: Templates For Party Invites: Complete Guide | C79: UK | D79: Used | E79: S24 | F79: 46334 | G79: Single
A80: UK-56 | B80: What Is A Rsvp On An Invitation: Complete Guide | C80: UK | D80: Skipped (duplicate) | H80: Identical artwork to IN-15, which is used in S03
A81: UK-57 | B81: Wedding Invitation Templates: Complete Guide | C81: UK | D81: Skipped (duplicate) | H81: Identical artwork to IN-38, which is used in C09
A82: UK-58 | B82: Online Wedding Invitation: Complete Guide | C82: UK | D82: Skipped (duplicate) | H82: Identical artwork to UK-48, which is used in S21
A83: UK-59 | B83: Make Your Own Wedding Invitations: Complete Guide | C83: UK | D83: Used | E83: S25 | F83: 46394 | G83: Single
A84: UK-61 | B84: Online Party Invitations: Complete Guide | C84: UK | D84: Skipped (duplicate) | H84: Identical artwork to UK-21, which is used in C24
A85: UK-62 | B85: Invited: Complete Guide | C85: UK | D85: Used | E85: S26 | F85: 46395 | G85: Single
A86: UK-63 | B86: Invitation Card Design: Complete Guide | C86: UK | D86: Used | E86: C15 | F86: 46395 | G86: Carousel
A87: UK-64 | B87: Meaning Of Rsvp In Invitation: Complete Guide | C87: UK | D87: Used | E87: C35 | F87: 46326 | G87: Carousel
A88: UK-65 | B88: Invitation Template: Complete Guide | C88: UK | D88: Used | E88: F18 | F88: 46324 | G88: Carousel
A89: UK-66 | B89: Create An Invitation: Complete Guide | C89: UK | D89: Used | E89: S27 | F89: 46397 | G89: Single
A90: UK-68 | B90: What Does RSVP Mean? Complete Guide to RSVP Etiquette | C90: UK | D90: Used | E90: C04 | F90: 46323 | G90: Carousel
A91: UK-69 | B91: Free Invite Templates: Complete Guide | C91: UK | D91: Used | E91: S28 | F91: 46398 | G91: Single
A92: UK-70 | B92: Rsvp Full Form: Complete Guide | C92: UK | D92: Used | E92: S29 | F92: 46401 | G92: Single
A93: UK-72 | B93: Create A Wedding Website: Complete Guide | C93: UK | D93: Used | E93: C23 | F93: 46348 | G93: Carousel
A94: US-1 | B94: What Should Be Included In A Wedding Invitation | C94: USA | D94: Used | E94: C01 | F94: 46353 | G94: Carousel
A95: US-2 | B95: Stationery Wedding Invites Complete Guide | C95: USA | D95: Used | E95: C26 | F95: 46356 | G95: Carousel
A96: US-3 | B96: Printed Wedding Invitations Complete Guide | C96: USA | D96: Skipped (duplicate) | H96: Identical artwork to US-13, which is used in R11
A97: US-4 | B97: Wedding Shower Invitations: Wording, Etiquette & Ideas (2026) | C97: USA | D97: Used | E97: R06 | F97: 46357 | G97: Reel
A98: US-5 | B98: Personalised Wedding Invitations Complete Guide | C98: USA | D98: Used | E98: C02 | F98: 46360 | G98: Carousel
A99: US-6 | B99: Gender Reveal Party Invitations: Wording, Ideas & Free Templates | C99: USA | D99: Used | E99: F29 | F99: 46342 | G99: Carousel
A100: US-7 | B100: Wedding Invitation Suites | C100: USA | D100: Skipped (duplicate) | H100: Identical artwork to UK-23, which is used in C25
A101: US-8 | B101: Print Invitations Complete Guide | C101: USA | D101: Used | E101: F35 | F101: 46377 | G101: Carousel
A102: US-9 | B102: Another Word For Invite: Complete Guide | C102: USA | D102: Used | E102: S50 | F102: 46396 | G102: Single
A103: US-10 | B103: Best Wedding Websites: Complete Guide | C103: USA | D103: Used | E103: C23 | F103: 46348 | G103: Carousel
A104: US-11 | B104: Jeff Bezos Wedding Invite: Complete Guide | C104: USA | D104: Used | E104: S30 | F104: 46357 | G104: Single
A105: US-12 | B105: Printable Party Invitations Complete Guide | C105: USA | D105: Used | E105: C20 | F105: 46371 | G105: Carousel
A106: US-13 | B106: Create A Wedding Website: Complete Guide | C106: USA | D106: Used | E106: R11 | F106: 46369 | G106: Reel
A107: US-14 | B107: Wedding Invitation Wording Examples: 50+ Samples for Every Style | C107: USA | D107: Used | E107: S31 | F107: 46362 | G107: Single
A108: US-15 | B108: Wedding Invitations Cheap | C108: USA | D108: Used | E108: C24 | F108: 46310 | G108: Carousel
A109: US-16 | B109: Create Your Own Wedding Invitations: Complete Guide | C109: USA | D109: Used | E109: S32 | F109: 46309 | G109: Single
A110: US-17 | B110: Elegant Wedding Invitations | C110: USA | D110: Used | E110: S33 | F110: 46365 | G110: Single
A111: US-18 | B111: Wedding Invites Cheap | C111: USA | D111: Used | E111: S34 | F111: 46368 | G111: Single
A112: US-21 | B112: Wedding Invitation Templates | C112: USA | D112: Used | E112: S35 | F112: 46303 | G112: Single
... A114: US-23 | B114: When Do You Send Out Wedding Invitations? The Complete Timeline | C114: USA | D114: Used | E114: R14 | F114: 46393 | G114: Reel
A115: US-29 | B115: Invitation Template Guide | C115: USA | D115: Skipped (duplicate) | H115: Identical artwork to US-18, which is used in S34
A116: US-30 | B116: Retirement Party Invitations Wording Ideas | C116: USA | D116: Used | E116: C22 | F116: 46382 | G116: Carousel
A117: US-34 | B117: Paperless Post Invitations Guide | C117: USA | D117: Used | E117: S36 | F117: 46388 | G117: Single
A118: US-35 | B118: Party Invitations - Complete Guide | C118: USA | D118: Used | E118: C12 | F118: 46327 | G118: Carousel
A119: US-37 | B119: Party Template Invite Guide | C119: USA | D119: Used | E119: S37 | F119: 46372 | G119: Single
A120: US-38 | B120: What Does RSVP Mean | C120: USA | D120: Used | E120: C04 | F120: 46323 | G120: Carousel
A121: US-39 | B121: Personalized Party Invites Guide | C121: USA | D121: Used | E121: F29 | F121: 46342 | G121: Carousel
A122: US-41 | B122: What Is A RSVP On An Invitation | C122: USA | D122: Used | E122: S38 | F122: 46375 | G122: Single
...

Sheet Festival coverage
A1: Festival | B1: Festival date | C1: Market | D1: ~10 days before | E1: Reminder (1-2 days) | F1: On the day | G1: Post IDs
A2: Sharad Navratri | B2: 46306 | C2: India | D2: 46302 | E2: 46305 | F2: 46306 | G2: F01 (T10), F02 (REM), F03 (DAY)
A3: Dussehra | B3: 46315 | C3: India | D3: 46305 | E3: 46314 | F3: 46315 | G3: F04 (T10), F05 (REM), F06 (DAY)
A4: Karva Chauth | B4: 46324 | C4: India | D4: 46314 | E4: 46323 | F4: 46324 | G4: F07 (T10), F08 (REM), F09 (DAY)
A5: Halloween | B5: 46326 | C5: USA | D5: 46316 | E5: 46325 | F5: 46326 | G5: F10 (T10), R02 (REM), F11 (DAY)
A6: Bonfire Night | B6: 46331 | C6: UK | D6: 46321 | E6: 46330 | F6: 46331 | G6: F12 (T10), F13 (REM), F14 (DAY)
A7: Dhanteras | B7: 46332 | C7: India | D7: 46322 | E7: 46331 | F7: 46332 | G7: F15 (T10), F16 (REM), F17 (DAY)
A8: Diwali | B8: 46334 | C8: India | D8: 46324 | E8: 46333 | F8: 46334 | G8: F18 (T10), R03 (REM), S24 (DAY)
A9: Bhai Dooj | B9: 46336 | C9: India | D9: 46326 | E9: 46335 | F9: 46336 | G9: C35 (T10), F19 (REM), F20 (DAY)
A10: Chhath Puja | B10: 46341 | C10: India | D10: 46330 | E10: 46340 | F10: 46341 | G10: F21 (T10), F22 (REM), F23 (DAY)
A11: Dev Uthani Ekadashi / wedding season opens | B11: 46346 | C11: India | D11: 46336 | E11: 46345 | F11: 46346 | G11: F24 (T10), F25 (REM), S06 (DAY)
A12: Guru Nanak Jayanti (Gurpurab) | B12: 46350 | C12: India | D12: 46340 | E12: 46349 | F12: 46350 | G12: F26 (T10), F27 (REM), F28 (DAY)
A13: Thanksgiving | B13: 46352 | C13: USA | D13: 46342 | E13: 46351 | F13: 46352 | G13: F29 (T10), R09 (REM), F30 (DAY)
... A18: Makar Sankranti / Pongal | B18: 46401 | C18: India | D18: 46391 | E18: 46400 | F18: 46401 | G18: F39 (T10), F40 (REM), F41 (DAY)
